Workbook

Sheet HYPOTHESES
A1: PRÉVISIONS FINANCIÈRES SUR 5 ANS : HYPOTHÈSES
A2: Référentiel : SYSCOHADA révisé (AUDCIF 2017) et CGI de Côte d'Ivoire. Montants en FCFA.
A3: Mode d'emploi : saisir uniquement les cellules sur fond JAUNE (texte bleu) de cet onglet et de l'onglet INVEST ET FINANCEMENT. Tout le reste (balances, bilan, compte de résultat, TFT) se recalcule automatiquement.
A4: Nom de l'entité | C4: MON ENTREPRISE
A5: Dernier exercice réel (année de base) | C5: 2024 | I5: Balance réelle reprise de l'onglet « 2025 » du fichier BALANCES_ET_PREVISIONS_TEST (soldes de clôture 31/12/2024).
A7: Rubrique | B7: Réf. / compte | C7: ="Réel "&$C$5 -> Réel 2024 | D7: =$C$5+1 -> 2025 | E7: =$C$5+2 -> 2026 | F7: =$C$5+3 -> 2027 | G7: =$C$5+4 -> 2028 | H7: =$C$5+5 -> 2029 | I7: Commentaire / source
A8: 1. ACTIVITÉ
A9: Taux de croissance du chiffre d'affaires | B9: % | D9: 0.07 | E9: 0.05 | F9: 0.05 | G9: 0.05 | H9: 0.05 | I9: Hypothèse à ajuster selon le carnet de commandes / marchés attendus.
A10: Taux de TVA | B10: % | D10: 0.18 | E10: 0.18 | F10: 0.18 | G10: 0.18 | H10: 0.18 | I10: CGI CI art. 359 : taux normal 18 %.
A11: Revenus financiers | B11: 77 | C11: =SUMIFS('BALANCE 2024'!$I:$I,'BALANCE 2024'!$C:$C,"TK") -> 848594 | D11: 848594 | E11: 848594 | F11: 848594 | G11: 848594 | H11: 848594 | I11: Défaut : niveau réel de l'année de base.
A12: 2. CHARGES D'EXPLOITATION EN % DU CHIFFRE D'AFFAIRES (clé de répartition)
A13: Achats et autres approvisionnements | B13: 604-605-608 | C13: =IF(SUMIFS('BALANCE 2024'!$I:$I,'BALANCE 2024'!$C:$C,"TC")=0,0,SUMIFS('BALANCE 2024'!$H:$H,'BALANCE 2024'!$C:$C,"RE")/SUMIFS('BALANCE 2024'!$I:$I,'BALANCE 2024'!$C:$C,"TC")) -> 0.39676301 | D13: 0.3968 | E13: 0.3968 | F13: 0.3968 | G13: 0.3968 | H13: 0.3968 | I13: Défaut : ratio réel de l'année de base. Chaque compte de détail est ensuite réparti selon sa part dans la balance de base.
A14: Transports | B14: 61 | C14: =IF(SUMIFS('BALANCE 2024'!$I:$I,'BALANCE 2024'!$C:$C,"TC")=0,0,SUMIFS('BALANCE 2024'!$H:$H,'BALANCE 2024'!$C:$C,"RG")/SUMIFS('BALANCE 2024'!$I:$I,'BALANCE 2024'!$C:$C,"TC")) -> 0.0054492903 | D14: 0.0054 | E14: 0.0054 | F14: 0.0054 | G14: 0.0054 | H14: 0.0054 | I14: Défaut : ratio réel de l'année de base. Chaque compte de détail est ensuite réparti selon sa part dans la balance de base.
A15: Services extérieurs | B15: 62-63 | C15: =IF(SUMIFS('BALANCE 2024'!$I:$I,'BALANCE 2024'!$C:$C,"TC")=0,0,SUMIFS('BALANCE 2024'!$H:$H,'BALANCE 2024'!$C:$C,"RH")/SUMIFS('BALANCE 2024'!$I:$I,'BALANCE 2024'!$C:$C,"TC")) -> 0.15230388 | D15: 0.1523 | E15: 0.1523 | F15: 0.1523 | G15: 0.1523 | H15: 0.1523 | I15: Défaut : ratio réel de l'année de base. Chaque compte de détail est ensuite réparti selon sa part dans la balance de base.
A16: Impôts et taxes | B16: 64 | C16: =IF(SUMIFS('BALANCE 2024'!$I:$I,'BALANCE 2024'!$C:$C,"TC")=0,0,SUMIFS('BALANCE 2024'!$H:$H,'BALANCE 2024'!$C:$C,"RI")/SUMIFS('BALANCE 2024'!$I:$I,'BALANCE 2024'!$C:$C,"TC")) -> 0.021211275 | D16: 0.0212 | E16: 0.0212 | F16: 0.0212 | G16: 0.0212 | H16: 0.0212 | I16: Défaut : ratio réel de l'année de base. Chaque compte de détail est ensuite réparti selon sa part dans la balance de base.
A17: Autres charges | B17: 65 | C17: =IF(SUMIFS('BALANCE 2024'!$I:$I,'BALANCE 2024'!$C:$C,"TC")=0,0,SUMIFS('BALANCE 2024'!$H:$H,'BALANCE 2024'!$C:$C,"RJ")/SUMIFS('BALANCE 2024'!$I:$I,'BALANCE 2024'!$C:$C,"TC")) -> 0.0018782894 | D17: 0.0019 | E17: 0.0019 | F17: 0.0019 | G17: 0.0019 | H17: 0.0019 | I17: Défaut : ratio réel de l'année de base. Chaque compte de détail est ensuite réparti selon sa part dans la balance de base.
A18: Charges de personnel | B18: 66 | C18: =IF(SUMIFS('BALANCE 2024'!$I:$I,'BALANCE 2024'!$C:$C,"TC")=0,0,SUMIFS('BALANCE 2024'!$H:$H,'BALANCE 2024'!$C:$C,"RK")/SUMIFS('BALANCE 2024'!$I:$I,'BALANCE 2024'!$C:$C,"TC")) -> 0.15124319 | D18: 0.1512 | E18: 0.1512 | F18: 0.1512 | G18: 0.1512 | H18: 0.1512 | I18: Défaut : ratio réel de l'année de base. Chaque compte de détail est ensuite réparti selon sa part dans la balance de base.
A19: 3. PROVISIONS
A20: Dotation aux provisions pour retraite (IFC) | B20: 691 / 196 | D20: 6059296 | E20: 6059296 | F20: 6059296 | G20: 6059296 | H20: 6059296 | I20: Défaut : dotation réelle de l'année de base.
A21: 4. BESOIN EN FONDS DE ROULEMENT
A22: Délai de paiement clients (jours de CA TTC) | B22: 411 | C22: =IF(C42=0,0,SUMIFS('BALANCE 2024'!$H:$H,'BALANCE 2024'!$C:$C,"BI")/(C42*(1+D10))*360) -> 196.82717 | D22: 190 | E22: 197 | F22: 197 | G22: 197 | H22: 197 | I22: Défaut : délai réel de l'année de base. Attention : délai légal max 60 j (AUDCG / directive UEMOA).
A23: Délai de paiement fournisseurs (jours d'achats et services TTC) | B23: 401 | C23: =IF(C49=0,0,SUMIFS('BALANCE 2024'!$I:$I,'BALANCE 2024'!$C:$C,"DJ")/(C49*(1+D10))*360) -> 57.251162 | D23: 57 | E23: 57 | F23: 57 | G23: 57 | H23: 57 | I23: Base : achats (60) + transports (61) + services extérieurs (62-63).
A24: Délai de paiement des fournisseurs d'investissement (jours d'acquisitions HT) | B24: 4812 | C24: =IF('INVEST ET FINANCEMENT'!C41=0,0,SUMIFS('BALANCE 2024'!$I:$I,'BALANCE 2024'!$C:$C,"DH")/'INVEST ET FINANCEMENT'!C41*360) -> 131.098 | D24: 131 | E24: 131 | F24: 131 | G24: 131 | H24: 131 | I24: Dette de l'année sur les acquisitions de l'année = acquisitions x délai / 360. Défaut : délai réel 2024 (132,9 M / 364,9 M d'acquisitions).
A25: Règlement de la dette fournisseurs d'investissement du 31/12 de base (% de l'encours) | B25: 4812 | D25: 0.6 | E25: 0.4 | F25: 0 | G25: 0 | H25: 0 | I25: Échéancier de l'encours 2024 (132,9 M) : non soldé en 2025. Le cumul ne doit pas dépasser 100 %.
A26: Encours de base restant dû au 31/12 | B26: 4812 | C26: =ROUND(SUMIFS('BALANCE 2024'!$I:$I,'BALANCE 2024'!$C:$C,"DH"),0) -> 132896547 | D26: =ROUND($C26*MAX(0,1-SUM($D25:D25)),0) -> 53158619 | E26: =ROUND($C26*MAX(0,1-SUM($D25:E25)),0) -> 0 | F26: =ROUND($C26*MAX(0,1-SUM($D25:F25)),0) -> 0 | G26: =ROUND($C26*MAX(0,1-SUM($D25:G25)),0) -> 0 | H26: =ROUND($C26*MAX(0,1-SUM($D25:H25)),0) -> 0
A27: Dette sur acquisitions de l'année | B27: 4812 | D27: =ROUND('INVEST ET FINANCEMENT'!D41*D24/360,0) -> 6012616 | E27: =ROUND('INVEST ET FINANCEMENT'!E41*E24/360,0) -> 12736111 | F27: =ROUND('INVEST ET FINANCEMENT'!F41*F24/360,0) -> 12736111 | G27: =ROUND('INVEST ET FINANCEMENT'!G41*G24/360,0) -> 27291667 | H27: =ROUND('INVEST ET FINANCEMENT'!H41*H24/360,0) -> 12736111
A28: Dette fournisseurs d'investissement au 31/12 (poste DH du bilan) | B28: 4812 | C28: =ROUND(C26,0) -> 132896547 | D28: =ROUND(D26+D27,0) -> 59171235 | E28: =ROUND(E26+E27,0) -> 12736111 | F28: =ROUND(F26+F27,0) -> 12736111 | G28: =ROUND(G26+G27,0) -> 27291667 | H28: =ROUND(H26+H27,0) -> 12736111
A29: Part des sorties de banque affectée à l'approvisionnement de la caisse (virement de fonds 585) | B29: 571 / 585 | D29: 0.2 | E29: 0.2 | F29: 0.2 | G29: 0.2 | H29: 0.2 | I29: Appro caisse = % x mouvements crédit du 521. Seule entrée en caisse (D 585 / C 521 puis D 571 / C 585). Créances clients encaissées par chèque ou virement. Soldes banque et caisse inchangés.
A30: Décaissements en espèces (% des approvisionnements de caisse de l'année) | B30: 571 | D30: 0.99 | E30: 0.99 | F30: 0.99 | G30: 0.99 | H30: 0.99 | I30: Moins de 100 % : la caisse augmente ; plus de 100 % : elle diminue. Solde de caisse = ouverture + appro x (1 - %). La banque absorbe l'écart.
A31: Ajustement des autres dettes (+ augmentation / - diminution de l'année) | B31: 4712 | D31: 0 | E31: 0 | F31: 0 | G31: 0 | H31: 0 | I31: Mouvement net saisi librement (créditeurs divers). Si le solde cumulé devient débiteur, il passe en autres créances (BJ).
I32: Les autres dettes fiscales et sociales évoluent comme leur charge de référence (66, 64) ; la TVA sur travaux en attente (4433, exigible à l'encaissement) suit les créances clients.
A33: 5. FISCALITÉ (Côte d'Ivoire)
A34: Taux de l'impôt sur les bénéfices | B34: % | D34: 0.25 | E34: 0.25 | F34: 0.25 | G34: 0.25 | H34: 0.25 | I34: CGI art. 51 : 25 %.
A35: Taux de l'IMF (sur CA TTC) | B35: % | D35: 0.005 | E35: 0.005 | F35: 0.005 | G35: 0.005 | H35: 0.005 | I35: CGI art. 39 : 0,5 % du CA TTC.
A36: IMF minimum | B36: FCFA | D36: 3000000 | E36: 3000000 | F36: 3000000 | G36: 3000000 | H36: 3000000 | I36: CGI art. 39.
A37: IMF maximum | B37: FCFA | D37: 35000000 | E37: 35000000 | F37: 35000000 | G37: 35000000 | H37: 35000000 | I37: CGI art. 39.
A38: Réintégrations fiscales nettes (+) / déductions (-) | B38: FCFA | D38: 0 | E38: 0 | F38: 0 | G38: 0 | H38: 0 | I38: Charges non déductibles (amendes, charges sans FNE, etc.) issues du tableau de passage.
A39: Dotation à la réserve légale (% du bénéfice) | B39: % | D39: 0.1 | E39: 0.1 | F39: 0.1 | G39: 0.1 | H39: 0.1 | I39: AUSCGIE art. 346 : 10 % jusqu'à 20 % du capital.
A40: Plafond de la réserve légale (% du capital) | B40: % | D40: 0.2 | E40: 0.2 | F40: 0.2 | G40: 0.2 | H40: 0.2 | I40: AUSCGIE art. 346.
A41: 6. CALCULS DU RÉSULTAT ET DE L'IMPÔT (ne pas modifier)
A42: Chiffre d'affaires (travaux facturés) | B42: 705 | C42: =ROUND(SUMIFS('BALANCE 2024'!$I:$I,'BALANCE 2024'!$C:$C,"TC"),0) -> 701026695 | D42: =ROUND(C42*(1+D9),0) -> 750098564 | E42: =ROUND(D42*(1+E9),0) -> 787603492 | F42: =ROUND(E42*(1+F9),0) -> 826983667 | G42: =ROUND(F42*(1+G9),0) -> 868332850 | H42: =ROUND(G42*(1+H9),0) -> 911749493
A43: Achats et autres approvisionnements | B43: 604-605-608 | C43: =ROUND(SUMIFS('BALANCE 2024'!$H:$H,'BALANCE 2024'!$C:$C,"RE"),0) -> 278141464 | D43: =ROUND(D42*D13,0) -> 297639110 | E43: =ROUND(E42*E13,0) -> 312521066 | F43: =ROUND(F42*F13,0) -> 328147119 | G43: =ROUND(G42*G13,0) -> 344554475 | H43: =ROUND(H42*H13,0) -> 361782199
A44: Transports | B44: 61 | C44: =ROUND(SUMIFS('BALANCE 2024'!$H:$H,'BALANCE 2024'!$C:$C,"RG"),0) -> 3820098 | D44: =ROUND(D42*D14,0) -> 4050532 | E44: =ROUND(E42*E14,0) -> 4253059 | F44: =ROUND(F42*F14,0) -> 4465712 | G44: =ROUND(G42*G14,0) -> 4688997 | H44: =ROUND(H42*H14,0) -> 4923447
A45: Services extérieurs | B45: 62-63 | C45: =ROUND(SUMIFS('BALANCE 2024'!$H:$H,'BALANCE 2024'!$C:$C,"RH"),0) -> 106769083 | D45: =ROUND(D42*D15,0) -> 114240011 | E45: =ROUND(E42*E15,0) -> 119952012 | F45: =ROUND(F42*F15,0) -> 125949612 | G45: =ROUND(G42*G15,0) -> 132247093 | H45: =ROUND(H42*H15,0) -> 138859448
A46: Impôts et taxes | B46: 64 | C46: =ROUND(SUMIFS('BALANCE 2024'!$H:$H,'BALANCE 2024'!$C:$C,"RI"),0) -> 14869670 | D46: =ROUND(D42*D16,0) -> 15902090 | E46: =ROUND(E42*E16,0) -> 16697194 | F46: =ROUND(F42*F16,0) -> 17532054 | G46: =ROUND(G42*G16,0) -> 18408656 | H46: =ROUND(H42*H16,0) -> 19329089
A47: Autres charges | B47: 65 | C47: =ROUND(SUMIFS('BALANCE 2024'!$H:$H,'BALANCE 2024'!$C:$C,"RJ"),0) -> 1316731 | D47: =ROUND(D42*D17,0) -> 1425187 | E47: =ROUND(E42*E17,0) -> 1496447 | F47: =ROUND(F42*F17,0) -> 1571269 | G47: =ROUND(G42*G17,0) -> 1649832 | H47: =ROUND(H42*H17,0) -> 1732324
A48: Charges de personnel | B48: 66 | C48: =ROUND(SUMIFS('BALANCE 2024'!$H:$H,'BALANCE 2024'!$C:$C,"RK"),0) -> 106025515 | D48: =ROUND(D42*D18,0) -> 113414903 | E48: =ROUND(E42*E18,0) -> 119085648 | F48: =ROUND(F42*F18,0) -> 125039930 | G48: =ROUND(G42*G18,0) -> 131291927 | H48: =ROUND(H42*H18,0) -> 137856523
A49: Base achats TTC fournisseurs (60+61+62-63, HT) | C49: =ROUND(C43+C44+C45,0) -> 388730645 | D49: =ROUND(D43+D44+D45,0) -> 415929653 | E49: =ROUND(E43+E44+E45,0) -> 436726137 | F49: =ROUND(F43+F44+F45,0) -> 458562443 | G49: =ROUND(G43+G44+G45,0) -> 481490565 | H49: =ROUND(H43+H44+H45,0) -> 505565094
A50: Dotations aux provisions (691) | B50: 691 | C50: =ROUND(SUMIFS('BALANCE 2024'!$H:$H,'BALANCE 2024'!$A:$A,">=691000",'BALANCE 2024'!$A:$A,"<692000"),0) -> 6059296 | D50: =ROUND(D20,0) -> 6059296 | E50: =ROUND(E20,0) -> 6059296 | F50: =ROUND(F20,0) -> 6059296 | G50: =ROUND(G20,0) -> 6059296 | H50: =ROUND(H20,0) -> 6059296
A51: Revenus financiers (77) | B51: 77 | C51: =ROUND(C11,0) -> 848594 | D51: =ROUND(D11,0) -> 848594 | E51: =ROUND(E11,0) -> 848594 | F51: =ROUND(F11,0) -> 848594 | G51: =ROUND(G11,0) -> 848594 | H51: =ROUND(H11,0) -> 848594
A52: Résultat avant impôt | B52: XG+XH | C52: =ROUND(C42+C51-C43-C44-C45-C46-C47-C48-'INVEST ET FINANCEMENT'!C42-C50-'INVEST ET FINANCEMENT'!C64-'INVEST ET FINANCEMENT'!C65,0) -> 96931836 | D52: =ROUND(D42+D51-D43-D44-D45-D46-D47-D48-'INVEST ET FINANCEMENT'!D42-D50-'INVEST ET FINANCEMENT'!D64-'INVEST ET FINANCEMENT'!D65,0) -> 123353157 | E52: =ROUND(E42+E51-E43-E44-E45-E46-E47-E48-'INVEST ET FINANCEMENT'!E42-E50-'INVEST ET FINANCEMENT'!E64-'INVEST ET FINANCEMENT'!E65,0) -> 114682036 | F52: =ROUND(F42+F51-F43-F44-F45-F46-F47-F48-'INVEST ET FINANCEMENT'!F42-F50-'INVEST ET FINANCEMENT'!F64-'INVEST ET FINANCEMENT'!F65,0) -> 121971114 | G52: =ROUND(G42+G51-G43-G44-G45-G46-G47-G48-'INVEST ET FINANCEMENT'!G42-G50-'INVEST ET FINANCEMENT'!G64-'INVEST ET FINANCEMENT'!G65,0) -> 134515784 | H52: =ROUND(H42+H51-H43-H44-H45-H46-H47-H48-'INVEST ET FINANCEMENT'!H42-H50-'INVEST ET FINANCEMENT'!H64-'INVEST ET FINANCEMENT'!H65,0) -> 144106858
A53: Résultat fiscal (après réintégrations) | D53: =ROUND(D52+D38,0) -> 123353157 | E53: =ROUND(E52+E38,0) -> 114682036 | F53: =ROUND(F52+F38,0) -> 121971114 | G53: =ROUND(G52+G38,0) -> 134515784 | H53: =ROUND(H52+H38,0) -> 144106858
A54: IS théorique (25 %) | D54: =ROUND(MAX(0,D53)*D34,0) -> 30838289 | E54: =ROUND(MAX(0,E53)*E34,0) -> 28670509 | F54: =ROUND(MAX(0,F53)*F34,0) -> 30492779 | G54: =ROUND(MAX(0,G53)*G34,0) -> 33628946 | H54: =ROUND(MAX(0,H53)*H34,0) -> 36026715
A55: IMF | D55: =ROUND(MIN(D37,MAX(D36,D35*(D42*(1+D10)+D51))),0) -> 4429824 | E55: =ROUND(MIN(E37,MAX(E36,E35*(E42*(1+E10)+E51))),0) -> 4651104 | F55: =ROUND(MIN(F37,MAX(F36,F35*(F42*(1+F10)+F51))),0) -> 4883447 | G55: =ROUND(MIN(G37,MAX(G36,G35*(G42*(1+G10)+G51))),0) -> 5127407 | H55: =ROUND(MIN(H37,MAX(H36,H35*(H42*(1+H10)+H51))),0) -> 5383565
A56: Impôt dû : le plus élevé de l'IS et de l'IMF | B56: 891 / 895 | C56: =ROUND(SUMIFS('BALANCE 2024'!$H:$H,'BALANCE 2024'!$C:$C,"RS"),0) -> 24232959 | D56: =ROUND(MAX(D54,D55),0) -> 30838289 | E56: =ROUND(MAX(E54,E55),0) -> 28670509 | F56: =ROUND(MAX(F54,F55),0) -> 30492779 | G56: =ROUND(MAX(G54,G55),0) -> 33628946 | H56: =ROUND(MAX(H54,H55),0) -> 36026715
A57: Résultat net de l'exercice | B57: XI | C57: =ROUND(C52-C56,0) -> 72698877 | D57: =ROUND(D52-D56,0) -> 92514868 | E57: =ROUND(E52-E56,0) -> 86011527 | F57: =ROUND(F52-F56,0) -> 91478335 | G57: =ROUND(G52-G56,0) -> 100886838 | H57: =ROUND(H52-H56,0) -> 108080143
A58: Affectation N-1 : dotation à la réserve légale | B58: 111 | D58: =ROUND(MIN(D39*MAX(0,C57),MAX(0,D40*'BALANCE 2024'!I5-'BALANCE 2024'!I6)),0) -> 2000000 | E58: =ROUND(MIN(E39*MAX(0,D57),MAX(0,E40*'BALANCE 2025'!I5-'BALANCE 2025'!I6)),0) -> 0 | F58: =ROUND(MIN(F39*MAX(0,E57),MAX(0,F40*'BALANCE 2026'!I5-'BALANCE 2026'!I6)),0) -> 0 | G58: =ROUND(MIN(G39*MAX(0,F57),MAX(0,G40*'BALANCE 2027'!I5-'BALANCE 2027'!I6)),0) -> 0 | H58: =ROUND(MIN(H39*MAX(0,G57),MAX(0,H40*'BALANCE 2028'!I5-'BALANCE 2028'!I6)),0) -> 0
A59: Affectation N-1 : dividendes versés | B59: 465 / 521 | D59: =ROUND(MAX(0,C57-D58)*'INVEST ET FINANCEMENT'!D55,0) -> 0 | E59: =ROUND(MAX(0,D57-E58)*'INVEST ET FINANCEMENT'!E55,0) -> 0 | F59: =ROUND(MAX(0,E57-F58)*'INVEST ET FINANCEMENT'!F55,0) -> 0 | G59: =ROUND(MAX(0,F57-G58)*'INVEST ET FINANCEMENT'!G55,0) -> 0 | H59: =ROUND(MAX(0,G57-H58)*'INVEST ET FINANCEMENT'!H55,0) -> 0
A60: Affectation N-1 : report à nouveau | B60: 121 | D60: =ROUND(C57-D58-D59,0) -> 70698877 | E60: =ROUND(D57-E58-E59,0) -> 92514868 | F60: =ROUND(E57-F58-F59,0) -> 86011527 | G60: =ROUND(F57-G58-G59,0) -> 91478335 | H60: =ROUND(G57-H58-H59,0) -> 100886838

Sheet INVEST ET FINANCEMENT
A1: HYPOTHÈSES D'INVESTISSEMENT ET DE FINANCEMENT
A2: Plan d'investissement, amortissements, endettement et plan de financement. Montants en FCFA.
A3: Mode d'emploi : saisir uniquement les cellules sur fond JAUNE (texte bleu). Les sections B, D et E se calculent automatiquement.
A4: ="Entité : "&HYPOTHESES!$C$4 -> Entité : MON ENTREPRISE
A7: Rubrique | B7: Réf. / compte | C7: ="Réel "&HYPOTHESES!$C$5 -> Réel 2024 | D7: =HYPOTHESES!$C$5+1 -> 2025 | E7: =HYPOTHESES!$C$5+2 -> 2026 | F7: =HYPOTHESES!$C$5+3 -> 2027 | G7: =HYPOTHESES!$C$5+4 -> 2028 | H7: =HYPOTHESES!$C$5+5 -> 2029 | I7: Commentaire / source
A8: A. PLAN D'INVESTISSEMENT (montants HT, acquisitions supposées au 1er janvier)
A9: Aménagements, agencements, installations | B9: 2341 / 2834 | C9: 0 | D9: 0 | E9: 0 | F9: 0 | G9: 0 | H9: 0 | I9: Colonne réel : acquisitions de l'année de base (mouvements débit 2024, hors location-acquisition 2456).
A10: Matériel et outillage industriel | B10: 2411 / 2841 | C10: 294528381 | D10: 0 | E10: 30000000 | F10: 30000000 | G10: 30000000 | H10: 30000000 | I10: Colonne réel : acquisitions de l'année de base (mouvements débit 2024, hors location-acquisition 2456).
A11: Matériel de bureau et informatique | B11: 2442 / 2844 | C11: 14513941 | D11: 930000 | E11: 5000000 | F11: 5000000 | G11: 5000000 | H11: 5000000 | I11: Colonne réel : acquisitions de l'année de base (mouvements débit 2024, hors location-acquisition 2456).
A12: Matériel de transport | B12: 2451 / 2845 | C12: 55896547 | D12: 15593220 | E12: 0 | F12: 0 | G12: 40000000 | H12: 0 | I12: Colonne réel : acquisitions de l'année de base (mouvements débit 2024, hors location-acquisition 2456).
A13: Nouveaux dépôts et cautionnements versés | B13: 275 | D13: 0 | E13: 0 | F13: 0 | G13: 0 | H13: 0
A14: Durée d'amortissement linéaire (années)
A15: Aménagements, agencements, installations | C15: 10 | I15: Durée d'utilité retenue (AUDCIF art. 45), fixée par l'entité.
A16: Matériel et outillage industriel | C16: 5 | I16: Durée d'utilité retenue (AUDCIF art. 45), fixée par l'entité.
A17: Matériel de bureau et informatique | C17: 2 | I17: Durée d'utilité retenue (AUDCIF art. 45), fixée par l'entité.
A18: Matériel de transport | C18: 3 | I18: Durée d'utilité retenue (AUDCIF art. 45), fixée par l'entité.
A19: Dotation annuelle sur les immobilisations existantes (plafonnée à la VNC restante)
A20: Aménagements, agencements, installations | B20: 681 | D20: 19282845 | E20: 19282845 | F20: 19282845 | G20: 19282845 | H20: 19282845 | I20: Défaut : dotation réelle de l'année de base.
A21: Matériel et outillage industriel | B21: 681 | D21: 28205053 | E21: 44854932 | F21: 44854932 | G21: 44854932 | H21: 44854932 | I21: Défaut : dotation réelle de l'année de base.
A22: Matériel de bureau et informatique | B22: 681 | D22: 4934884 | E22: 4934884 | F22: 4934884 | G22: 4934884 | H22: 4934884 | I22: Défaut : dotation réelle de l'année de base.
A23: Matériel de transport | B23: 681 | D23: 13760638 | E23: 10760638 | F23: 10760638 | G23: 10760638 | H23: 10760638 | I23: Défaut : dotation réelle de l'année de base.
A24: VNC au 31/12 de base des immo. existantes : aménagements, agencements, installations | B24: 2341 / 2834 | C24: 61665016 | I24: Brut moins amortissements de la balance de base.
A25: VNC au 31/12 de base des immo. existantes : matériel et outillage industriel | B25: 2411 / 2841 | C25: 257861504 | I25: Brut moins amortissements de la balance de base.
A26: VNC au 31/12 de base des immo. existantes : matériel de bureau et informatique | B26: 2442 / 2844 | C26: 9579057 | I26: Brut moins amortissements de la balance de base.
A27: VNC au 31/12 de base des immo. existantes : matériel de transport | B27: 2451 / 2845 | C27: 73755603 | I27: Brut moins amortissements de la balance de base.
A28: B. AMORTISSEMENTS ET TABLEAU DES IMMOBILISATIONS CORPORELLES (calculé)
A29: Dotation sur existant : aménagements, agencements, installations | B29: 681 | D29: =ROUND(MIN(D20,$C24),0) -> 19282845 | E29: =ROUND(MIN(E20,$C24-SUM($D29:D29)),0) -> 19282845 | F29: =ROUND(MIN(F20,$C24-SUM($D29:E29)),0) -> 19282845 | G29: =ROUND(MIN(G20,$C24-SUM($D29:F29)),0) -> 3816481 | H29: =ROUND(MIN(H20,$C24-SUM($D29:G29)),0) -> 0
A30: Dotation sur acquisitions nouvelles : aménagements, agencements, installations | B30: 681 | D30: =ROUND(SUMPRODUCT($D9:D9/$C15*((D$7-$D$7:D$7)<$C15)),0) -> 0 | E30: =ROUND(SUMPRODUCT($D9:E9/$C15*((E$7-$D$7:E$7)<$C15)),0) -> 0 | F30: =ROUND(SUMPRODUCT($D9:F9/$C15*((F$7-$D$7:F$7)<$C15)),0) -> 0 | G30: =ROUND(SUMPRODUCT($D9:G9/$C15*((G$7-$D$7:G$7)<$C15)),0) -> 0 | H30: =ROUND(SUMPRODUCT($D9:H9/$C15*((H$7-$D$7:H$7)<$C15)),0) -> 0
A31: Dotation totale : aménagements, agencements, installations | B31: 681 | D31: =ROUND(D29+D30,0) -> 19282845 | E31: =ROUND(E29+E30,0) -> 19282845 | F31: =ROUND(F29+F30,0) -> 19282845 | G31: =ROUND(G29+G30,0) -> 3816481 | H31: =ROUND(H29+H30,0) -> 0
A32: Dotation sur existant : matériel et outillage industriel | B32: 681 | D32: =ROUND(MIN(D21,$C25),0) -> 28205053 | E32: =ROUND(MIN(E21,$C25-SUM($D32:D32)),0) -> 44854932 | F32: =ROUND(MIN(F21,$C25-SUM($D32:E32)),0) -> 44854932 | G32: =ROUND(MIN(G21,$C25-SUM($D32:F32)),0) -> 44854932 | H32: =ROUND(MIN(H21,$C25-SUM($D32:G32)),0) -> 44854932
A33: Dotation sur acquisitions nouvelles : matériel et outillage industriel | B33: 681 | D33: =ROUND(SUMPRODUCT($D10:D10/$C16*((D$7-$D$7:D$7)<$C16)),0) -> 0 | E33: =ROUND(SUMPRODUCT($D10:E10/$C16*((E$7-$D$7:E$7)<$C16)),0) -> 6000000 | F33: =ROUND(SUMPRODUCT($D10:F10/$C16*((F$7-$D$7:F$7)<$C16)),0) -> 12000000 | G33: =ROUND(SUMPRODUCT($D10:G10/$C16*((G$7-$D$7:G$7)<$C16)),0) -> 18000000 | H33: =ROUND(SUMPRODUCT($D10:H10/$C16*((H$7-$D$7:H$7)<$C16)),0) -> 24000000
A34: Dotation totale : matériel et outillage industriel | B34: 681 | D34: =ROUND(D32+D33,0) -> 28205053 | E34: =ROUND(E32+E33,0) -> 50854932 | F34: =ROUND(F32+F33,0) -> 56854932 | G34: =ROUND(G32+G33,0) -> 62854932 | H34: =ROUND(H32+H33,0) -> 68854932
A35: Dotation sur existant : matériel de bureau et informatique | B35: 681 | D35: =ROUND(MIN(D22,$C26),0) -> 4934884 | E35: =ROUND(MIN(E22,$C26-SUM($D35:D35)),0) -> 4644173 | F35: =ROUND(MIN(F22,$C26-SUM($D35:E35)),0) -> 0 | G35: =ROUND(MIN(G22,$C26-SUM($D35:F35)),0) -> 0 | H35: =ROUND(MIN(H22,$C26-SUM($D35:G35)),0) -> 0
A36: Dotation sur acquisitions nouvelles : matériel de bureau et informatique | B36: 681 | D36: =ROUND(SUMPRODUCT($D11:D11/$C17*((D$7-$D$7:D$7)<$C17)),0) -> 465000 | E36: =ROUND(SUMPRODUCT($D11:E11/$C17*((E$7-$D$7:E$7)<$C17)),0) -> 2965000 | F36: =ROUND(SUMPRODUCT($D11:F11/$C17*((F$7-$D$7:F$7)<$C17)),0) -> 5000000 | G36: =ROUND(SUMPRODUCT($D11:G11/$C17*((G$7-$D$7:G$7)<$C17)),0) -> 5000000 | H36: =ROUND(SUMPRODUCT($D11:H11/$C17*((H$7-$D$7:H$7)<$C17)),0) -> 5000000
A37: Dotation totale : matériel de bureau et informatique | B37: 681 | D37: =ROUND(D35+D36,0) -> 5399884 | E37: =ROUND(E35+E36,0) -> 7609173 | F37: =ROUND(F35+F36,0) -> 5000000 | G37: =ROUND(G35+G36,0) -> 5000000 | H37: =ROUND(H35+H36,0) -> 5000000
A38: Dotation sur existant : matériel de transport | B38: 681 | D38: =ROUND(MIN(D23,$C27),0) -> 13760638 | E38: =ROUND(MIN(E23,$C27-SUM($D38:D38)),0) -> 10760638 | F38: =ROUND(MIN(F23,$C27-SUM($D38:E38)),0) -> 10760638 | G38: =ROUND(MIN(G23,$C27-SUM($D38:F38)),0) -> 10760638 | H38: =ROUND(MIN(H23,$C27-SUM($D38:G38)),0) -> 10760638
A39: Dotation sur acquisitions nouvelles : matériel de transport | B39: 681 | D39: =ROUND(SUMPRODUCT($D12:D12/$C18*((D$7-$D$7:D$7)<$C18)),0) -> 5197740 | E39: =ROUND(SUMPRODUCT($D12:E12/$C18*((E$7-$D$7:E$7)<$C18)),0) -> 5197740 | F39: =ROUND(SUMPRODUCT($D12:F12/$C18*((F$7-$D$7:F$7)<$C18)),0) -> 5197740 | G39: =ROUND(SUMPRODUCT($D12:G12/$C18*((G$7-$D$7:G$7)<$C18)),0) -> 13333333 | H39: =ROUND(SUMPRODUCT($D12:H12/$C18*((H$7-$D$7:H$7)<$C18)),0) -> 13333333
A40: Dotation totale : matériel de transport | B40: 681 | D40: =ROUND(D38+D39,0) -> 18958378 | E40: =ROUND(E38+E39,0) -> 15958378 | F40: =ROUND(F38+F39,0) -> 15958378 | G40: =ROUND(G38+G39,0) -> 24093971 | H40: =ROUND(H38+H39,0) -> 24093971
A41: Total investissements corporels | C41: =ROUND(C9+C10+C11+C12,0) -> 364938869 | D41: =ROUND(D9+D10+D11+D12,0) -> 16523220 | E41: =ROUND(E9+E10+E11+E12,0) -> 35000000 | F41: =ROUND(F9+F10+F11+F12,0) -> 35000000 | G41: =ROUND(G9+G10+G11+G12,0) -> 75000000 | H41: =ROUND(H9+H10+H11+H12,0) -> 35000000
A42: Total dotations aux amortissements (681) | B42: 681 | C42: =ROUND(SUMIFS('BALANCE 2024'!$H:$H,'BALANCE 2024'!$A:$A,">=681000",'BALANCE 2024'!$A:$A,"<682000"),0) -> 79833299 | D42: =ROUND(D31+D34+D37+D40,0) -> 71846160 | E42: =ROUND(E31+E34+E37+E40,0) -> 93705328 | F42: =ROUND(F31+F34+F37+F40,0) -> 97096155 | G42: =ROUND(G31+G34+G37+G40,0) -> 95765384 | H42: =ROUND(H31+H34+H37+H40,0) -> 97948903
A43: Immobilisations corporelles brutes au 31/12 | B43: 22 à 24 | C43: =ROUND(SUMIFS('BALANCE 2024'!$H:$H,'BALANCE 2024'!$C:$C,"AJ")+SUMIFS('BALANCE 2024'!$H:$H,'BALANCE 2024'!$C:$C,"AK")+SUMIFS('BALANCE 2024'!$H:$H,'BALANCE 2024'!$C:$C,"AL")+SUMIFS('BALANCE 2024'!$H:$H,'BALANCE 2024'!$C:$C,"AM")+SUMIFS('BALANCE 2024'!$H:$H,'BALANCE 2024'!$C:$C,"AN"),0) -> 876398854 | D43: =ROUND(C43+D41,0) -> 892922074 | E43: =ROUND(D43+E41,0) -> 927922074 | F43: =ROUND(E43+F41,0) -> 962922074 | G43: =ROUND(F43+G41,0) -> 1037922074 | H43: =ROUND(G43+H41,0) -> 1072922074
A44: Amortissements cumulés au 31/12 | B44: 28 | C44: =ROUND(SUMIFS('BALANCE 2024'!$I:$I,'BALANCE 2024'!$C:$C,"AJ")+SUMIFS('BALANCE 2024'!$I:$I,'BALANCE 2024'!$C:$C,"AK")+SUMIFS('BALANCE 2024'!$I:$I,'BALANCE 2024'!$C:$C,"AL")+SUMIFS('BALANCE 2024'!$I:$I,'BALANCE 2024'!$C:$C,"AM")+SUMIFS('BALANCE 2024'!$I:$I,'BALANCE 2024'!$C:$C,"AN"),0) -> 473537674 | D44: =ROUND(C44+D42,0) -> 545383834 | E44: =ROUND(D44+E42,0) -> 639089162 | F44: =ROUND(E44+F42,0) -> 736185317 | G44: =ROUND(F44+G42,0) -> 831950701 | H44: =ROUND(G44+H42,0) -> 929899604
A45: Valeur nette comptable au 31/12 (= poste AI du bilan) | B45: AI | C45: =ROUND(C43-C44,0) -> 402861180 | D45: =ROUND(D43-D44,0) -> 347538240 | E45: =ROUND(E43-E44,0) -> 288832912 | F45: =ROUND(F43-F44,0) -> 226736757 | G45: =ROUND(G43-G44,0) -> 205971373 | H45: =ROUND(H43-H44,0) -> 143022470
A46: C. HYPOTHÈSES DE FINANCEMENT ET DE CAPITAUX PROPRES
A47: Nouveaux emprunts | B47: 162 | D47: 54395682 | E47: 0 | F47: 0 | G47: 0 | H47: 0
A48: Remboursements d'emprunts | B48: 162 | D48: 94054514 | E48: 0 | F48: 0 | G48: 0 | H48: 0 | I48: 2025 : encours BNI 39 658 832 + nouvel emprunt 54 395 682. Ne pas rembourser plus que l'encours (voir contrôle).
A49: Remboursements de dettes de location-acquisition | B49: 173 | D49: 10619694 | E49: 0 | F49: 0 | G49: 0 | H49: 0 | I49: Défaut : solde 10,6 M remboursé en année 1.
A50: Taux d'intérêt moyen sur dettes financières | B50: % | D50: 0.06 | E50: 0.08 | F50: 0.08 | G50: 0.08 | H50: 0.08 | I50: Appliqué à l'encours d'ouverture (671 emprunts, 672 location-acquisition).
A51: Augmentation de capital en numéraire | B51: 101 | D51: 0 | E51: 0 | F51: 0 | G51: 0 | H51: 0
A52: Remboursement du compte courant d'associés de base (% de l'encours) | B52: 4621 | D52: 1 | E52: 0 | F52: 0 | G52: 0 | H52: 0 | I52: Encours au 31/12/2024 : 3,7 M, soldé en 2025.
A53: Nouveaux apports en compte courant d'associés | B53: 4621 | D53: 0 | E53: 0 | F53: 0 | G53: 0 | H53: 0
A54: Compte courant d'associés au 31/12 | B54: 4621 | C54: =ROUND(SUMIFS('BALANCE 2024'!$I:$I,'BALANCE 2024'!$A:$A,462100)-SUMIFS('BALANCE 2024'!$H:$H,'BALANCE 2024'!$A:$A,462100),0) -> 3700000 | D54: =ROUND($C54*MAX(0,1-SUM($D52:D52))+SUM($D53:D53),0) -> 0 | E54: =ROUND($C54*MAX(0,1-SUM($D52:E52))+SUM($D53:E53),0) -> 0 | F54: =ROUND($C54*MAX(0,1-SUM($D52:F52))+SUM($D53:F53),0) -> 0 | G54: =ROUND($C54*MAX(0,1-SUM($D52:G52))+SUM($D53:G53),0) -> 0 | H54: =ROUND($C54*MAX(0,1-SUM($D52:H52))+SUM($D53:H53),0) -> 0
A55: Dividendes distribués (% du bénéfice N-1 après réserve légale) | B55: % | D55: 0 | E55: 0 | F55: 0 | G55: 0 | H55: 0 | I55: Le solde est porté en report à nouveau (affectation votée en AG de l'année N).
A56: D. TABLEAU D'ENDETTEMENT (calculé)
A57: Emprunts : encours au 1er janvier | B57: 162 | D57: =ROUND('BALANCE 2024'!I9,0) -> 39658832 | E57: =ROUND('BALANCE 2025'!I9,0) -> 0 | F57: =ROUND('BALANCE 2026'!I9,0) -> 0 | G57: =ROUND('BALANCE 2027'!I9,0) -> 0 | H57: =ROUND('BALANCE 2028'!I9,0) -> 0
A58: + Nouveaux emprunts | B58: 162 | D58: =ROUND(D47,0) -> 54395682 | E58: =ROUND(E47,0) -> 0 | F58: =ROUND(F47,0) -> 0 | G58: =ROUND(G47,0) -> 0 | H58: =ROUND(H47,0) -> 0
A59: - Remboursements | B59: 162 | D59: =ROUND(-D48,0) -> -94054514 | E59: =ROUND(-E48,0) -> 0 | F59: =ROUND(-F48,0) -> 0 | G59: =ROUND(-G48,0) -> 0 | H59: =ROUND(-H48,0) -> 0
A60: Emprunts : encours au 31 décembre | B60: DA | C60: =ROUND(SUMIFS('BALANCE 2024'!$I:$I,'BALANCE 2024'!$C:$C,"DA"),0) -> 39658832 | D60: =ROUND(D57+D58+D59,0) -> 0 | E60: =ROUND(E57+E58+E59,0) -> 0 | F60: =ROUND(F57+F58+F59,0) -> 0 | G60: =ROUND(G57+G58+G59,0) -> 0 | H60: =ROUND(H57+H58+H59,0) -> 0
A61: Location-acquisition : encours au 1er janvier | B61: 173 | D61: =ROUND('BALANCE 2024'!I10,0) -> 10619694 | E61: =ROUND('BALANCE 2025'!I10,0) -> 0 | F61: =ROUND('BALANCE 2026'!I10,0) -> 0 | G61: =ROUND('BALANCE 2027'!I10,0) -> 0 | H61: =ROUND('BALANCE 2028'!I10,0) -> 0
A62: - Remboursements | B62: 173 | D62: =ROUND(-D49,0) -> -10619694 | E62: =ROUND(-E49,0) -> 0 | F62: =ROUND(-F49,0) -> 0 | G62: =ROUND(-G49,0) -> 0 | H62: =ROUND(-H49,0) -> 0
A63: Location-acquisition : encours au 31 décembre | B63: DB | C63: =ROUND(SUMIFS('BALANCE 2024'!$I:$I,'BALANCE 2024'!$C:$C,"DB"),0) -> 10619694 | D63: =ROUND(D61+D62,0) -> 0 | E63: =ROUND(E61+E62,0) -> 0 | F63: =ROUND(F61+F62,0) -> 0 | G63: =ROUND(G61+G62,0) -> 0 | H63: =ROUND(H61+H62,0) -> 0
A64: Intérêts des emprunts (671) | B64: 671 | C64: =ROUND(SUMIFS('BALANCE 2024'!$H:$H,'BALANCE 2024'!$A:$A,">=671000",'BALANCE 2024'!$A:$A,"<672000"),0) -> 4142819 | D64: =ROUND(D50*'BALANCE 2024'!I9,0) -> 2379530 | E64: =ROUND(E50*'BALANCE 2025'!I9,0) -> 0 | F64: =ROUND(F50*'BALANCE 2026'!I9,0) -> 0 | G64: =ROUND(G50*'BALANCE 2027'!I9,0) -> 0 | H64: =ROUND(H50*'BALANCE 2028'!I9,0) -> 0
A65: Intérêts de location-acquisition (672) | B65: 672 | C65: =ROUND(SUMIFS('BALANCE 2024'!$H:$H,'BALANCE 2024'!$A:$A,">=672000",'BALANCE 2024'!$A:$A,"<673000"),0) -> 3965478 | D65: =ROUND(D50*'BALANCE 2024'!I10,0) -> 637182 | E65: =ROUND(E50*'BALANCE 2025'!I10,0) -> 0 | F65: =ROUND(F50*'BALANCE 2026'!I10,0) -> 0 | G65: =ROUND(G50*'BALANCE 2027'!I10,0) -> 0 | H65: =ROUND(H50*'BALANCE 2028'!I10,0) -> 0
A66: Service de la dette (remboursements + intérêts) | D66: =ROUND(D48+D49+D64+D65,0) -> 107690920 | E66: =ROUND(E48+E49+E64+E65,0) -> 0 | F66: =ROUND(F48+F49+F64+F65,0) -> 0 | G66: =ROUND(G48+G49+G64+G65,0) -> 0 | H66: =ROUND(H48+H49+H64+H65,0) -> 0
A67: E. PLAN DE FINANCEMENT (calculé)
A68: Emplois : investissements corporels | D68: =ROUND(D41,0) -> 16523220 | E68: =ROUND(E41,0) -> 35000000 | F68: =ROUND(F41,0) -> 35000000 | G68: =ROUND(G41,0) -> 75000000 | H68: =ROUND(H41,0) -> 35000000
A69: Emplois : immobilisations financières | D69: =ROUND(D13,0) -> 0 | E69: =ROUND(E13,0) -> 0 | F69: =ROUND(F13,0) -> 0 | G69: =ROUND(G13,0) -> 0 | H69: =ROUND(H13,0) -> 0
A70: Emplois : remboursements de dettes financières | D70: =ROUND(D48+D49,0) -> 104674208 | E70: =ROUND(E48+E49,0) -> 0 | F70: =ROUND(F48+F49,0) -> 0 | G70: =ROUND(G48+G49,0) -> 0 | H70: =ROUND(H48+H49,0) -> 0
A71: Emplois : dividendes versés | D71: =ROUND(HYPOTHESES!D59,0) -> 0 | E71: =ROUND(HYPOTHESES!E59,0) -> 0 | F71: =ROUND(HYPOTHESES!F59,0) -> 0 | G71: =ROUND(HYPOTHESES!G59,0) -> 0 | H71: =ROUND(HYPOTHESES!H59,0) -> 0
A72: TOTAL EMPLOIS | D72: =ROUND(SUM(D68:D71),0) -> 121197428 | E72: =ROUND(SUM(E68:E71),0) -> 35000000 | F72: =ROUND(SUM(F68:F71),0) -> 35000000 | G72: =ROUND(SUM(G68:G71),0) -> 75000000 | H72: =ROUND(SUM(H68:H71),0) -> 35000000
A73: Ressources : capacité d'autofinancement globale (CAFG) | B73: FA | D73: =ROUND(HYPOTHESES!D57+D42+HYPOTHESES!D50,0) -> 170420324 | E73: =ROUND(HYPOTHESES!E57+E42+HYPOTHESES!E50,0) -> 185776151 | F73: =ROUND(HYPOTHESES!F57+F42+HYPOTHESES!F50,0) -> 194633786 | G73: =ROUND(HYPOTHESES!G57+G42+HYPOTHESES!G50,0) -> 202711518 | H73: =ROUND(HYPOTHESES!H57+H42+HYPOTHESES!H50,0) -> 212088342
A74: Ressources : augmentation de capital | D74: =ROUND(D51,0) -> 0 | E74: =ROUND(E51,0) -> 0 | F74: =ROUND(F51,0) -> 0 | G74: =ROUND(G51,0) -> 0 | H74: =ROUND(H51,0) -> 0
A75: Ressources : nouveaux emprunts | D75: =ROUND(D47,0) -> 54395682 | E75: =ROUND(E47,0) -> 0 | F75: =ROUND(F47,0) -> 0 | G75: =ROUND(G47,0) -> 0 | H75: =ROUND(H47,0) -> 0
A76: TOTAL RESSOURCES | D76: =ROUND(SUM(D73:D75),0) -> 224816006 | E76: =ROUND(SUM(E73:E75),0) -> 185776151 | F76: =ROUND(SUM(F73:F75),0) -> 194633786 | G76: =ROUND(SUM(G73:G75),0) -> 202711518 | H76: =ROUND(SUM(H73:H75),0) -> 212088342
A77: Variation du fonds de roulement (ressources - emplois) | D77: =ROUND(D76-D72,0) -> 103618578 | E77: =ROUND(E76-E72,0) -> 150776151 | F77: =ROUND(F76-F72,0) -> 159633786 | G77: =ROUND(G76-G72,0) -> 127711518 | H77: =ROUND(H76-H72,0) -> 177088342 | I77: Un solde négatif signifie que les investissements et remboursements sont financés en puisant dans la trésorerie.

Sheet BALANCE 2024
A1: BALANCE GÉNÉRALE À 6 COLONNES : EXERCICE 2024 (RÉEL)
A2: Balance réelle reprise de l'onglet « 2025 » du fichier BALANCES_ET_PREVISIONS_TEST (ouverture 2024, mouvements 2024, clôture 2024).
D3: Soldes d'ouverture | F3: Mouvements de l'exercice | H3: Soldes de clôture | J3: Contrôle
A4: Compte | B4: Intitulé | C4: Poste | D4: Débit | E4: Crédit | F4: Débit | G4: Crédit | H4: Débit | I4: Crédit | J4: Ouv.+Mvts-Clôt.
A5: 101000 | B5: Capital social | C5: CA | D5: 0 | E5: 10000000 | F5: 0 | G5: 0 | H5: 0 | I5: 10000000 | J5: =(D5-E5)+(F5-G5)-(H5-I5) -> 0
A6: 111000 | B6: Réserve légale | C6: CF | D6: 0 | E6: 0 | F6: 0 | G6: 0 | H6: 0 | I6: 0 | J6: =(D6-E6)+(F6-G6)-(H6-I6) -> 0
A7: 121000 | B7: Report à nouveau | C7: CH | D7: 0 | E7: 654621364 | F7: 0 | G7: 119178487 | H7: 0 | I7: 773799851 | J7: =(D7-E7)+(F7-G7)-(H7-I7) -> 0
A8: 130100 | B8: Résultat en instance d'affectation : bénéfice | C8: R13 | D8: 0 | E8: 119178487 | F8: 119178487 | G8: 0 | H8: 0 | I8: 0 | J8: =(D8-E8)+(F8-G8)-(H8-I8) -> 0
A9: 162002 | B9: Emprunts auprès des établissements de crédit (BNI) | C9: DA | D9: 0 | E9: 0 | F9: 351341168 | G9: 391000000 | H9: 0 | I9: 39658832 | J9: =(D9-E9)+(F9-G9)-(H9-I9) -> 0
A10: 173060 | B10: Dettes de location-acquisition | C10: DB | D10: 0 | E10: 0 | F10: 18000000 | G10: 28619694 | H10: 0 | I10: 10619694 | J10: =(D10-E10)+(F10-G10)-(H10-I10) -> 0
A11: 196100 | B11: Provisions pour pensions et obligations similaires (IFC) | C11: DC | D11: 0 | E11: 15214600 | F11: 0 | G11: 6059296 | H11: 0 | I11: 21273896 | J11: =(D11-E11)+(F11-G11)-(H11-I11) -> 0
A12: 234100 | B12: Aménagements, agencements et installations techniques | C12: AL | D12: 103601492 | E12: 0 | F12: 0 | G12: 0 | H12: 103601492 | I12: 0 | J12: =(D12-E12)+(F12-G12)-(H12-I12) -> 0
A13: 241100 | B13: Matériel industriel | C13: AM | D13: 19316887 | E13: 0 | F13: 294528381 | G13: 0 | H13: 313845268 | I13: 0 | J13: =(D13-E13)+(F13-G13)-(H13-I13) -> 0
A14: 244100 | B14: Matériel de bureau | C14: AM | D14: 2050000 | E14: 0 | F14: 7256956 | G14: 0 | H14: 9306956 | I14: 0 | J14: =(D14-E14)+(F14-G14)-(H14-I14) -> 0
A15: 244200 | B15: Matériel informatique | C15: AM | D15: 5723474 | E15: 0 | F15: 7256985 | G15: 0 | H15: 12980459 | I15: 0 | J15: =(D15-E15)+(F15-G15)-(H15-I15) -> 0
A16: 245100 | B16: Matériel automobile | C16: AN | D16: 352148438 | E16: 0 | F16: 55896547 | G16: 0 | H16: 408044985 | I16: 0 | J16: =(D16-E16)+(F16-G16)-(H16-I16) -> 0
... A94: 895000 | B94: Impôt minimum forfaitaire (IMF) | C94: RS | D94: 0 | E94: 0 | F94: 0 | G94: 0 | H94: 0 | I94: 0 | J94: =(D94-E94)+(F94-G94)-(H94-I94) -> 0
B96: TOTAL BALANCE | D96: =SUM(D5:D94) -> 1308965390 | E96: =SUM(E5:E94) -> 1308965390 | F96: =SUM(F5:F94) -> 4378495087 | G96: =SUM(G5:G94) -> 4378495087 | H96: =SUM(H5:H94) -> 2342400758 | I96: =SUM(I5:I94) -> 2342400758 | J96: =SUM(J5:J94) -> 0
B97: Écart débit - crédit (doit être nul) | D97: =D96-E96 -> 0 | F97: =F96-G96 -> 0 | H97: =H96-I96 -> 0

Sheet BALANCE 2025
A1: BALANCE GÉNÉRALE À 6 COLONNES : EXERCICE 2025 (PRÉVISIONNEL)
A2: Ouverture = clôture de l'exercice précédent (classes 6 à 8 soldées, résultat N-1 en 13). Clôture calculée depuis les hypothèses ; mouvements = flux de l'exercice. Soldes après inventaire, avant écritures de clôture. Ne rien saisir.
D3: Soldes d'ouverture | F3: Mouvements de l'exercice | H3: Soldes de clôture | J3: Contrôle
A4: Compte | B4: Intitulé | C4: Poste | D4: Débit | E4: Crédit | F4: Débit | G4: Crédit | H4: Débit | I4: Crédit | J4: Ouv.+Mvts-Clôt.
A5: 101000 | B5: Capital social | C5: CA | D5: ='BALANCE 2024'!H5 -> 0 | E5: ='BALANCE 2024'!I5 -> 10000000 | F5: =ROUND('INVEST ET FINANCEMENT'!D$51,0)+(H5-I5)-(D5-E5) -> 0 | G5: =ROUND('INVEST ET FINANCEMENT'!D$51,0) -> 0 | H5: 0 | I5: =ROUND(E5+'INVEST ET FINANCEMENT'!D$51,0) -> 10000000 | J5: =(D5-E5)+(F5-G5)-(H5-I5) -> 0
A6: 111000 | B6: Réserve légale | C6: CF | D6: ='BALANCE 2024'!H6 -> 0 | E6: ='BALANCE 2024'!I6 -> 0 | F6: =ROUND(HYPOTHESES!D$58,0)+(H6-I6)-(D6-E6) -> 0 | G6: =ROUND(HYPOTHESES!D$58,0) -> 2000000 | H6: 0 | I6: =ROUND(E6+HYPOTHESES!D$58,0) -> 2000000 | J6: =(D6-E6)+(F6-G6)-(H6-I6) -> 0
A7: 121000 | B7: Report à nouveau | C7: CH | D7: ='BALANCE 2024'!H7 -> 0 | E7: ='BALANCE 2024'!I7 -> 773799851 | F7: =MAX(0,(H7-I7)-(D7-E7)) -> 0 | G7: =MAX(0,(D7-E7)-(H7-I7)) -> 70698877 | H7: =ROUND(MAX(0,-(E7-D7+HYPOTHESES!D$60)),0) -> 0 | I7: =ROUND(MAX(0,(E7-D7+HYPOTHESES!D$60)),0) -> 844498728 | J7: =(D7-E7)+(F7-G7)-(H7-I7) -> 0
A8: 130100 | B8: Résultat en instance d'affectation : bénéfice | C8: R13 | D8: =MAX(0,-(SUM('BALANCE 2024'!I48:I94)-SUM('BALANCE 2024'!H48:H94))) -> 0 | E8: =MAX(0,(SUM('BALANCE 2024'!I48:I94)-SUM('BALANCE 2024'!H48:H94))) -> 72698877 | F8: =MAX(0,(H8-I8)-(D8-E8)) -> 72698877 | G8: =MAX(0,(D8-E8)-(H8-I8)) -> 0 | H8: 0 | I8: 0 | J8: =(D8-E8)+(F8-G8)-(H8-I8) -> 0
A9: 162002 | B9: Emprunts auprès des établissements de crédit (BNI) | C9: DA | D9: ='BALANCE 2024'!H9 -> 0 | E9: ='BALANCE 2024'!I9 -> 39658832 | F9: =ROUND('INVEST ET FINANCEMENT'!D$47,0)+(H9-I9)-(D9-E9) -> 94054514 | G9: =ROUND('INVEST ET FINANCEMENT'!D$47,0) -> 54395682 | H9: 0 | I9: =ROUND(E9+'INVEST ET FINANCEMENT'!D$47-'INVEST ET FINANCEMENT'!D$48,0) -> 0 | J9: =(D9-E9)+(F9-G9)-(H9-I9) -> 0
A10: 173060 | B10: Dettes de location-acquisition | C10: DB | D10: ='BALANCE 2024'!H10 -> 0 | E10: ='BALANCE 2024'!I10 -> 10619694 | F10: =ROUND('INVEST ET FINANCEMENT'!D$49,0) -> 10619694 | G10: =ROUND('INVEST ET FINANCEMENT'!D$49,0)+(D10-E10)-(H10-I10) -> 0 | H10: 0 | I10: =ROUND(E10-'INVEST ET FINANCEMENT'!D$49,0) -> 0 | J10: =(D10-E10)+(F10-G10)-(H10-I10) -> 0
A11: 196100 | B11: Provisions pour pensions et obligations similaires (IFC) | C11: DC | D11: ='BALANCE 2024'!H11 -> 0 | E11: ='BALANCE 2024'!I11 -> 21273896 | F11: =ROUND(HYPOTHESES!D$20,0)+(H11-I11)-(D11-E11) -> 0 | G11: =ROUND(HYPOTHESES!D$20,0) -> 6059296 | H11: 0 | I11: =ROUND(E11+HYPOTHESES!D$20,0) -> 27333192 | J11: =(D11-E11)+(F11-G11)-(H11-I11) -> 0
A12: 234100 | B12: Aménagements, agencements et installations techniques | C12: AL | D12: ='BALANCE 2024'!H12 -> 103601492 | E12: ='BALANCE 2024'!I12 -> 0 | F12: =ROUND('INVEST ET FINANCEMENT'!D$9,0) -> 0 | G12: =ROUND('INVEST ET FINANCEMENT'!D$9,0)+(D12-E12)-(H12-I12) -> 0 | H12: =ROUND(D12+'INVEST ET FINANCEMENT'!D$9,0) -> 103601492 | I12: 0 | J12: =(D12-E12)+(F12-G12)-(H12-I12) -> 0
A13: 241100 | B13: Matériel industriel | C13: AM | D13: ='BALANCE 2024'!H13 -> 313845268 | E13: ='BALANCE 2024'!I13 -> 0 | F13: =ROUND('INVEST ET FINANCEMENT'!D$10,0) -> 0 | G13: =ROUND('INVEST ET FINANCEMENT'!D$10,0)+(D13-E13)-(H13-I13) -> 0 | H13: =ROUND(D13+'INVEST ET FINANCEMENT'!D$10,0) -> 313845268 | I13: 0 | J13: =(D13-E13)+(F13-G13)-(H13-I13) -> 0
A14: 244100 | B14: Matériel de bureau | C14: AM | D14: ='BALANCE 2024'!H14 -> 9306956 | E14: ='BALANCE 2024'!I14 -> 0 | F14: =MAX(0,(H14-I14)-(D14-E14)) -> 0 | G14: =MAX(0,(D14-E14)-(H14-I14)) -> 0 | H14: =ROUND(D14,0) -> 9306956 | I14: 0 | J14: =(D14-E14)+(F14-G14)-(H14-I14) -> 0
A15: 244200 | B15: Matériel informatique | C15: AM | D15: ='BALANCE 2024'!H15 -> 12980459 | E15: ='BALANCE 2024'!I15 -> 0 | F15: =ROUND('INVEST ET FINANCEMENT'!D$11,0) -> 930000 | G15: =ROUND('INVEST ET FINANCEMENT'!D$11,0)+(D15-E15)-(H15-I15) -> 0 | H15: =ROUND(D15+'INVEST ET FINANCEMENT'!D$11,0) -> 13910459 | I15: 0 | J15: =(D15-E15)+(F15-G15)-(H15-I15) -> 0
A16: 245100 | B16: Matériel automobile | C16: AN | D16: ='BALANCE 2024'!H16 -> 408044985 | E16: ='BALANCE 2024'!I16 -> 0 | F16: =ROUND('INVEST ET FINANCEMENT'!D$12,0) -> 15593220 | G16: =ROUND('INVEST ET FINANCEMENT'!D$12,0)+(D16-E16)-(H16-I16) -> 0 | H16: =ROUND(D16+'INVEST ET FINANCEMENT'!D$12,0) -> 423638205 | I16: 0 | J16: =(D16-E16)+(F16-G16)-(H16-I16) -> 0
A17: 245600 | B17: Matériel de transport en location-acquisition | C17: AN | D17: ='BALANCE 2024'!H17 -> 28619694 | E17: ='BALANCE 2024'!I17 -> 0 | F17: =MAX(0,(H17-I17)-(D17-E17)) -> 0 | G17: =MAX(0,(D17-E17)-(H17-I17)) -> 0 | H17: =ROUND(D17,0) -> 28619694 | I17: 0 | J17: =(D17-E17)+(F17-G17)-(H17-I17) -> 0
A18: 271800 | B18: Autres prêts et créances | C18: AS | D18: ='BALANCE 2024'!H18 -> 25000000 | E18: ='BALANCE 2024'!I18 -> 0 | F18: =MAX(0,(H18-I18)-(D18-E18)) -> 0 | G18: =MAX(0,(D18-E18)-(H18-I18)) -> 0 | H18: =ROUND(D18,0) -> 25000000 | I18: 0 | J18: =(D18-E18)+(F18-G18)-(H18-I18) -> 0
A19: 275100 | B19: Dépôts et cautionnements versés | C19: AS | D19: ='BALANCE 2024'!H19 -> 231420138 | E19: ='BALANCE 2024'!I19 -> 0 | F19: =ROUND('INVEST ET FINANCEMENT'!D$13,0) -> 0 | G19: =ROUND('INVEST ET FINANCEMENT'!D$13,0)+(D19-E19)-(H19-I19) -> 0 | H19: =ROUND(D19+'INVEST ET FINANCEMENT'!D$13,0) -> 231420138 | I19: 0 | J19: =(D19-E19)+(F19-G19)-(H19-I19) -> 0
A20: 283400 | B20: Amortissements des aménagements, agencements | C20: AL | D20: ='BALANCE 2024'!H20 -> 0 | E20: ='BALANCE 2024'!I20 -> 41936476 | F20: =ROUND('INVEST ET FINANCEMENT'!D$31,0)+(H20-I20)-(D20-E20) -> 0 | G20: =ROUND('INVEST ET FINANCEMENT'!D$31,0) -> 19282845 | H20: 0 | I20: =ROUND(E20+'INVEST ET FINANCEMENT'!D$31,0) -> 61219321 | J20: =(D20-E20)+(F20-G20)-(H20-I20) -> 0
A21: 284100 | B21: Amortissements du matériel et outillage | C21: AM | D21: ='BALANCE 2024'!H21 -> 0 | E21: ='BALANCE 2024'!I21 -> 55983764 | F21: =ROUND('INVEST ET FINANCEMENT'!D$34,0)+(H21-I21)-(D21-E21) -> 0 | G21: =ROUND('INVEST ET FINANCEMENT'!D$34,0) -> 28205053 | H21: 0 | I21: =ROUND(E21+'INVEST ET FINANCEMENT'!D$34,0) -> 84188817 | J21: =(D21-E21)+(F21-G21)-(H21-I21) -> 0
A22: 284400 | B22: Amortissements du matériel de bureau et informatique | C22: AM | D22: ='BALANCE 2024'!H22 -> 0 | E22: ='BALANCE 2024'!I22 -> 12708358 | F22: =ROUND('INVEST ET FINANCEMENT'!D$37,0)+(H22-I22)-(D22-E22) -> 0 | G22: =ROUND('INVEST ET FINANCEMENT'!D$37,0) -> 5399884 | H22: 0 | I22: =ROUND(E22+'INVEST ET FINANCEMENT'!D$37,0) -> 18108242 | J22: =(D22-E22)+(F22-G22)-(H22-I22) -> 0
A23: 284500 | B23: Amortissements du matériel de transport | C23: AN | D23: ='BALANCE 2024'!H23 -> 0 | E23: ='BALANCE 2024'!I23 -> 362909076 | F23: =ROUND('INVEST ET FINANCEMENT'!D$40,0)+(H23-I23)-(D23-E23) -> 0 | G23: =ROUND('INVEST ET FINANCEMENT'!D$40,0) -> 18958378 | H23: 0 | I23: =ROUND(E23+'INVEST ET FINANCEMENT'!D$40,0) -> 381867454 | J23: =(D23-E23)+(F23-G23)-(H23-I23) -> 0
A24: 401100 | B24: Fournisseurs | C24: DJ | D24: ='BALANCE 2024'!H24 -> 0 | E24: ='BALANCE 2024'!I24 -> 72947866 | F24: =ROUND(HYPOTHESES!D$49*(1+HYPOTHESES!D$10),0)+(H24-I24)-(D24-E24) -> 486035333 | G24: =ROUND(HYPOTHESES!D$49*(1+HYPOTHESES!D$10),0) -> 490796991 | H24: 0 | I24: =ROUND(HYPOTHESES!D$49*(1+HYPOTHESES!D$10)*HYPOTHESES!D$23/360,0) -> 77709524 | J24: =(D24-E24)+(F24-G24)-(H24-I24) -> 0
A25: 409100 | B25: Fournisseurs avances et accoptes ve | C25: BH | D25: ='BALANCE 2024'!H25 -> 0 | E25: ='BALANCE 2024'!I25 -> 0 | F25: =MAX(0,(H25-I25)-(D25-E25)) -> 0 | G25: =MAX(0,(D25-E25)-(H25-I25)) -> 0 | H25: =ROUND(D25,0) -> 0 | I25: =ROUND(E25,0) -> 0 | J25: =(D25-E25)+(F25-G25)-(H25-I25) -> 0
A26: 411100 | B26: Clients | C26: BI | D26: ='BALANCE 2024'!H26 -> 452271396 | E26: ='BALANCE 2024'!I26 -> 0 | F26: =ROUND(HYPOTHESES!D$42*(1+HYPOTHESES!D$10),0) -> 885116306 | G26: =ROUND(HYPOTHESES!D$42*(1+HYPOTHESES!D$10),0)+(D26-E26)-(H26-I26) -> 870242985 | H26: =ROUND(HYPOTHESES!D$42*(1+HYPOTHESES!D$10)*HYPOTHESES!D$22/360,0) -> 467144717 | I26: 0 | J26: =(D26-E26)+(F26-G26)-(H26-I26) -> 0
A27: 422000 | B27: Personnel, rémunérations dues | C27: DK | D27: ='BALANCE 2024'!H27 -> 0 | E27: ='BALANCE 2024'!I27 -> 11147549 | F27: =ROUND(IF(HYPOTHESES!$C$48=0,0,'BALANCE 2024'!$G$27*HYPOTHESES!D$48/HYPOTHESES!$C$48),0)+(H27-I27)-(D27-E27) -> 86159431 | G27: =ROUND(IF(HYPOTHESES!$C$48=0,0,'BALANCE 2024'!$G$27*HYPOTHESES!D$48/HYPOTHESES!$C$48),0) -> 86936353 | H27: 0 | I27: =ROUND(IF(HYPOTHESES!$C$48=0,0,'BALANCE 2024'!$I$27*HYPOTHESES!D$48/HYPOTHESES!$C$48),0) -> 11924471 | J27: =(D27-E27)+(F27-G27)-(H27-I27) -> 0
A28: 431301 | B28: CNPS, retraite part employeur | C28: DK | D28: ='BALANCE 2024'!H28 -> 0 | E28: ='BALANCE 2024'!I28 -> 4859377 | F28: =ROUND(IF(HYPOTHESES!$C$48=0,0,'BALANCE 2024'!$G$28*HYPOTHESES!D$48/HYPOTHESES!$C$48),0)+(H28-I28)-(D28-E28) -> 7154830 | G28: =ROUND(IF(HYPOTHESES!$C$48=0,0,'BALANCE 2024'!$G$28*HYPOTHESES!D$48/HYPOTHESES!$C$48),0) -> 7493502 | H28: 0 | I28: =ROUND(IF(HYPOTHESES!$C$48=0,0,'BALANCE 2024'!$I$28*HYPOTHESES!D$48/HYPOTHESES!$C$48),0) -> 5198049 | J28: =(D28-E28)+(F28-G28)-(H28-I28) -> 0
A29: 431302 | B29: CNPS, retraite part salariale | C29: DK | D29: ='BALANCE 2024'!H29 -> 0 | E29: ='BALANCE 2024'!I29 -> 1202405 | F29: =ROUND(IF(HYPOTHESES!$C$48=0,0,'BALANCE 2024'!$G$29*HYPOTHESES!D$48/HYPOTHESES!$C$48),0)+(H29-I29)-(D29-E29) -> 12174245 | G29: =ROUND(IF(HYPOTHESES!$C$48=0,0,'BALANCE 2024'!$G$29*HYPOTHESES!D$48/HYPOTHESES!$C$48),0) -> 12258046 | H29: 0 | I29: =ROUND(IF(HYPOTHESES!$C$48=0,0,'BALANCE 2024'!$I$29*HYPOTHESES!D$48/HYPOTHESES!$C$48),0) -> 1286206 | J29: =(D29-E29)+(F29-G29)-(H29-I29) -> 0
A30: 431802 | B30: CMU, part salariale | C30: DK | D30: ='BALANCE 2024'!H30 -> 0 | E30: ='BALANCE 2024'!I30 -> 161938 | F30: =ROUND(IF(HYPOTHESES!$C$48=0,0,'BALANCE 2024'!$G$30*HYPOTHESES!D$48/HYPOTHESES!$C$48),0)+(H30-I30)-(D30-E30) -> 403349 | G30: =ROUND(IF(HYPOTHESES!$C$48=0,0,'BALANCE 2024'!$G$30*HYPOTHESES!D$48/HYPOTHESES!$C$48),0) -> 414635 | H30: 0 | I30: =ROUND(IF(HYPOTHESES!$C$48=0,0,'BALANCE 2024'!$I$30*HYPOTHESES!D$48/HYPOTHESES!$C$48),0) -> 173224 | J30: =(D30-E30)+(F30-G30)-(H30-I30) -> 0
A31: 433300 | B31: Assurance et organisme de sante | C31: DK | D31: ='BALANCE 2024'!H31 -> 0 | E31: ='BALANCE 2024'!I31 -> 0 | F31: =ROUND(IF(HYPOTHESES!$C$48=0,0,'BALANCE 2024'!$G$31*HYPOTHESES!D$48/HYPOTHESES!$C$48),0)+(H31-I31)-(D31-E31) -> 0 | G31: =ROUND(IF(HYPOTHESES!$C$48=0,0,'BALANCE 2024'!$G$31*HYPOTHESES!D$48/HYPOTHESES!$C$48),0) -> 0 | H31: 0 | I31: =ROUND(IF(HYPOTHESES!$C$48=0,0,'BALANCE 2024'!$I$31*HYPOTHESES!D$48/HYPOTHESES!$C$48),0) -> 0 | J31: =(D31-E31)+(F31-G31)-(H31-I31) -> 0
A32: 441000 | B32: État, impôt sur les bénéfices | C32: DK | D32: ='BALANCE 2024'!H32 -> 0 | E32: ='BALANCE 2024'!I32 -> 24232959 | F32: =ROUND(HYPOTHESES!D$56,0)+(H32-I32)-(D32-E32) -> 24232959 | G32: =ROUND(HYPOTHESES!D$56,0) -> 30838289 | H32: 0 | I32: =ROUND(HYPOTHESES!D$56,0) -> 30838289 | J32: =(D32-E32)+(F32-G32)-(H32-I32) -> 0
A33: 442800 | B33: Autres impôts et taxes | C33: DK | D33: ='BALANCE 2024'!H33 -> 0 | E33: ='BALANCE 2024'!I33 -> 725658 | F33: =ROUND(IF(HYPOTHESES!$C$46=0,0,'BALANCE 2024'!$G$33*HYPOTHESES!D$46/HYPOTHESES!$C$46),0)+(H33-I33)-(D33-E33) -> 725658 | G33: =ROUND(IF(HYPOTHESES!$C$46=0,0,'BALANCE 2024'!$G$33*HYPOTHESES!D$46/HYPOTHESES!$C$46),0) -> 776041 | H33: 0 | I33: =ROUND(IF(HYPOTHESES!$C$46=0,0,'BALANCE 2024'!$I$33*HYPOTHESES!D$46/HYPOTHESES!$C$46),0) -> 776041 | J33: =(D33-E33)+(F33-G33)-(H33-I33) -> 0
A34: 442801 | B34: FDFP, taxe d'apprentissage | C34: DK | D34: ='BALANCE 2024'!H34 -> 0 | E34: ='BALANCE 2024'!I34 -> 104066 | F34: =ROUND(IF(HYPOTHESES!$C$46=0,0,'BALANCE 2024'!$G$34*HYPOTHESES!D$46/HYPOTHESES!$C$46),0)+(H34-I34)-(D34-E34) -> 104066 | G34: =ROUND(IF(HYPOTHESES!$C$46=0,0,'BALANCE 2024'!$G$34*HYPOTHESES!D$46/HYPOTHESES!$C$46),0) -> 111291 | H34: 0 | I34: =ROUND(IF(HYPOTHESES!$C$46=0,0,'BALANCE 2024'!$I$34*HYPOTHESES!D$46/HYPOTHESES!$C$46),0) -> 111291 | J34: =(D34-E34)+(F34-G34)-(H34-I34) -> 0
A35: 442802 | B35: FDFP, formation continue | C35: DK | D35: ='BALANCE 2024'!H35 -> 0 | E35: ='BALANCE 2024'!I35 -> 156106 | F35: =ROUND(IF(HYPOTHESES!$C$46=0,0,'BALANCE 2024'!$G$35*HYPOTHESES!D$46/HYPOTHESES!$C$46),0)+(H35-I35)-(D35-E35) -> 156106 | G35: =ROUND(IF(HYPOTHESES!$C$46=0,0,'BALANCE 2024'!$G$35*HYPOTHESES!D$46/HYPOTHESES!$C$46),0) -> 166945 | H35: 0 | I35: =ROUND(IF(HYPOTHESES!$C$46=0,0,'BALANCE 2024'!$I$35*HYPOTHESES!D$46/HYPOTHESES!$C$46),0) -> 166945 | J35: =(D35-E35)+(F35-G35)-(H35-I35) -> 0
A36: 442803 | B36: FDFP, FPC à régulariser | C36: DK | D36: ='BALANCE 2024'!H36 -> 0 | E36: ='BALANCE 2024'!I36 -> 156105 | F36: =ROUND(IF(HYPOTHESES!$C$46=0,0,'BALANCE 2024'!$G$36*HYPOTHESES!D$46/HYPOTHESES!$C$46),0)+(H36-I36)-(D36-E36) -> 156105 | G36: =ROUND(IF(HYPOTHESES!$C$46=0,0,'BALANCE 2024'!$G$36*HYPOTHESES!D$46/HYPOTHESES!$C$46),0) -> 166944 | H36: 0 | I36: =ROUND(IF(HYPOTHESES!$C$46=0,0,'BALANCE 2024'!$I$36*HYPOTHESES!D$46/HYPOTHESES!$C$46),0) -> 166944 | J36: =(D36-E36)+(F36-G36)-(H36-I36) -> 0
A37: 442820 | B37: Impôt sur salaires, part patronale | C37: DK | D37: ='BALANCE 2024'!H37 -> 0 | E37: ='BALANCE 2024'!I37 -> 367610 | F37: =ROUND(IF(HYPOTHESES!$C$46=0,0,'BALANCE 2024'!$G$37*HYPOTHESES!D$46/HYPOTHESES!$C$46),0)+(H37-I37)-(D37-E37) -> 858441 | G37: =ROUND(IF(HYPOTHESES!$C$46=0,0,'BALANCE 2024'!$G$37*HYPOTHESES!D$46/HYPOTHESES!$C$46),0) -> 883965 | H37: 0 | I37: =ROUND(IF(HYPOTHESES!$C$46=0,0,'BALANCE 2024'!$I$37*HYPOTHESES!D$46/HYPOTHESES!$C$46),0) -> 393134 | J37: =(D37-E37)+(F37-G37)-(H37-I37) -> 0
A38: 442840 | B38: Patente | C38: DK | D38: ='BALANCE 2024'!H38 -> 0 | E38: ='BALANCE 2024'!I38 -> 5000000 | F38: =ROUND(IF(HYPOTHESES!$C$46=0,0,'BALANCE 2024'!$G$38*HYPOTHESES!D$46/HYPOTHESES!$C$46),0)+(H38-I38)-(D38-E38) -> 9336686 | G38: =ROUND(IF(HYPOTHESES!$C$46=0,0,'BALANCE 2024'!$G$38*HYPOTHESES!D$46/HYPOTHESES!$C$46),0) -> 9683842 | H38: 0 | I38: =ROUND(IF(HYPOTHESES!$C$46=0,0,'BALANCE 2024'!$I$38*HYPOTHESES!D$46/HYPOTHESES!$C$46),0) -> 5347156 | J38: =(D38-E38)+(F38-G38)-(H38-I38) -> 0
A39: 443300 | B39: État, TVA facturée sur travaux (en attente) | C39: DK | D39: ='BALANCE 2024'!H39 -> 0 | E39: ='BALANCE 2024'!I39 -> 52145698 | F39: =ROUND(HYPOTHESES!D$42*HYPOTHESES!D$10,0)+(H39-I39)-(D39-E39) -> 133302887 | G39: =ROUND(HYPOTHESES!D$42*HYPOTHESES!D$10,0) -> 135017742 | H39: 0 | I39: =ROUND(IF('BALANCE 2024'!$H$26=0,0,'BALANCE 2024'!$I$39*H26/'BALANCE 2024'!$H$26),0) -> 53860553 | J39: =(D39-E39)+(F39-G39)-(H39-I39) -> 0
A40: 446000 | B40: Taxe spéciale d'équipement | C40: DK | D40: ='BALANCE 2024'!H40 -> 0 | E40: ='BALANCE 2024'!I40 -> 200000 | F40: =ROUND(IF(HYPOTHESES!$C$46=0,0,'BALANCE 2024'!$G$40*HYPOTHESES!D$46/HYPOTHESES!$C$46),0)+(H40-I40)-(D40-E40) -> 212497 | G40: =ROUND(IF(HYPOTHESES!$C$46=0,0,'BALANCE 2024'!$G$40*HYPOTHESES!D$46/HYPOTHESES!$C$46),0) -> 226383 | H40: 0 | I40: =ROUND(IF(HYPOTHESES!$C$46=0,0,'BALANCE 2024'!$I$40*HYPOTHESES!D$46/HYPOTHESES!$C$46),0) -> 213886 | J40: =(D40-E40)+(F40-G40)-(H40-I40) -> 0
A41: 447201 | B41: ITS retenu à la source | C41: DK | D41: ='BALANCE 2024'!H41 -> 0 | E41: ='BALANCE 2024'!I41 -> 1631638 | F41: =ROUND(IF(HYPOTHESES!$C$48=0,0,'BALANCE 2024'!$G$41*HYPOTHESES!D$48/HYPOTHESES!$C$48),0)+(H41-I41)-(D41-E41) -> 6198651 | G41: =ROUND(IF(HYPOTHESES!$C$48=0,0,'BALANCE 2024'!$G$41*HYPOTHESES!D$48/HYPOTHESES!$C$48),0) -> 6312367 | H41: 0 | I41: =ROUND(IF(HYPOTHESES!$C$48=0,0,'BALANCE 2024'!$I$41*HYPOTHESES!D$48/HYPOTHESES!$C$48),0) -> 1745354 | J41: =(D41-E41)+(F41-G41)-(H41-I41) -> 0
A42: 462100 | B42: Associés, comptes courants | C42: DM | D42: ='BALANCE 2024'!H42 -> 0 | E42: ='BALANCE 2024'!I42 -> 3700000 | F42: =ROUND('INVEST ET FINANCEMENT'!D$53,0)+(H42-I42)-(D42-E42) -> 3700000 | G42: =ROUND('INVEST ET FINANCEMENT'!D$53,0) -> 0 | H42: 0 | I42: =ROUND('INVEST ET FINANCEMENT'!D$54,0) -> 0 | J42: =(D42-E42)+(F42-G42)-(H42-I42) -> 0
A43: 471200 | B43: Créditeurs divers (ajustements des autres dettes) | C43: DMBJ | D43: ='BALANCE 2024'!H43 -> 0 | E43: ='BALANCE 2024'!I43 -> 0 | F43: =MAX(0,(H43-I43)-(D43-E43)) -> 0 | G43: =MAX(0,(D43-E43)-(H43-I43)) -> 0 | H43: =ROUND(MAX(0,-(E43-D43+HYPOTHESES!D$31)),0) -> 0 | I43: =ROUND(MAX(0,(E43-D43+HYPOTHESES!D$31)),0) -> 0 | J43: =(D43-E43)+(F43-G43)-(H43-I43) -> 0
A44: 481200 | B44: Fournisseurs d'investissements | C44: DH | D44: ='BALANCE 2024'!H44 -> 0 | E44: ='BALANCE 2024'!I44 -> 132896547 | F44: =ROUND('INVEST ET FINANCEMENT'!D$41,0)+(H44-I44)-(D44-E44) -> 90248532 | G44: =ROUND('INVEST ET FINANCEMENT'!D$41,0) -> 16523220 | H44: 0 | I44: =ROUND(HYPOTHESES!D$28,0) -> 59171235 | J44: =(D44-E44)+(F44-G44)-(H44-I44) -> 0
A45: 521101 | B45: Banque SGCI | C45: TRESO | D45: ='BALANCE 2024'!H45 -> 122588265 | E45: ='BALANCE 2024'!I45 -> 0 | F45: =ROUND(G26+HYPOTHESES!D$51+'INVEST ET FINANCEMENT'!D$47+'INVEST ET FINANCEMENT'!D$51,0) -> 925487261 | G45: =ROUND(G26+HYPOTHESES!D$51+'INVEST ET FINANCEMENT'!D$47+'INVEST ET FINANCEMENT'!D$51,0)+(D45-E45)-(H45-I45) -> 901097419 | H45: =ROUND(MAX(0,(H99-(H46-I46))),0) -> 146978107 | I45: =ROUND(MAX(0,-(H99-(H46-I46))),0) -> 0 | J45: =(D45-E45)+(F45-G45)-(H45-I45) -> 0
A46: 571101 | B46: Caisse | C46: BS | D46: ='BALANCE 2024'!H46 -> 5545693 | E46: ='BALANCE 2024'!I46 -> 0 | F46: =ROUND(H101,0) -> 180219484 | G46: =ROUND(H101,0)+(D46-E46)-(H46-I46) -> 178417289 | H46: =ROUND(MAX(0,((D46-E46)+H101*(1-HYPOTHESES!D$30))),0) -> 7347888 | I46: =ROUND(MAX(0,-((D46-E46)+H101*(1-HYPOTHESES!D$30))),0) -> 0 | J46: =(D46-E46)+(F46-G46)-(H46-I46) -> 0
A47: 585000 | B47: Virements de fonds | C47: BS | D47: ='BALANCE 2024'!H47 -> 0 | E47: ='BALANCE 2024'!I47 -> 0 | F47: =ROUND(H101,0) -> 180219484 | G47: =ROUND(H101,0)+(D47-E47)-(H47-I47) -> 180219484 | H47: =ROUND(D47,0) -> 0 | I47: =ROUND(E47,0) -> 0 | J47: =(D47-E47)+(F47-G47)-(H47-I47) -> 0
A48: 604300 | B48: Produits d'entretien | C48: RE | D48: 0 | E48: 0 | F48: =MAX(0,(H48-I48)-(D48-E48)) -> 1338051 | G48: =MAX(0,(D48-E48)-(H48-I48)) -> 0 | H48: =ROUND(IF(HYPOTHESES!$C$43=0,0,'BALANCE 2024'!$H$48*HYPOTHESES!D$43/HYPOTHESES!$C$43),0) -> 1338051 | I48: 0 | J48: =(D48-E48)+(F48-G48)-(H48-I48) -> 0
A49: 605100 | B49: Eau | C49: RE | D49: 0 | E49: 0 | F49: =MAX(0,(H49-I49)-(D49-E49)) -> 133309 | G49: =MAX(0,(D49-E49)-(H49-I49)) -> 0 | H49: =ROUND(IF(HYPOTHESES!$C$43=0,0,'BALANCE 2024'!$H$49*HYPOTHESES!D$43/HYPOTHESES!$C$43),0) -> 133309 | I49: 0 | J49: =(D49-E49)+(F49-G49)-(H49-I49) -> 0
A50: 605200 | B50: Eléctricité | C50: RE | D50: 0 | E50: 0 | F50: =MAX(0,(H50-I50)-(D50-E50)) -> 42762672 | G50: =MAX(0,(D50-E50)-(H50-I50)) -> 0 | H50: =ROUND(IF(HYPOTHESES!$C$43=0,0,'BALANCE 2024'!$H$50*HYPOTHESES!D$43/HYPOTHESES!$C$43),0) -> 42762672 | I50: 0 | J50: =(D50-E50)+(F50-G50)-(H50-I50) -> 0
A51: 605300 | B51: Autres énergies | C51: RE | D51: 0 | E51: 0 | F51: =MAX(0,(H51-I51)-(D51-E51)) -> 21229767 | G51: =MAX(0,(D51-E51)-(H51-I51)) -> 0 | H51: =ROUND(IF(HYPOTHESES!$C$43=0,0,'BALANCE 2024'!$H$51*HYPOTHESES!D$43/HYPOTHESES!$C$43),0) -> 21229767 | I51: 0 | J51: =(D51-E51)+(F51-G51)-(H51-I51) -> 0
A52: 605500 | B52: Fournitures de bureau non stockable | C52: RE | D52: 0 | E52: 0 | F52: =MAX(0,(H52-I52)-(D52-E52)) -> 13776049 | G52: =MAX(0,(D52-E52)-(H52-I52)) -> 0 | H52: =ROUND(IF(HYPOTHESES!$C$43=0,0,'BALANCE 2024'!$H$52*HYPOTHESES!D$43/HYPOTHESES!$C$43),0) -> 13776049 | I52: 0 | J52: =(D52-E52)+(F52-G52)-(H52-I52) -> 0
A53: 605600 | B53: Achats de petit matériel et outilla | C53: RE | D53: 0 | E53: 0 | F53: =MAX(0,(H53-I53)-(D53-E53)) -> 3950407 | G53: =MAX(0,(D53-E53)-(H53-I53)) -> 0 | H53: =ROUND(IF(HYPOTHESES!$C$43=0,0,'BALANCE 2024'!$H$53*HYPOTHESES!D$43/HYPOTHESES!$C$43),0) -> 3950407 | I53: 0 | J53: =(D53-E53)+(F53-G53)-(H53-I53) -> 0
A54: 605700 | B54: Achats d'études et prestations de s | C54: RE | D54: 0 | E54: 0 | F54: =MAX(0,(H54-I54)-(D54-E54)) -> 85779542 | G54: =MAX(0,(D54-E54)-(H54-I54)) -> 0 | H54: =ROUND(IF(HYPOTHESES!$C$43=0,0,'BALANCE 2024'!$H$54*HYPOTHESES!D$43/HYPOTHESES!$C$43),0) -> 85779542 | I54: 0 | J54: =(D54-E54)+(F54-G54)-(H54-I54) -> 0
A55: 605800 | B55: Achats de materiels et equiepents | C55: RE | D55: 0 | E55: 0 | F55: =MAX(0,(H55-I55)-(D55-E55)) -> 128669313 | G55: =MAX(0,(D55-E55)-(H55-I55)) -> 0 | H55: =ROUND(HYPOTHESES!D$43-(H48+H49+H50+H51+H52+H53+H54),0) -> 128669313 | I55: 0 | J55: =(D55-E55)+(F55-G55)-(H55-I55) -> 0
A56: 616000 | B56: Transports de plis | C56: RG | D56: 0 | E56: 0 | F56: =MAX(0,(H56-I56)-(D56-E56)) -> 99569 | G56: =MAX(0,(D56-E56)-(H56-I56)) -> 0 | H56: =ROUND(IF(HYPOTHESES!$C$44=0,0,'BALANCE 2024'!$H$56*HYPOTHESES!D$44/HYPOTHESES!$C$44),0) -> 99569 | I56: 0 | J56: =(D56-E56)+(F56-G56)-(H56-I56) -> 0
A57: 618200 | B57: Transports entre ‚tablissement ou c | C57: RG | D57: 0 | E57: 0 | F57: =MAX(0,(H57-I57)-(D57-E57)) -> 1661464 | G57: =MAX(0,(D57-E57)-(H57-I57)) -> 0 | H57: =ROUND(IF(HYPOTHESES!$C$44=0,0,'BALANCE 2024'!$H$57*HYPOTHESES!D$44/HYPOTHESES!$C$44),0) -> 1661464 | I57: 0 | J57: =(D57-E57)+(F57-G57)-(H57-I57) -> 0
A58: 618300 | B58: Transports administratifs | C58: RG | D58: 0 | E58: 0 | F58: =MAX(0,(H58-I58)-(D58-E58)) -> 2289499 | G58: =MAX(0,(D58-E58)-(H58-I58)) -> 0 | H58: =ROUND(HYPOTHESES!D$44-(H56+H57),0) -> 2289499 | I58: 0 | J58: =(D58-E58)+(F58-G58)-(H58-I58) -> 0
A59: 622200 | B59: Location de batiment | C59: RH | D59: 0 | E59: 0 | F59: =MAX(0,(H59-I59)-(D59-E59)) -> 17799094 | G59: =MAX(0,(D59-E59)-(H59-I59)) -> 0 | H59: =ROUND(IF(HYPOTHESES!$C$45=0,0,'BALANCE 2024'!$H$59*HYPOTHESES!D$45/HYPOTHESES!$C$45),0) -> 17799094 | I59: 0 | J59: =(D59-E59)+(F59-G59)-(H59-I59) -> 0
A60: 624200 | B60: Entretien et réparation des biens m | C60: RH | D60: 0 | E60: 0 | F60: =MAX(0,(H60-I60)-(D60-E60)) -> 36596794 | G60: =MAX(0,(D60-E60)-(H60-I60)) -> 0 | H60: =ROUND(HYPOTHESES!D$45-(H59+H61+H62+H63+H64+H65+H66+H67),0) -> 36596794 | I60: 0 | J60: =(D60-E60)+(F60-G60)-(H60-I60) -> 0
A61: 625800 | B61: Autres primes d'assurances | C61: RH | D61: 0 | E61: 0 | F61: =MAX(0,(H61-I61)-(D61-E61)) -> 4910803 | G61: =MAX(0,(D61-E61)-(H61-I61)) -> 0 | H61: =ROUND(IF(HYPOTHESES!$C$45=0,0,'BALANCE 2024'!$H$61*HYPOTHESES!D$45/HYPOTHESES!$C$45),0) -> 4910803 | I61: 0 | J61: =(D61-E61)+(F61-G61)-(H61-I61) -> 0
A62: 626600 | B62: Documentation techniques | C62: RH | D62: 0 | E62: 0 | F62: =MAX(0,(H62-I62)-(D62-E62)) -> 34239 | G62: =MAX(0,(D62-E62)-(H62-I62)) -> 0 | H62: =ROUND(IF(HYPOTHESES!$C$45=0,0,'BALANCE 2024'!$H$62*HYPOTHESES!D$45/HYPOTHESES!$C$45),0) -> 34239 | I62: 0 | J62: =(D62-E62)+(F62-G62)-(H62-I62) -> 0
A63: 627700 | B63: Frais de colloques, séminaires, con | C63: RH | D63: 0 | E63: 0 | F63: =MAX(0,(H63-I63)-(D63-E63)) -> 62593 | G63: =MAX(0,(D63-E63)-(H63-I63)) -> 0 | H63: =ROUND(IF(HYPOTHESES!$C$45=0,0,'BALANCE 2024'!$H$63*HYPOTHESES!D$45/HYPOTHESES!$C$45),0) -> 62593 | I63: 0 | J63: =(D63-E63)+(F63-G63)-(H63-I63) -> 0
A64: 628800 | B64: Autres frais de télécommunications | C64: RH | D64: 0 | E64: 0 | F64: =MAX(0,(H64-I64)-(D64-E64)) -> 849605 | G64: =MAX(0,(D64-E64)-(H64-I64)) -> 0 | H64: =ROUND(IF(HYPOTHESES!$C$45=0,0,'BALANCE 2024'!$H$64*HYPOTHESES!D$45/HYPOTHESES!$C$45),0) -> 849605 | I64: 0 | J64: =(D64-E64)+(F64-G64)-(H64-I64) -> 0
A65: 631800 | B65: Autres frais bancaires | C65: RH | D65: 0 | E65: 0 | F65: =MAX(0,(H65-I65)-(D65-E65)) -> 24170860 | G65: =MAX(0,(D65-E65)-(H65-I65)) -> 0 | H65: =ROUND(IF(HYPOTHESES!$C$45=0,0,'BALANCE 2024'!$H$65*HYPOTHESES!D$45/HYPOTHESES!$C$45),0) -> 24170860 | I65: 0 | J65: =(D65-E65)+(F65-G65)-(H65-I65) -> 0
A66: 632800 | B66: Divers frais | C66: RH | D66: 0 | E66: 0 | F66: =MAX(0,(H66-I66)-(D66-E66)) -> 5085623 | G66: =MAX(0,(D66-E66)-(H66-I66)) -> 0 | H66: =ROUND(IF(HYPOTHESES!$C$45=0,0,'BALANCE 2024'!$H$66*HYPOTHESES!D$45/HYPOTHESES!$C$45),0) -> 5085623 | I66: 0 | J66: =(D66-E66)+(F66-G66)-(H66-I66) -> 0
A67: 638800 | B67: Charges externes diverses | C67: RH | D67: 0 | E67: 0 | F67: =MAX(0,(H67-I67)-(D67-E67)) -> 24730400 | G67: =MAX(0,(D67-E67)-(H67-I67)) -> 0 | H67: =ROUND(IF(HYPOTHESES!$C$45=0,0,'BALANCE 2024'!$H$67*HYPOTHESES!D$45/HYPOTHESES!$C$45),0) -> 24730400 | I67: 0 | J67: =(D67-E67)+(F67-G67)-(H67-I67) -> 0
A68: 641100 | B68: Impot foncier | C68: RI | D68: 0 | E68: 0 | F68: =MAX(0,(H68-I68)-(D68-E68)) -> 384995 | G68: =MAX(0,(D68-E68)-(H68-I68)) -> 0 | H68: =ROUND(IF(HYPOTHESES!$C$46=0,0,'BALANCE 2024'!$H$68*HYPOTHESES!D$46/HYPOTHESES!$C$46),0) -> 384995 | I68: 0 | J68: =(D68-E68)+(F68-G68)-(H68-I68) -> 0
A69: 641201 | B69: Patente commerciale | C69: RI | D69: 0 | E69: 0 | F69: =MAX(0,(H69-I69)-(D69-E69)) -> 9683843 | G69: =MAX(0,(D69-E69)-(H69-I69)) -> 0 | H69: =ROUND(HYPOTHESES!D$46-(H68+H70+H71+H72+H73+H74+H75+H76),0) -> 9683843 | I69: 0 | J69: =(D69-E69)+(F69-G69)-(H69-I69) -> 0
A70: 641202 | B70: Patente transport | C70: RI | D70: 0 | E70: 0 | F70: =MAX(0,(H70-I70)-(D70-E70)) -> 1656223 | G70: =MAX(0,(D70-E70)-(H70-I70)) -> 0 | H70: =ROUND(IF(HYPOTHESES!$C$46=0,0,'BALANCE 2024'!$H$70*HYPOTHESES!D$46/HYPOTHESES!$C$46),0) -> 1656223 | I70: 0 | J70: =(D70-E70)+(F70-G70)-(H70-I70) -> 0
A71: 641300 | B71: Taxes sur appointements et salaires | C71: RI | D71: 0 | E71: 0 | F71: =MAX(0,(H71-I71)-(D71-E71)) -> 883965 | G71: =MAX(0,(D71-E71)-(H71-I71)) -> 0 | H71: =ROUND(IF(HYPOTHESES!$C$46=0,0,'BALANCE 2024'!$H$71*HYPOTHESES!D$46/HYPOTHESES!$C$46),0) -> 883965 | I71: 0 | J71: =(D71-E71)+(F71-G71)-(H71-I71) -> 0
A72: 641400 | B72: Taxes d'apprentissage | C72: RI | D72: 0 | E72: 0 | F72: =MAX(0,(H72-I72)-(D72-E72)) -> 111291 | G72: =MAX(0,(D72-E72)-(H72-I72)) -> 0 | H72: =ROUND(IF(HYPOTHESES!$C$46=0,0,'BALANCE 2024'!$H$72*HYPOTHESES!D$46/HYPOTHESES!$C$46),0) -> 111291 | I72: 0 | J72: =(D72-E72)+(F72-G72)-(H72-I72) -> 0
A73: 641500 | B73: Formation professionnelle continue | C73: RI | D73: 0 | E73: 0 | F73: =MAX(0,(H73-I73)-(D73-E73)) -> 333888 | G73: =MAX(0,(D73-E73)-(H73-I73)) -> 0 | H73: =ROUND(IF(HYPOTHESES!$C$46=0,0,'BALANCE 2024'!$H$73*HYPOTHESES!D$46/HYPOTHESES!$C$46),0) -> 333888 | I73: 0 | J73: =(D73-E73)+(F73-G73)-(H73-I73) -> 0
A74: 641830 | B74: Tse | C74: RI | D74: 0 | E74: 0 | F74: =MAX(0,(H74-I74)-(D74-E74)) -> 226383 | G74: =MAX(0,(D74-E74)-(H74-I74)) -> 0 | H74: =ROUND(IF(HYPOTHESES!$C$46=0,0,'BALANCE 2024'!$H$74*HYPOTHESES!D$46/HYPOTHESES!$C$46),0) -> 226383 | I74: 0 | J74: =(D74-E74)+(F74-G74)-(H74-I74) -> 0
A75: 646200 | B75: Droits de timbre | C75: RI | D75: 0 | E75: 0 | F75: =MAX(0,(H75-I75)-(D75-E75)) -> 1845461 | G75: =MAX(0,(D75-E75)-(H75-I75)) -> 0 | H75: =ROUND(IF(HYPOTHESES!$C$46=0,0,'BALANCE 2024'!$H$75*HYPOTHESES!D$46/HYPOTHESES!$C$46),0) -> 1845461 | I75: 0 | J75: =(D75-E75)+(F75-G75)-(H75-I75) -> 0
A76: 648000 | B76: Autres impots et taxes | C76: RI | D76: 0 | E76: 0 | F76: =MAX(0,(H76-I76)-(D76-E76)) -> 776041 | G76: =MAX(0,(D76-E76)-(H76-I76)) -> 0 | H76: =ROUND(IF(HYPOTHESES!$C$46=0,0,'BALANCE 2024'!$H$76*HYPOTHESES!D$46/HYPOTHESES!$C$46),0) -> 776041 | I76: 0 | J76: =(D76-E76)+(F76-G76)-(H76-I76) -> 0
A77: 658800 | B77: Autres charges diverses | C77: RJ | D77: 0 | E77: 0 | F77: =MAX(0,(H77-I77)-(D77-E77)) -> 1425187 | G77: =MAX(0,(D77-E77)-(H77-I77)) -> 0 | H77: =ROUND(HYPOTHESES!D$47,0) -> 1425187 | I77: 0 | J77: =(D77-E77)+(F77-G77)-(H77-I77) -> 0
A78: 661100 | B78: Appointements salaires national | C78: RK | D78: 0 | E78: 0 | F78: =MAX(0,(H78-I78)-(D78-E78)) -> 63089886 | G78: =MAX(0,(D78-E78)-(H78-I78)) -> 0 | H78: =ROUND(HYPOTHESES!D$48-(H79+H80+H81+H82+H83),0) -> 63089886 | I78: 0 | J78: =(D78-E78)+(F78-G78)-(H78-I78) -> 0
A79: 661200 | B79: Primes et gratifications | C79: RK | D79: 0 | E79: 0 | F79: =MAX(0,(H79-I79)-(D79-E79)) -> 21327567 | G79: =MAX(0,(D79-E79)-(H79-I79)) -> 0 | H79: =ROUND(IF(HYPOTHESES!$C$48=0,0,'BALANCE 2024'!$H$79*HYPOTHESES!D$48/HYPOTHESES!$C$48),0) -> 21327567 | I79: 0 | J79: =(D79-E79)+(F79-G79)-(H79-I79) -> 0
A80: 661300 | B80: Congés payés | C80: RK | D80: 0 | E80: 0 | F80: =MAX(0,(H80-I80)-(D80-E80)) -> 7037068 | G80: =MAX(0,(D80-E80)-(H80-I80)) -> 0 | H80: =ROUND(IF(HYPOTHESES!$C$48=0,0,'BALANCE 2024'!$H$80*HYPOTHESES!D$48/HYPOTHESES!$C$48),0) -> 7037068 | I80: 0 | J80: =(D80-E80)+(F80-G80)-(H80-I80) -> 0
A81: 661400 | B81: Indem.preavis&licenc imposables | C81: RK | D81: 0 | E81: 0 | F81: =MAX(0,(H81-I81)-(D81-E81)) -> 7106530 | G81: =MAX(0,(D81-E81)-(H81-I81)) -> 0 | H81: =ROUND(IF(HYPOTHESES!$C$48=0,0,'BALANCE 2024'!$H$81*HYPOTHESES!D$48/HYPOTHESES!$C$48),0) -> 7106530 | I81: 0 | J81: =(D81-E81)+(F81-G81)-(H81-I81) -> 0
A82: 663400 | B82: Indemnités de transport | C82: RK | D82: 0 | E82: 0 | F82: =MAX(0,(H82-I82)-(D82-E82)) -> 7360350 | G82: =MAX(0,(D82-E82)-(H82-I82)) -> 0 | H82: =ROUND(IF(HYPOTHESES!$C$48=0,0,'BALANCE 2024'!$H$82*HYPOTHESES!D$48/HYPOTHESES!$C$48),0) -> 7360350 | I82: 0 | J82: =(D82-E82)+(F82-G82)-(H82-I82) -> 0
A83: 664104 | B83: Charges socialescr employeur | C83: RK | D83: 0 | E83: 0 | F83: =MAX(0,(H83-I83)-(D83-E83)) -> 7493502 | G83: =MAX(0,(D83-E83)-(H83-I83)) -> 0 | H83: =ROUND(IF(HYPOTHESES!$C$48=0,0,'BALANCE 2024'!$H$83*HYPOTHESES!D$48/HYPOTHESES!$C$48),0) -> 7493502 | I83: 0 | J83: =(D83-E83)+(F83-G83)-(H83-I83) -> 0
A84: 671201 | B84: Interet des emprunts ecobank | C84: RM | D84: 0 | E84: 0 | F84: =MAX(0,(H84-I84)-(D84-E84)) -> 2379530 | G84: =MAX(0,(D84-E84)-(H84-I84)) -> 0 | H84: =ROUND('INVEST ET FINANCEMENT'!D$64,0) -> 2379530 | I84: 0 | J84: =(D84-E84)+(F84-G84)-(H84-I84) -> 0
A85: 672301 | B85: Interet de credit bail bni -1 | C85: RM | D85: 0 | E85: 0 | F85: =MAX(0,(H85-I85)-(D85-E85)) -> 637182 | G85: =MAX(0,(D85-E85)-(H85-I85)) -> 0 | H85: =ROUND('INVEST ET FINANCEMENT'!D$65,0) -> 637182 | I85: 0 | J85: =(D85-E85)+(F85-G85)-(H85-I85) -> 0
A86: 681301 | B86: Dotations aux amortissements : aménagements | C86: RL | D86: 0 | E86: 0 | F86: =MAX(0,(H86-I86)-(D86-E86)) -> 19282845 | G86: =MAX(0,(D86-E86)-(H86-I86)) -> 0 | H86: =ROUND('INVEST ET FINANCEMENT'!D$31,0) -> 19282845 | I86: 0 | J86: =(D86-E86)+(F86-G86)-(H86-I86) -> 0
A87: 681302 | B87: Dotations aux amortissements : matériel et outillage | C87: RL | D87: 0 | E87: 0 | F87: =MAX(0,(H87-I87)-(D87-E87)) -> 28205053 | G87: =MAX(0,(D87-E87)-(H87-I87)) -> 0 | H87: =ROUND('INVEST ET FINANCEMENT'!D$34,0) -> 28205053 | I87: 0 | J87: =(D87-E87)+(F87-G87)-(H87-I87) -> 0
A88: 681303 | B88: Dotations aux amortissements : bureau et informatique | C88: RL | D88: 0 | E88: 0 | F88: =MAX(0,(H88-I88)-(D88-E88)) -> 5399884 | G88: =MAX(0,(D88-E88)-(H88-I88)) -> 0 | H88: =ROUND('INVEST ET FINANCEMENT'!D$37,0) -> 5399884 | I88: 0 | J88: =(D88-E88)+(F88-G88)-(H88-I88) -> 0
A89: 681304 | B89: Dotations aux amortissements : transport | C89: RL | D89: 0 | E89: 0 | F89: =MAX(0,(H89-I89)-(D89-E89)) -> 18958378 | G89: =MAX(0,(D89-E89)-(H89-I89)) -> 0 | H89: =ROUND('INVEST ET FINANCEMENT'!D$40,0) -> 18958378 | I89: 0 | J89: =(D89-E89)+(F89-G89)-(H89-I89) -> 0
A90: 691100 | B90: Dotations aux provisions pour risques et charges | C90: RL | D90: 0 | E90: 0 | F90: =MAX(0,(H90-I90)-(D90-E90)) -> 6059296 | G90: =MAX(0,(D90-E90)-(H90-I90)) -> 0 | H90: =ROUND(HYPOTHESES!D$50,0) -> 6059296 | I90: 0 | J90: =(D90-E90)+(F90-G90)-(H90-I90) -> 0
A91: 705100 | B91: Travaux facturés | C91: TC | D91: 0 | E91: 0 | F91: =MAX(0,(H91-I91)-(D91-E91)) -> 0 | G91: =MAX(0,(D91-E91)-(H91-I91)) -> 750098564 | H91: 0 | I91: =ROUND(HYPOTHESES!D$42,0) -> 750098564 | J91: =(D91-E91)+(F91-G91)-(H91-I91) -> 0
A92: 771200 | B92: Intérêts des prêts | C92: TK | D92: 0 | E92: 0 | F92: =MAX(0,(H92-I92)-(D92-E92)) -> 0 | G92: =MAX(0,(D92-E92)-(H92-I92)) -> 848594 | H92: 0 | I92: =ROUND(HYPOTHESES!D$51,0) -> 848594 | J92: =(D92-E92)+(F92-G92)-(H92-I92) -> 0
A93: 891100 | B93: Impôts sur les bénéfices | C93: RS | D93: 0 | E93: 0 | F93: =MAX(0,(H93-I93)-(D93-E93)) -> 30838289 | G93: =MAX(0,(D93-E93)-(H93-I93)) -> 0 | H93: =ROUND(IF(HYPOTHESES!D$54>=HYPOTHESES!D$55,HYPOTHESES!D$56,0),0) -> 30838289 | I93: 0 | J93: =(D93-E93)+(F93-G93)-(H93-I93) -> 0
A94: 895000 | B94: Impôt minimum forfaitaire (IMF) | C94: RS | D94: 0 | E94: 0 | F94: =MAX(0,(H94-I94)-(D94-E94)) -> 0 | G94: =MAX(0,(D94-E94)-(H94-I94)) -> 0 | H94: =ROUND(IF(HYPOTHESES!D$54<HYPOTHESES!D$55,HYPOTHESES!D$56,0),0) -> 0 | I94: 0 | J94: =(D94-E94)+(F94-G94)-(H94-I94) -> 0
B96: TOTAL BALANCE | D96: =SUM(D5:D94) -> 1713224346 | E96: =SUM(E5:E94) -> 1713224346 | F96: =SUM(F5:F94) -> 3884530906 | G96: =SUM(G5:G94) -> 3884530906 | H96: =SUM(H5:H94) -> 2429245214 | I96: =SUM(I5:I94) -> 2429245214 | J96: =SUM(J5:J94) -> 0
B97: Écart débit - crédit (doit être nul) | D97: =D96-E96 -> 0 | F97: =F96-G96 -> 0 | H97: =H96-I96 -> 0
B99: Calcul : trésorerie totale à répartir (banque + caisse) | H99: =-(SUM(H5:H44)-SUM(I5:I44)+SUM(H47:H94)-SUM(I47:I94)) -> 154325995
B100: Calcul : sorties de banque de l'exercice (crédit 521) | H100: =ROUND((G26+HYPOTHESES!D$51+'INVEST ET FINANCEMENT'!D$47+'INVEST ET FINANCEMENT'!D$51+(D45-E45)+(D46-E46)-H99)/(1-HYPOTHESES!D$29*(1-HYPOTHESES!D$30)),0) -> 901097419
B101: Calcul : approvisionnement de la caisse (% des sorties de banque) | H101: =ROUND(HYPOTHESES!D$29*H100,0) -> 180219484

Sheet BALANCE 2026
A1: BALANCE GÉNÉRALE À 6 COLONNES : EXERCICE 2026 (PRÉVISIONNEL)
A2: Ouverture = clôture de l'exercice précédent (classes 6 à 8 soldées, résultat N-1 en 13). Clôture calculée depuis les hypothèses ; mouvements = flux de l'exercice. Soldes après inventaire, avant écritures de clôture. Ne rien saisir.
D3: Soldes d'ouverture | F3: Mouvements de l'exercice | H3: Soldes de clôture | J3: Contrôle
A4: Compte | B4: Intitulé | C4: Poste | D4: Débit | E4: Crédit | F4: Débit | G4: Crédit | H4: Débit | I4: Crédit | J4: Ouv.+Mvts-Clôt.
A5: 101000 | B5: Capital social | C5: CA | D5: ='BALANCE 2025'!H5 -> 0 | E5: ='BALANCE 2025'!I5 -> 10000000 | F5: =ROUND('INVEST ET FINANCEMENT'!E$51,0)+(H5-I5)-(D5-E5) -> 0 | G5: =ROUND('INVEST ET FINANCEMENT'!E$51,0) -> 0 | H5: 0 | I5: =ROUND(E5+'INVEST ET FINANCEMENT'!E$51,0) -> 10000000 | J5: =(D5-E5)+(F5-G5)-(H5-I5) -> 0
A6: 111000 | B6: Réserve légale | C6: CF | D6: ='BALANCE 2025'!H6 -> 0 | E6: ='BALANCE 2025'!I6 -> 2000000 | F6: =ROUND(HYPOTHESES!E$58,0)+(H6-I6)-(D6-E6) -> 0 | G6: =ROUND(HYPOTHESES!E$58,0) -> 0 | H6: 0 | I6: =ROUND(E6+HYPOTHESES!E$58,0) -> 2000000 | J6: =(D6-E6)+(F6-G6)-(H6-I6) -> 0
A7: 121000 | B7: Report à nouveau | C7: CH | D7: ='BALANCE 2025'!H7 -> 0 | E7: ='BALANCE 2025'!I7 -> 844498728 | F7: =MAX(0,(H7-I7)-(D7-E7)) -> 0 | G7: =MAX(0,(D7-E7)-(H7-I7)) -> 92514868 | H7: =ROUND(MAX(0,-(E7-D7+HYPOTHESES!E$60)),0) -> 0 | I7: =ROUND(MAX(0,(E7-D7+HYPOTHESES!E$60)),0) -> 937013596 | J7: =(D7-E7)+(F7-G7)-(H7-I7) -> 0
A8: 130100 | B8: Résultat en instance d'affectation : bénéfice | C8: R13 | D8: =MAX(0,-(SUM('BALANCE 2025'!I48:I94)-SUM('BALANCE 2025'!H48:H94))) -> 0 | E8: =MAX(0,(SUM('BALANCE 2025'!I48:I94)-SUM('BALANCE 2025'!H48:H94))) -> 92514868 | F8: =MAX(0,(H8-I8)-(D8-E8)) -> 92514868 | G8: =MAX(0,(D8-E8)-(H8-I8)) -> 0 | H8: 0 | I8: 0 | J8: =(D8-E8)+(F8-G8)-(H8-I8) -> 0
A9: 162002 | B9: Emprunts auprès des établissements de crédit (BNI) | C9: DA | D9: ='BALANCE 2025'!H9 -> 0 | E9: ='BALANCE 2025'!I9 -> 0 | F9: =ROUND('INVEST ET FINANCEMENT'!E$47,0)+(H9-I9)-(D9-E9) -> 0 | G9: =ROUND('INVEST ET FINANCEMENT'!E$47,0) -> 0 | H9: 0 | I9: =ROUND(E9+'INVEST ET FINANCEMENT'!E$47-'INVEST ET FINANCEMENT'!E$48,0) -> 0 | J9: =(D9-E9)+(F9-G9)-(H9-I9) -> 0
A10: 173060 | B10: Dettes de location-acquisition | C10: DB | D10: ='BALANCE 2025'!H10 -> 0 | E10: ='BALANCE 2025'!I10 -> 0 | F10: =ROUND('INVEST ET FINANCEMENT'!E$49,0) -> 0 | G10: =ROUND('INVEST ET FINANCEMENT'!E$49,0)+(D10-E10)-(H10-I10) -> 0 | H10: 0 | I10: =ROUND(E10-'INVEST ET FINANCEMENT'!E$49,0) -> 0 | J10: =(D10-E10)+(F10-G10)-(H10-I10) -> 0
A11: 196100 | B11: Provisions pour pensions et obligations similaires (IFC) | C11: DC | D11: ='BALANCE 2025'!H11 -> 0 | E11: ='BALANCE 2025'!I11 -> 27333192 | F11: =ROUND(HYPOTHESES!E$20,0)+(H11-I11)-(D11-E11) -> 0 | G11: =ROUND(HYPOTHESES!E$20,0) -> 6059296 | H11: 0 | I11: =ROUND(E11+HYPOTHESES!E$20,0) -> 33392488 | J11: =(D11-E11)+(F11-G11)-(H11-I11) -> 0
A12: 234100 | B12: Aménagements, agencements et installations techniques | C12: AL | D12: ='BALANCE 2025'!H12 -> 103601492 | E12: ='BALANCE 2025'!I12 -> 0 | F12: =ROUND('INVEST ET FINANCEMENT'!E$9,0) -> 0 | G12: =ROUND('INVEST ET FINANCEMENT'!E$9,0)+(D12-E12)-(H12-I12) -> 0 | H12: =ROUND(D12+'INVEST ET FINANCEMENT'!E$9,0) -> 103601492 | I12: 0 | J12: =(D12-E12)+(F12-G12)-(H12-I12) -> 0
A13: 241100 | B13: Matériel industriel | C13: AM | D13: ='BALANCE 2025'!H13 -> 313845268 | E13: ='BALANCE 2025'!I13 -> 0 | F13: =ROUND('INVEST ET FINANCEMENT'!E$10,0) -> 30000000 | G13: =ROUND('INVEST ET FINANCEMENT'!E$10,0)+(D13-E13)-(H13-I13) -> 0 | H13: =ROUND(D13+'INVEST ET FINANCEMENT'!E$10,0) -> 343845268 | I13: 0 | J13: =(D13-E13)+(F13-G13)-(H13-I13) -> 0
A14: 244100 | B14: Matériel de bureau | C14: AM | D14: ='BALANCE 2025'!H14 -> 9306956 | E14: ='BALANCE 2025'!I14 -> 0 | F14: =MAX(0,(H14-I14)-(D14-E14)) -> 0 | G14: =MAX(0,(D14-E14)-(H14-I14)) -> 0 | H14: =ROUND(D14,0) -> 9306956 | I14: 0 | J14: =(D14-E14)+(F14-G14)-(H14-I14) -> 0
A15: 244200 | B15: Matériel informatique | C15: AM | D15: ='BALANCE 2025'!H15 -> 13910459 | E15: ='BALANCE 2025'!I15 -> 0 | F15: =ROUND('INVEST ET FINANCEMENT'!E$11,0) -> 5000000 | G15: =ROUND('INVEST ET FINANCEMENT'!E$11,0)+(D15-E15)-(H15-I15) -> 0 | H15: =ROUND(D15+'INVEST ET FINANCEMENT'!E$11,0) -> 18910459 | I15: 0 | J15: =(D15-E15)+(F15-G15)-(H15-I15) -> 0
A16: 245100 | B16: Matériel automobile | C16: AN | D16: ='BALANCE 2025'!H16 -> 423638205 | E16: ='BALANCE 2025'!I16 -> 0 | F16: =ROUND('INVEST ET FINANCEMENT'!E$12,0) -> 0 | G16: =ROUND('INVEST ET FINANCEMENT'!E$12,0)+(D16-E16)-(H16-I16) -> 0 | H16: =ROUND(D16+'INVEST ET FINANCEMENT'!E$12,0) -> 423638205 | I16: 0 | J16: =(D16-E16)+(F16-G16)-(H16-I16) -> 0
A17: 245600 | B17: Matériel de transport en location-acquisition | C17: AN | D17: ='BALANCE 2025'!H17 -> 28619694 | E17: ='BALANCE 2025'!I17 -> 0 | F17: =MAX(0,(H17-I17)-(D17-E17)) -> 0 | G17: =MAX(0,(D17-E17)-(H17-I17)) -> 0 | H17: =ROUND(D17,0) -> 28619694 | I17: 0 | J17: =(D17-E17)+(F17-G17)-(H17-I17) -> 0
A18: 271800 | B18: Autres prêts et créances | C18: AS | D18: ='BALANCE 2025'!H18 -> 25000000 | E18: ='BALANCE 2025'!I18 -> 0 | F18: =MAX(0,(H18-I18)-(D18-E18)) -> 0 | G18: =MAX(0,(D18-E18)-(H18-I18)) -> 0 | H18: =ROUND(D18,0) -> 25000000 | I18: 0 | J18: =(D18-E18)+(F18-G18)-(H18-I18) -> 0
A19: 275100 | B19: Dépôts et cautionnements versés | C19: AS | D19: ='BALANCE 2025'!H19 -> 231420138 | E19: ='BALANCE 2025'!I19 -> 0 | F19: =ROUND('INVEST ET FINANCEMENT'!E$13,0) -> 0 | G19: =ROUND('INVEST ET FINANCEMENT'!E$13,0)+(D19-E19)-(H19-I19) -> 0 | H19: =ROUND(D19+'INVEST ET FINANCEMENT'!E$13,0) -> 231420138 | I19: 0 | J19: =(D19-E19)+(F19-G19)-(H19-I19) -> 0
A20: 283400 | B20: Amortissements des aménagements, agencements | C20: AL | D20: ='BALANCE 2025'!H20 -> 0 | E20: ='BALANCE 2025'!I20 -> 61219321 | F20: =ROUND('INVEST ET FINANCEMENT'!E$31,0)+(H20-I20)-(D20-E20) -> 0 | G20: =ROUND('INVEST ET FINANCEMENT'!E$31,0) -> 19282845 | H20: 0 | I20: =ROUND(E20+'INVEST ET FINANCEMENT'!E$31,0) -> 80502166 | J20: =(D20-E20)+(F20-G20)-(H20-I20) -> 0
A21: 284100 | B21: Amortissements du matériel et outillage | C21: AM | D21: ='BALANCE 2025'!H21 -> 0 | E21: ='BALANCE 2025'!I21 -> 84188817 | F21: =ROUND('INVEST ET FINANCEMENT'!E$34,0)+(H21-I21)-(D21-E21) -> 0 | G21: =ROUND('INVEST ET FINANCEMENT'!E$34,0) -> 50854932 | H21: 0 | I21: =ROUND(E21+'INVEST ET FINANCEMENT'!E$34,0) -> 135043749 | J21: =(D21-E21)+(F21-G21)-(H21-I21) -> 0
A22: 284400 | B22: Amortissements du matériel de bureau et informatique | C22: AM | D22: ='BALANCE 2025'!H22 -> 0 | E22: ='BALANCE 2025'!I22 -> 18108242 | F22: =ROUND('INVEST ET FINANCEMENT'!E$37,0)+(H22-I22)-(D22-E22) -> 0 | G22: =ROUND('INVEST ET FINANCEMENT'!E$37,0) -> 7609173 | H22: 0 | I22: =ROUND(E22+'INVEST ET FINANCEMENT'!E$37,0) -> 25717415 | J22: =(D22-E22)+(F22-G22)-(H22-I22) -> 0
A23: 284500 | B23: Amortissements du matériel de transport | C23: AN | D23: ='BALANCE 2025'!H23 -> 0 | E23: ='BALANCE 2025'!I23 -> 381867454 | F23: =ROUND('INVEST ET FINANCEMENT'!E$40,0)+(H23-I23)-(D23-E23) -> 0 | G23: =ROUND('INVEST ET FINANCEMENT'!E$40,0) -> 15958378 | H23: 0 | I23: =ROUND(E23+'INVEST ET FINANCEMENT'!E$40,0) -> 397825832 | J23: =(D23-E23)+(F23-G23)-(H23-I23) -> 0
A24: 401100 | B24: Fournisseurs | C24: DJ | D24: ='BALANCE 2025'!H24 -> 0 | E24: ='BALANCE 2025'!I24 -> 77709524 | F24: =ROUND(HYPOTHESES!E$49*(1+HYPOTHESES!E$10),0)+(H24-I24)-(D24-E24) -> 511451366 | G24: =ROUND(HYPOTHESES!E$49*(1+HYPOTHESES!E$10),0) -> 515336842 | H24: 0 | I24: =ROUND(HYPOTHESES!E$49*(1+HYPOTHESES!E$10)*HYPOTHESES!E$23/360,0) -> 81595000 | J24: =(D24-E24)+(F24-G24)-(H24-I24) -> 0
A25: 409100 | B25: Fournisseurs avances et accoptes ve | C25: BH | D25: ='BALANCE 2025'!H25 -> 0 | E25: ='BALANCE 2025'!I25 -> 0 | F25: =MAX(0,(H25-I25)-(D25-E25)) -> 0 | G25: =MAX(0,(D25-E25)-(H25-I25)) -> 0 | H25: =ROUND(D25,0) -> 0 | I25: =ROUND(E25,0) -> 0 | J25: =(D25-E25)+(F25-G25)-(H25-I25) -> 0
A26: 411100 | B26: Clients | C26: BI | D26: ='BALANCE 2025'!H26 -> 467144717 | E26: ='BALANCE 2025'!I26 -> 0 | F26: =ROUND(HYPOTHESES!E$42*(1+HYPOTHESES!E$10),0) -> 929372121 | G26: =ROUND(HYPOTHESES!E$42*(1+HYPOTHESES!E$10),0)+(D26-E26)-(H26-I26) -> 887943761 | H26: =ROUND(HYPOTHESES!E$42*(1+HYPOTHESES!E$10)*HYPOTHESES!E$22/360,0) -> 508573077 | I26: 0 | J26: =(D26-E26)+(F26-G26)-(H26-I26) -> 0
A27: 422000 | B27: Personnel, rémunérations dues | C27: DK | D27: ='BALANCE 2025'!H27 -> 0 | E27: ='BALANCE 2025'!I27 -> 11924471 | F27: =ROUND(IF(HYPOTHESES!$C$48=0,0,'BALANCE 2024'!$G$27*HYPOTHESES!E$48/HYPOTHESES!$C$48),0)+(H27-I27)-(D27-E27) -> 90686947 | G27: =ROUND(IF(HYPOTHESES!$C$48=0,0,'BALANCE 2024'!$G$27*HYPOTHESES!E$48/HYPOTHESES!$C$48),0) -> 91283171 | H27: 0 | I27: =ROUND(IF(HYPOTHESES!$C$48=0,0,'BALANCE 2024'!$I$27*HYPOTHESES!E$48/HYPOTHESES!$C$48),0) -> 12520695 | J27: =(D27-E27)+(F27-G27)-(H27-I27) -> 0
A28: 431301 | B28: CNPS, retraite part employeur | C28: DK | D28: ='BALANCE 2025'!H28 -> 0 | E28: ='BALANCE 2025'!I28 -> 5198049 | F28: =ROUND(IF(HYPOTHESES!$C$48=0,0,'BALANCE 2024'!$G$28*HYPOTHESES!E$48/HYPOTHESES!$C$48),0)+(H28-I28)-(D28-E28) -> 7608275 | G28: =ROUND(IF(HYPOTHESES!$C$48=0,0,'BALANCE 2024'!$G$28*HYPOTHESES!E$48/HYPOTHESES!$C$48),0) -> 7868177 | H28: 0 | I28: =ROUND(IF(HYPOTHESES!$C$48=0,0,'BALANCE 2024'!$I$28*HYPOTHESES!E$48/HYPOTHESES!$C$48),0) -> 5457951 | J28: =(D28-E28)+(F28-G28)-(H28-I28) -> 0
A29: 431302 | B29: CNPS, retraite part salariale | C29: DK | D29: ='BALANCE 2025'!H29 -> 0 | E29: ='BALANCE 2025'!I29 -> 1286206 | F29: =ROUND(IF(HYPOTHESES!$C$48=0,0,'BALANCE 2024'!$G$29*HYPOTHESES!E$48/HYPOTHESES!$C$48),0)+(H29-I29)-(D29-E29) -> 12806638 | G29: =ROUND(IF(HYPOTHESES!$C$48=0,0,'BALANCE 2024'!$G$29*HYPOTHESES!E$48/HYPOTHESES!$C$48),0) -> 12870948 | H29: 0 | I29: =ROUND(IF(HYPOTHESES!$C$48=0,0,'BALANCE 2024'!$I$29*HYPOTHESES!E$48/HYPOTHESES!$C$48),0) -> 1350516 | J29: =(D29-E29)+(F29-G29)-(H29-I29) -> 0
A30: 431802 | B30: CMU, part salariale | C30: DK | D30: ='BALANCE 2025'!H30 -> 0 | E30: ='BALANCE 2025'!I30 -> 173224 | F30: =ROUND(IF(HYPOTHESES!$C$48=0,0,'BALANCE 2024'!$G$30*HYPOTHESES!E$48/HYPOTHESES!$C$48),0)+(H30-I30)-(D30-E30) -> 426706 | G30: =ROUND(IF(HYPOTHESES!$C$48=0,0,'BALANCE 2024'!$G$30*HYPOTHESES!E$48/HYPOTHESES!$C$48),0) -> 435367 | H30: 0 | I30: =ROUND(IF(HYPOTHESES!$C$48=0,0,'BALANCE 2024'!$I$30*HYPOTHESES!E$48/HYPOTHESES!$C$48),0) -> 181885 | J30: =(D30-E30)+(F30-G30)-(H30-I30) -> 0
A31: 433300 | B31: Assurance et organisme de sante | C31: DK | D31: ='BALANCE 2025'!H31 -> 0 | E31: ='BALANCE 2025'!I31 -> 0 | F31: =ROUND(IF(HYPOTHESES!$C$48=0,0,'BALANCE 2024'!$G$31*HYPOTHESES!E$48/HYPOTHESES!$C$48),0)+(H31-I31)-(D31-E31) -> 0 | G31: =ROUND(IF(HYPOTHESES!$C$48=0,0,'BALANCE 2024'!$G$31*HYPOTHESES!E$48/HYPOTHESES!$C$48),0) -> 0 | H31: 0 | I31: =ROUND(IF(HYPOTHESES!$C$48=0,0,'BALANCE 2024'!$I$31*HYPOTHESES!E$48/HYPOTHESES!$C$48),0) -> 0 | J31: =(D31-E31)+(F31-G31)-(H31-I31) -> 0
A32: 441000 | B32: État, impôt sur les bénéfices | C32: DK | D32: ='BALANCE 2025'!H32 -> 0 | E32: ='BALANCE 2025'!I32 -> 30838289 | F32: =ROUND(HYPOTHESES!E$56,0)+(H32-I32)-(D32-E32) -> 30838289 | G32: =ROUND(HYPOTHESES!E$56,0) -> 28670509 | H32: 0 | I32: =ROUND(HYPOTHESES!E$56,0) -> 28670509 | J32: =(D32-E32)+(F32-G32)-(H32-I32) -> 0
A33: 442800 | B33: Autres impôts et taxes | C33: DK | D33: ='BALANCE 2025'!H33 -> 0 | E33: ='BALANCE 2025'!I33 -> 776041 | F33: =ROUND(IF(HYPOTHESES!$C$46=0,0,'BALANCE 2024'!$G$33*HYPOTHESES!E$46/HYPOTHESES!$C$46),0)+(H33-I33)-(D33-E33) -> 776041 | G33: =ROUND(IF(HYPOTHESES!$C$46=0,0,'BALANCE 2024'!$G$33*HYPOTHESES!E$46/HYPOTHESES!$C$46),0) -> 814843 | H33: 0 | I33: =ROUND(IF(HYPOTHESES!$C$46=0,0,'BALANCE 2024'!$I$33*HYPOTHESES!E$46/HYPOTHESES!$C$46),0) -> 814843 | J33: =(D33-E33)+(F33-G33)-(H33-I33) -> 0
A34: 442801 | B34: FDFP, taxe d'apprentissage | C34: DK | D34: ='BALANCE 2025'!H34 -> 0 | E34: ='BALANCE 2025'!I34 -> 111291 | F34: =ROUND(IF(HYPOTHESES!$C$46=0,0,'BALANCE 2024'!$G$34*HYPOTHESES!E$46/HYPOTHESES!$C$46),0)+(H34-I34)-(D34-E34) -> 111291 | G34: =ROUND(IF(HYPOTHESES!$C$46=0,0,'BALANCE 2024'!$G$34*HYPOTHESES!E$46/HYPOTHESES!$C$46),0) -> 116856 | H34: 0 | I34: =ROUND(IF(HYPOTHESES!$C$46=0,0,'BALANCE 2024'!$I$34*HYPOTHESES!E$46/HYPOTHESES!$C$46),0) -> 116856 | J34: =(D34-E34)+(F34-G34)-(H34-I34) -> 0
A35: 442802 | B35: FDFP, formation continue | C35: DK | D35: ='BALANCE 2025'!H35 -> 0 | E35: ='BALANCE 2025'!I35 -> 166945 | F35: =ROUND(IF(HYPOTHESES!$C$46=0,0,'BALANCE 2024'!$G$35*HYPOTHESES!E$46/HYPOTHESES!$C$46),0)+(H35-I35)-(D35-E35) -> 166945 | G35: =ROUND(IF(HYPOTHESES!$C$46=0,0,'BALANCE 2024'!$G$35*HYPOTHESES!E$46/HYPOTHESES!$C$46),0) -> 175292 | H35: 0 | I35: =ROUND(IF(HYPOTHESES!$C$46=0,0,'BALANCE 2024'!$I$35*HYPOTHESES!E$46/HYPOTHESES!$C$46),0) -> 175292 | J35: =(D35-E35)+(F35-G35)-(H35-I35) -> 0
A36: 442803 | B36: FDFP, FPC à régulariser | C36: DK | D36: ='BALANCE 2025'!H36 -> 0 | E36: ='BALANCE 2025'!I36 -> 166944 | F36: =ROUND(IF(HYPOTHESES!$C$46=0,0,'BALANCE 2024'!$G$36*HYPOTHESES!E$46/HYPOTHESES!$C$46),0)+(H36-I36)-(D36-E36) -> 166944 | G36: =ROUND(IF(HYPOTHESES!$C$46=0,0,'BALANCE 2024'!$G$36*HYPOTHESES!E$46/HYPOTHESES!$C$46),0) -> 175291 | H36: 0 | I36: =ROUND(IF(HYPOTHESES!$C$46=0,0,'BALANCE 2024'!$I$36*HYPOTHESES!E$46/HYPOTHESES!$C$46),0) -> 175291 | J36: =(D36-E36)+(F36-G36)-(H36-I36) -> 0
A37: 442820 | B37: Impôt sur salaires, part patronale | C37: DK | D37: ='BALANCE 2025'!H37 -> 0 | E37: ='BALANCE 2025'!I37 -> 393134 | F37: =ROUND(IF(HYPOTHESES!$C$46=0,0,'BALANCE 2024'!$G$37*HYPOTHESES!E$46/HYPOTHESES!$C$46),0)+(H37-I37)-(D37-E37) -> 908507 | G37: =ROUND(IF(HYPOTHESES!$C$46=0,0,'BALANCE 2024'!$G$37*HYPOTHESES!E$46/HYPOTHESES!$C$46),0) -> 928163 | H37: 0 | I37: =ROUND(IF(HYPOTHESES!$C$46=0,0,'BALANCE 2024'!$I$37*HYPOTHESES!E$46/HYPOTHESES!$C$46),0) -> 412790 | J37: =(D37-E37)+(F37-G37)-(H37-I37) -> 0
A38: 442840 | B38: Patente | C38: DK | D38: ='BALANCE 2025'!H38 -> 0 | E38: ='BALANCE 2025'!I38 -> 5347156 | F38: =ROUND(IF(HYPOTHESES!$C$46=0,0,'BALANCE 2024'!$G$38*HYPOTHESES!E$46/HYPOTHESES!$C$46),0)+(H38-I38)-(D38-E38) -> 9900676 | G38: =ROUND(IF(HYPOTHESES!$C$46=0,0,'BALANCE 2024'!$G$38*HYPOTHESES!E$46/HYPOTHESES!$C$46),0) -> 10168034 | H38: 0 | I38: =ROUND(IF(HYPOTHESES!$C$46=0,0,'BALANCE 2024'!$I$38*HYPOTHESES!E$46/HYPOTHESES!$C$46),0) -> 5614514 | J38: =(D38-E38)+(F38-G38)-(H38-I38) -> 0
A39: 443300 | B39: État, TVA facturée sur travaux (en attente) | C39: DK | D39: ='BALANCE 2025'!H39 -> 0 | E39: ='BALANCE 2025'!I39 -> 53860553 | F39: =ROUND(HYPOTHESES!E$42*HYPOTHESES!E$10,0)+(H39-I39)-(D39-E39) -> 136992049 | G39: =ROUND(HYPOTHESES!E$42*HYPOTHESES!E$10,0) -> 141768629 | H39: 0 | I39: =ROUND(IF('BALANCE 2024'!$H$26=0,0,'BALANCE 2024'!$I$39*H26/'BALANCE 2024'!$H$26),0) -> 58637133 | J39: =(D39-E39)+(F39-G39)-(H39-I39) -> 0
A40: 446000 | B40: Taxe spéciale d'équipement | C40: DK | D40: ='BALANCE 2025'!H40 -> 0 | E40: ='BALANCE 2025'!I40 -> 213886 | F40: =ROUND(IF(HYPOTHESES!$C$46=0,0,'BALANCE 2024'!$G$40*HYPOTHESES!E$46/HYPOTHESES!$C$46),0)+(H40-I40)-(D40-E40) -> 227007 | G40: =ROUND(IF(HYPOTHESES!$C$46=0,0,'BALANCE 2024'!$G$40*HYPOTHESES!E$46/HYPOTHESES!$C$46),0) -> 237702 | H40: 0 | I40: =ROUND(IF(HYPOTHESES!$C$46=0,0,'BALANCE 2024'!$I$40*HYPOTHESES!E$46/HYPOTHESES!$C$46),0) -> 224581 | J40: =(D40-E40)+(F40-G40)-(H40-I40) -> 0
A41: 447201 | B41: ITS retenu à la source | C41: DK | D41: ='BALANCE 2025'!H41 -> 0 | E41: ='BALANCE 2025'!I41 -> 1745354 | F41: =ROUND(IF(HYPOTHESES!$C$48=0,0,'BALANCE 2024'!$G$41*HYPOTHESES!E$48/HYPOTHESES!$C$48),0)+(H41-I41)-(D41-E41) -> 6540718 | G41: =ROUND(IF(HYPOTHESES!$C$48=0,0,'BALANCE 2024'!$G$41*HYPOTHESES!E$48/HYPOTHESES!$C$48),0) -> 6627986 | H41: 0 | I41: =ROUND(IF(HYPOTHESES!$C$48=0,0,'BALANCE 2024'!$I$41*HYPOTHESES!E$48/HYPOTHESES!$C$48),0) -> 1832622 | J41: =(D41-E41)+(F41-G41)-(H41-I41) -> 0
A42: 462100 | B42: Associés, comptes courants | C42: DM | D42: ='BALANCE 2025'!H42 -> 0 | E42: ='BALANCE 2025'!I42 -> 0 | F42: =ROUND('INVEST ET FINANCEMENT'!E$53,0)+(H42-I42)-(D42-E42) -> 0 | G42: =ROUND('INVEST ET FINANCEMENT'!E$53,0) -> 0 | H42: 0 | I42: =ROUND('INVEST ET FINANCEMENT'!E$54,0) -> 0 | J42: =(D42-E42)+(F42-G42)-(H42-I42) -> 0
A43: 471200 | B43: Créditeurs divers (ajustements des autres dettes) | C43: DMBJ | D43: ='BALANCE 2025'!H43 -> 0 | E43: ='BALANCE 2025'!I43 -> 0 | F43: =MAX(0,(H43-I43)-(D43-E43)) -> 0 | G43: =MAX(0,(D43-E43)-(H43-I43)) -> 0 | H43: =ROUND(MAX(0,-(E43-D43+HYPOTHESES!E$31)),0) -> 0 | I43: =ROUND(MAX(0,(E43-D43+HYPOTHESES!E$31)),0) -> 0 | J43: =(D43-E43)+(F43-G43)-(H43-I43) -> 0
A44: 481200 | B44: Fournisseurs d'investissements | C44: DH | D44: ='BALANCE 2025'!H44 -> 0 | E44: ='BALANCE 2025'!I44 -> 59171235 | F44: =ROUND('INVEST ET FINANCEMENT'!E$41,0)+(H44-I44)-(D44-E44) -> 81435124 | G44: =ROUND('INVEST ET FINANCEMENT'!E$41,0) -> 35000000 | H44: 0 | I44: =ROUND(HYPOTHESES!E$28,0) -> 12736111 | J44: =(D44-E44)+(F44-G44)-(H44-I44) -> 0
A45: 521101 | B45: Banque SGCI | C45: TRESO | D45: ='BALANCE 2025'!H45 -> 146978107 | E45: ='BALANCE 2025'!I45 -> 0 | F45: =ROUND(G26+HYPOTHESES!E$51+'INVEST ET FINANCEMENT'!E$47+'INVEST ET FINANCEMENT'!E$51,0) -> 888792355 | G45: =ROUND(G26+HYPOTHESES!E$51+'INVEST ET FINANCEMENT'!E$47+'INVEST ET FINANCEMENT'!E$51,0)+(D45-E45)-(H45-I45) -> 819649576 | H45: =ROUND(MAX(0,(H99-(H46-I46))),0) -> 216120886 | I45: =ROUND(MAX(0,-(H99-(H46-I46))),0) -> 0 | J45: =(D45-E45)+(F45-G45)-(H45-I45) -> 0
A46: 571101 | B46: Caisse | C46: BS | D46: ='BALANCE 2025'!H46 -> 7347888 | E46: ='BALANCE 2025'!I46 -> 0 | F46: =ROUND(H101,0) -> 163929915 | G46: =ROUND(H101,0)+(D46-E46)-(H46-I46) -> 162290616 | H46: =ROUND(MAX(0,((D46-E46)+H101*(1-HYPOTHESES!E$30))),0) -> 8987187 | I46: =ROUND(MAX(0,-((D46-E46)+H101*(1-HYPOTHESES!E$30))),0) -> 0 | J46: =(D46-E46)+(F46-G46)-(H46-I46) -> 0
A47: 585000 | B47: Virements de fonds | C47: BS | D47: ='BALANCE 2025'!H47 -> 0 | E47: ='BALANCE 2025'!I47 -> 0 | F47: =ROUND(H101,0) -> 163929915 | G47: =ROUND(H101,0)+(D47-E47)-(H47-I47) -> 163929915 | H47: =ROUND(D47,0) -> 0 | I47: =ROUND(E47,0) -> 0 | J47: =(D47-E47)+(F47-G47)-(H47-I47) -> 0
A48: 604300 | B48: Produits d'entretien | C48: RE | D48: 0 | E48: 0 | F48: =MAX(0,(H48-I48)-(D48-E48)) -> 1404953 | G48: =MAX(0,(D48-E48)-(H48-I48)) -> 0 | H48: =ROUND(IF(HYPOTHESES!$C$43=0,0,'BALANCE 2024'!$H$48*HYPOTHESES!E$43/HYPOTHESES!$C$43),0) -> 1404953 | I48: 0 | J48: =(D48-E48)+(F48-G48)-(H48-I48) -> 0
A49: 605100 | B49: Eau | C49: RE | D49: 0 | E49: 0 | F49: =MAX(0,(H49-I49)-(D49-E49)) -> 139974 | G49: =MAX(0,(D49-E49)-(H49-I49)) -> 0 | H49: =ROUND(IF(HYPOTHESES!$C$43=0,0,'BALANCE 2024'!$H$49*HYPOTHESES!E$43/HYPOTHESES!$C$43),0) -> 139974 | I49: 0 | J49: =(D49-E49)+(F49-G49)-(H49-I49) -> 0
A50: 605200 | B50: Eléctricité | C50: RE | D50: 0 | E50: 0 | F50: =MAX(0,(H50-I50)-(D50-E50)) -> 44900806 | G50: =MAX(0,(D50-E50)-(H50-I50)) -> 0 | H50: =ROUND(IF(HYPOTHESES!$C$43=0,0,'BALANCE 2024'!$H$50*HYPOTHESES!E$43/HYPOTHESES!$C$43),0) -> 44900806 | I50: 0 | J50: =(D50-E50)+(F50-G50)-(H50-I50) -> 0
A51: 605300 | B51: Autres énergies | C51: RE | D51: 0 | E51: 0 | F51: =MAX(0,(H51-I51)-(D51-E51)) -> 22291255 | G51: =MAX(0,(D51-E51)-(H51-I51)) -> 0 | H51: =ROUND(IF(HYPOTHESES!$C$43=0,0,'BALANCE 2024'!$H$51*HYPOTHESES!E$43/HYPOTHESES!$C$43),0) -> 22291255 | I51: 0 | J51: =(D51-E51)+(F51-G51)-(H51-I51) -> 0
A52: 605500 | B52: Fournitures de bureau non stockable | C52: RE | D52: 0 | E52: 0 | F52: =MAX(0,(H52-I52)-(D52-E52)) -> 14464851 | G52: =MAX(0,(D52-E52)-(H52-I52)) -> 0 | H52: =ROUND(IF(HYPOTHESES!$C$43=0,0,'BALANCE 2024'!$H$52*HYPOTHESES!E$43/HYPOTHESES!$C$43),0) -> 14464851 | I52: 0 | J52: =(D52-E52)+(F52-G52)-(H52-I52) -> 0
A53: 605600 | B53: Achats de petit matériel et outilla | C53: RE | D53: 0 | E53: 0 | F53: =MAX(0,(H53-I53)-(D53-E53)) -> 4147927 | G53: =MAX(0,(D53-E53)-(H53-I53)) -> 0 | H53: =ROUND(IF(HYPOTHESES!$C$43=0,0,'BALANCE 2024'!$H$53*HYPOTHESES!E$43/HYPOTHESES!$C$43),0) -> 4147927 | I53: 0 | J53: =(D53-E53)+(F53-G53)-(H53-I53) -> 0
A54: 605700 | B54: Achats d'études et prestations de s | C54: RE | D54: 0 | E54: 0 | F54: =MAX(0,(H54-I54)-(D54-E54)) -> 90068520 | G54: =MAX(0,(D54-E54)-(H54-I54)) -> 0 | H54: =ROUND(IF(HYPOTHESES!$C$43=0,0,'BALANCE 2024'!$H$54*HYPOTHESES!E$43/HYPOTHESES!$C$43),0) -> 90068520 | I54: 0 | J54: =(D54-E54)+(F54-G54)-(H54-I54) -> 0
A55: 605800 | B55: Achats de materiels et equiepents | C55: RE | D55: 0 | E55: 0 | F55: =MAX(0,(H55-I55)-(D55-E55)) -> 135102780 | G55: =MAX(0,(D55-E55)-(H55-I55)) -> 0 | H55: =ROUND(HYPOTHESES!E$43-(H48+H49+H50+H51+H52+H53+H54),0) -> 135102780 | I55: 0 | J55: =(D55-E55)+(F55-G55)-(H55-I55) -> 0
A56: 616000 | B56: Transports de plis | C56: RG | D56: 0 | E56: 0 | F56: =MAX(0,(H56-I56)-(D56-E56)) -> 104548 | G56: =MAX(0,(D56-E56)-(H56-I56)) -> 0 | H56: =ROUND(IF(HYPOTHESES!$C$44=0,0,'BALANCE 2024'!$H$56*HYPOTHESES!E$44/HYPOTHESES!$C$44),0) -> 104548 | I56: 0 | J56: =(D56-E56)+(F56-G56)-(H56-I56) -> 0
A57: 618200 | B57: Transports entre ‚tablissement ou c | C57: RG | D57: 0 | E57: 0 | F57: =MAX(0,(H57-I57)-(D57-E57)) -> 1744538 | G57: =MAX(0,(D57-E57)-(H57-I57)) -> 0 | H57: =ROUND(IF(HYPOTHESES!$C$44=0,0,'BALANCE 2024'!$H$57*HYPOTHESES!E$44/HYPOTHESES!$C$44),0) -> 1744538 | I57: 0 | J57: =(D57-E57)+(F57-G57)-(H57-I57) -> 0
A58: 618300 | B58: Transports administratifs | C58: RG | D58: 0 | E58: 0 | F58: =MAX(0,(H58-I58)-(D58-E58)) -> 2403973 | G58: =MAX(0,(D58-E58)-(H58-I58)) -> 0 | H58: =ROUND(HYPOTHESES!E$44-(H56+H57),0) -> 2403973 | I58: 0 | J58: =(D58-E58)+(F58-G58)-(H58-I58) -> 0
A59: 622200 | B59: Location de batiment | C59: RH | D59: 0 | E59: 0 | F59: =MAX(0,(H59-I59)-(D59-E59)) -> 18689049 | G59: =MAX(0,(D59-E59)-(H59-I59)) -> 0 | H59: =ROUND(IF(HYPOTHESES!$C$45=0,0,'BALANCE 2024'!$H$59*HYPOTHESES!E$45/HYPOTHESES!$C$45),0) -> 18689049 | I59: 0 | J59: =(D59-E59)+(F59-G59)-(H59-I59) -> 0
A60: 624200 | B60: Entretien et réparation des biens m | C60: RH | D60: 0 | E60: 0 | F60: =MAX(0,(H60-I60)-(D60-E60)) -> 38426632 | G60: =MAX(0,(D60-E60)-(H60-I60)) -> 0 | H60: =ROUND(HYPOTHESES!E$45-(H59+H61+H62+H63+H64+H65+H66+H67),0) -> 38426632 | I60: 0 | J60: =(D60-E60)+(F60-G60)-(H60-I60) -> 0
A61: 625800 | B61: Autres primes d'assurances | C61: RH | D61: 0 | E61: 0 | F61: =MAX(0,(H61-I61)-(D61-E61)) -> 5156343 | G61: =MAX(0,(D61-E61)-(H61-I61)) -> 0 | H61: =ROUND(IF(HYPOTHESES!$C$45=0,0,'BALANCE 2024'!$H$61*HYPOTHESES!E$45/HYPOTHESES!$C$45),0) -> 5156343 | I61: 0 | J61: =(D61-E61)+(F61-G61)-(H61-I61) -> 0
A62: 626600 | B62: Documentation techniques | C62: RH | D62: 0 | E62: 0 | F62: =MAX(0,(H62-I62)-(D62-E62)) -> 35951 | G62: =MAX(0,(D62-E62)-(H62-I62)) -> 0 | H62: =ROUND(IF(HYPOTHESES!$C$45=0,0,'BALANCE 2024'!$H$62*HYPOTHESES!E$45/HYPOTHESES!$C$45),0) -> 35951 | I62: 0 | J62: =(D62-E62)+(F62-G62)-(H62-I62) -> 0
A63: 627700 | B63: Frais de colloques, séminaires, con | C63: RH | D63: 0 | E63: 0 | F63: =MAX(0,(H63-I63)-(D63-E63)) -> 65723 | G63: =MAX(0,(D63-E63)-(H63-I63)) -> 0 | H63: =ROUND(IF(HYPOTHESES!$C$45=0,0,'BALANCE 2024'!$H$63*HYPOTHESES!E$45/HYPOTHESES!$C$45),0) -> 65723 | I63: 0 | J63: =(D63-E63)+(F63-G63)-(H63-I63) -> 0
A64: 628800 | B64: Autres frais de télécommunications | C64: RH | D64: 0 | E64: 0 | F64: =MAX(0,(H64-I64)-(D64-E64)) -> 892086 | G64: =MAX(0,(D64-E64)-(H64-I64)) -> 0 | H64: =ROUND(IF(HYPOTHESES!$C$45=0,0,'BALANCE 2024'!$H$64*HYPOTHESES!E$45/HYPOTHESES!$C$45),0) -> 892086 | I64: 0 | J64: =(D64-E64)+(F64-G64)-(H64-I64) -> 0
A65: 631800 | B65: Autres frais bancaires | C65: RH | D65: 0 | E65: 0 | F65: =MAX(0,(H65-I65)-(D65-E65)) -> 25379403 | G65: =MAX(0,(D65-E65)-(H65-I65)) -> 0 | H65: =ROUND(IF(HYPOTHESES!$C$45=0,0,'BALANCE 2024'!$H$65*HYPOTHESES!E$45/HYPOTHESES!$C$45),0) -> 25379403 | I65: 0 | J65: =(D65-E65)+(F65-G65)-(H65-I65) -> 0
A66: 632800 | B66: Divers frais | C66: RH | D66: 0 | E66: 0 | F66: =MAX(0,(H66-I66)-(D66-E66)) -> 5339905 | G66: =MAX(0,(D66-E66)-(H66-I66)) -> 0 | H66: =ROUND(IF(HYPOTHESES!$C$45=0,0,'BALANCE 2024'!$H$66*HYPOTHESES!E$45/HYPOTHESES!$C$45),0) -> 5339905 | I66: 0 | J66: =(D66-E66)+(F66-G66)-(H66-I66) -> 0
A67: 638800 | B67: Charges externes diverses | C67: RH | D67: 0 | E67: 0 | F67: =MAX(0,(H67-I67)-(D67-E67)) -> 25966920 | G67: =MAX(0,(D67-E67)-(H67-I67)) -> 0 | H67: =ROUND(IF(HYPOTHESES!$C$45=0,0,'BALANCE 2024'!$H$67*HYPOTHESES!E$45/HYPOTHESES!$C$45),0) -> 25966920 | I67: 0 | J67: =(D67-E67)+(F67-G67)-(H67-I67) -> 0
A68: 641100 | B68: Impot foncier | C68: RI | D68: 0 | E68: 0 | F68: =MAX(0,(H68-I68)-(D68-E68)) -> 404245 | G68: =MAX(0,(D68-E68)-(H68-I68)) -> 0 | H68: =ROUND(IF(HYPOTHESES!$C$46=0,0,'BALANCE 2024'!$H$68*HYPOTHESES!E$46/HYPOTHESES!$C$46),0) -> 404245 | I68: 0 | J68: =(D68-E68)+(F68-G68)-(H68-I68) -> 0
A69: 641201 | B69: Patente commerciale | C69: RI | D69: 0 | E69: 0 | F69: =MAX(0,(H69-I69)-(D69-E69)) -> 10168034 | G69: =MAX(0,(D69-E69)-(H69-I69)) -> 0 | H69: =ROUND(HYPOTHESES!E$46-(H68+H70+H71+H72+H73+H74+H75+H76),0) -> 10168034 | I69: 0 | J69: =(D69-E69)+(F69-G69)-(H69-I69) -> 0
A70: 641202 | B70: Patente transport | C70: RI | D70: 0 | E70: 0 | F70: =MAX(0,(H70-I70)-(D70-E70)) -> 1739034 | G70: =MAX(0,(D70-E70)-(H70-I70)) -> 0 | H70: =ROUND(IF(HYPOTHESES!$C$46=0,0,'BALANCE 2024'!$H$70*HYPOTHESES!E$46/HYPOTHESES!$C$46),0) -> 1739034 | I70: 0 | J70: =(D70-E70)+(F70-G70)-(H70-I70) -> 0
A71: 641300 | B71: Taxes sur appointements et salaires | C71: RI | D71: 0 | E71: 0 | F71: =MAX(0,(H71-I71)-(D71-E71)) -> 928163 | G71: =MAX(0,(D71-E71)-(H71-I71)) -> 0 | H71: =ROUND(IF(HYPOTHESES!$C$46=0,0,'BALANCE 2024'!$H$71*HYPOTHESES!E$46/HYPOTHESES!$C$46),0) -> 928163 | I71: 0 | J71: =(D71-E71)+(F71-G71)-(H71-I71) -> 0
A72: 641400 | B72: Taxes d'apprentissage | C72: RI | D72: 0 | E72: 0 | F72: =MAX(0,(H72-I72)-(D72-E72)) -> 116856 | G72: =MAX(0,(D72-E72)-(H72-I72)) -> 0 | H72: =ROUND(IF(HYPOTHESES!$C$46=0,0,'BALANCE 2024'!$H$72*HYPOTHESES!E$46/HYPOTHESES!$C$46),0) -> 116856 | I72: 0 | J72: =(D72-E72)+(F72-G72)-(H72-I72) -> 0
A73: 641500 | B73: Formation professionnelle continue | C73: RI | D73: 0 | E73: 0 | F73: =MAX(0,(H73-I73)-(D73-E73)) -> 350583 | G73: =MAX(0,(D73-E73)-(H73-I73)) -> 0 | H73: =ROUND(IF(HYPOTHESES!$C$46=0,0,'BALANCE 2024'!$H$73*HYPOTHESES!E$46/HYPOTHESES!$C$46),0) -> 350583 | I73: 0 | J73: =(D73-E73)+(F73-G73)-(H73-I73) -> 0
A74: 641830 | B74: Tse | C74: RI | D74: 0 | E74: 0 | F74: =MAX(0,(H74-I74)-(D74-E74)) -> 237702 | G74: =MAX(0,(D74-E74)-(H74-I74)) -> 0 | H74: =ROUND(IF(HYPOTHESES!$C$46=0,0,'BALANCE 2024'!$H$74*HYPOTHESES!E$46/HYPOTHESES!$C$46),0) -> 237702 | I74: 0 | J74: =(D74-E74)+(F74-G74)-(H74-I74) -> 0
A75: 646200 | B75: Droits de timbre | C75: RI | D75: 0 | E75: 0 | F75: =MAX(0,(H75-I75)-(D75-E75)) -> 1937734 | G75: =MAX(0,(D75-E75)-(H75-I75)) -> 0 | H75: =ROUND(IF(HYPOTHESES!$C$46=0,0,'BALANCE 2024'!$H$75*HYPOTHESES!E$46/HYPOTHESES!$C$46),0) -> 1937734 | I75: 0 | J75: =(D75-E75)+(F75-G75)-(H75-I75) -> 0
A76: 648000 | B76: Autres impots et taxes | C76: RI | D76: 0 | E76: 0 | F76: =MAX(0,(H76-I76)-(D76-E76)) -> 814843 | G76: =MAX(0,(D76-E76)-(H76-I76)) -> 0 | H76: =ROUND(IF(HYPOTHESES!$C$46=0,0,'BALANCE 2024'!$H$76*HYPOTHESES!E$46/HYPOTHESES!$C$46),0) -> 814843 | I76: 0 | J76: =(D76-E76)+(F76-G76)-(H76-I76) -> 0
A77: 658800 | B77: Autres charges diverses | C77: RJ | D77: 0 | E77: 0 | F77: =MAX(0,(H77-I77)-(D77-E77)) -> 1496447 | G77: =MAX(0,(D77-E77)-(H77-I77)) -> 0 | H77: =ROUND(HYPOTHESES!E$47,0) -> 1496447 | I77: 0 | J77: =(D77-E77)+(F77-G77)-(H77-I77) -> 0
A78: 661100 | B78: Appointements salaires national | C78: RK | D78: 0 | E78: 0 | F78: =MAX(0,(H78-I78)-(D78-E78)) -> 66244380 | G78: =MAX(0,(D78-E78)-(H78-I78)) -> 0 | H78: =ROUND(HYPOTHESES!E$48-(H79+H80+H81+H82+H83),0) -> 66244380 | I78: 0 | J78: =(D78-E78)+(F78-G78)-(H78-I78) -> 0
A79: 661200 | B79: Primes et gratifications | C79: RK | D79: 0 | E79: 0 | F79: =MAX(0,(H79-I79)-(D79-E79)) -> 22393945 | G79: =MAX(0,(D79-E79)-(H79-I79)) -> 0 | H79: =ROUND(IF(HYPOTHESES!$C$48=0,0,'BALANCE 2024'!$H$79*HYPOTHESES!E$48/HYPOTHESES!$C$48),0) -> 22393945 | I79: 0 | J79: =(D79-E79)+(F79-G79)-(H79-I79) -> 0
A80: 661300 | B80: Congés payés | C80: RK | D80: 0 | E80: 0 | F80: =MAX(0,(H80-I80)-(D80-E80)) -> 7388922 | G80: =MAX(0,(D80-E80)-(H80-I80)) -> 0 | H80: =ROUND(IF(HYPOTHESES!$C$48=0,0,'BALANCE 2024'!$H$80*HYPOTHESES!E$48/HYPOTHESES!$C$48),0) -> 7388922 | I80: 0 | J80: =(D80-E80)+(F80-G80)-(H80-I80) -> 0
A81: 661400 | B81: Indem.preavis&licenc imposables | C81: RK | D81: 0 | E81: 0 | F81: =MAX(0,(H81-I81)-(D81-E81)) -> 7461856 | G81: =MAX(0,(D81-E81)-(H81-I81)) -> 0 | H81: =ROUND(IF(HYPOTHESES!$C$48=0,0,'BALANCE 2024'!$H$81*HYPOTHESES!E$48/HYPOTHESES!$C$48),0) -> 7461856 | I81: 0 | J81: =(D81-E81)+(F81-G81)-(H81-I81) -> 0
A82: 663400 | B82: Indemnités de transport | C82: RK | D82: 0 | E82: 0 | F82: =MAX(0,(H82-I82)-(D82-E82)) -> 7728368 | G82: =MAX(0,(D82-E82)-(H82-I82)) -> 0 | H82: =ROUND(IF(HYPOTHESES!$C$48=0,0,'BALANCE 2024'!$H$82*HYPOTHESES!E$48/HYPOTHESES!$C$48),0) -> 7728368 | I82: 0 | J82: =(D82-E82)+(F82-G82)-(H82-I82) -> 0
A83: 664104 | B83: Charges socialescr employeur | C83: RK | D83: 0 | E83: 0 | F83: =MAX(0,(H83-I83)-(D83-E83)) -> 7868177 | G83: =MAX(0,(D83-E83)-(H83-I83)) -> 0 | H83: =ROUND(IF(HYPOTHESES!$C$48=0,0,'BALANCE 2024'!$H$83*HYPOTHESES!E$48/HYPOTHESES!$C$48),0) -> 7868177 | I83: 0 | J83: =(D83-E83)+(F83-G83)-(H83-I83) -> 0
A84: 671201 | B84: Interet des emprunts ecobank | C84: RM | D84: 0 | E84: 0 | F84: =MAX(0,(H84-I84)-(D84-E84)) -> 0 | G84: =MAX(0,(D84-E84)-(H84-I84)) -> 0 | H84: =ROUND('INVEST ET FINANCEMENT'!E$64,0) -> 0 | I84: 0 | J84: =(D84-E84)+(F84-G84)-(H84-I84) -> 0
A85: 672301 | B85: Interet de credit bail bni -1 | C85: RM | D85: 0 | E85: 0 | F85: =MAX(0,(H85-I85)-(D85-E85)) -> 0 | G85: =MAX(0,(D85-E85)-(H85-I85)) -> 0 | H85: =ROUND('INVEST ET FINANCEMENT'!E$65,0) -> 0 | I85: 0 | J85: =(D85-E85)+(F85-G85)-(H85-I85) -> 0
A86: 681301 | B86: Dotations aux amortissements : aménagements | C86: RL | D86: 0 | E86: 0 | F86: =MAX(0,(H86-I86)-(D86-E86)) -> 19282845 | G86: =MAX(0,(D86-E86)-(H86-I86)) -> 0 | H86: =ROUND('INVEST ET FINANCEMENT'!E$31,0) -> 19282845 | I86: 0 | J86: =(D86-E86)+(F86-G86)-(H86-I86) -> 0
A87: 681302 | B87: Dotations aux amortissements : matériel et outillage | C87: RL | D87: 0 | E87: 0 | F87: =MAX(0,(H87-I87)-(D87-E87)) -> 50854932 | G87: =MAX(0,(D87-E87)-(H87-I87)) -> 0 | H87: =ROUND('INVEST ET FINANCEMENT'!E$34,0) -> 50854932 | I87: 0 | J87: =(D87-E87)+(F87-G87)-(H87-I87) -> 0
A88: 681303 | B88: Dotations aux amortissements : bureau et informatique | C88: RL | D88: 0 | E88: 0 | F88: =MAX(0,(H88-I88)-(D88-E88)) -> 7609173 | G88: =MAX(0,(D88-E88)-(H88-I88)) -> 0 | H88: =ROUND('INVEST ET FINANCEMENT'!E$37,0) -> 7609173 | I88: 0 | J88: =(D88-E88)+(F88-G88)-(H88-I88) -> 0
A89: 681304 | B89: Dotations aux amortissements : transport | C89: RL | D89: 0 | E89: 0 | F89: =MAX(0,(H89-I89)-(D89-E89)) -> 15958378 | G89: =MAX(0,(D89-E89)-(H89-I89)) -> 0 | H89: =ROUND('INVEST ET FINANCEMENT'!E$40,0) -> 15958378 | I89: 0 | J89: =(D89-E89)+(F89-G89)-(H89-I89) -> 0
A90: 691100 | B90: Dotations aux provisions pour risques et charges | C90: RL | D90: 0 | E90: 0 | F90: =MAX(0,(H90-I90)-(D90-E90)) -> 6059296 | G90: =MAX(0,(D90-E90)-(H90-I90)) -> 0 | H90: =ROUND(HYPOTHESES!E$50,0) -> 6059296 | I90: 0 | J90: =(D90-E90)+(F90-G90)-(H90-I90) -> 0
A91: 705100 | B91: Travaux facturés | C91: TC | D91: 0 | E91: 0 | F91: =MAX(0,(H91-I91)-(D91-E91)) -> 0 | G91: =MAX(0,(D91-E91)-(H91-I91)) -> 787603492 | H91: 0 | I91: =ROUND(HYPOTHESES!E$42,0) -> 787603492 | J91: =(D91-E91)+(F91-G91)-(H91-I91) -> 0
A92: 771200 | B92: Intérêts des prêts | C92: TK | D92: 0 | E92: 0 | F92: =MAX(0,(H92-I92)-(D92-E92)) -> 0 | G92: =MAX(0,(D92-E92)-(H92-I92)) -> 848594 | H92: 0 | I92: =ROUND(HYPOTHESES!E$51,0) -> 848594 | J92: =(D92-E92)+(F92-G92)-(H92-I92) -> 0
A93: 891100 | B93: Impôts sur les bénéfices | C93: RS | D93: 0 | E93: 0 | F93: =MAX(0,(H93-I93)-(D93-E93)) -> 28670509 | G93: =MAX(0,(D93-E93)-(H93-I93)) -> 0 | H93: =ROUND(IF(HYPOTHESES!E$54>=HYPOTHESES!E$55,HYPOTHESES!E$56,0),0) -> 28670509 | I93: 0 | J93: =(D93-E93)+(F93-G93)-(H93-I93) -> 0
A94: 895000 | B94: Impôt minimum forfaitaire (IMF) | C94: RS | D94: 0 | E94: 0 | F94: =MAX(0,(H94-I94)-(D94-E94)) -> 0 | G94: =MAX(0,(D94-E94)-(H94-I94)) -> 0 | H94: =ROUND(IF(HYPOTHESES!E$54<HYPOTHESES!E$55,HYPOTHESES!E$56,0),0) -> 0 | I94: 0 | J94: =(D94-E94)+(F94-G94)-(H94-I94) -> 0
B96: TOTAL BALANCE | D96: =SUM(D5:D94) -> 1770812924 | E96: =SUM(E5:E94) -> 1770812924 | F96: =SUM(F5:F94) -> 3867023256 | G96: =SUM(G5:G94) -> 3867023256 | H96: =SUM(H5:H94) -> 2620463921 | I96: =SUM(I5:I94) -> 2620463921 | J96: =SUM(J5:J94) -> 0
B97: Écart débit - crédit (doit être nul) | D97: =D96-E96 -> 0 | F97: =F96-G96 -> 0 | H97: =H96-I96 -> 0
B99: Calcul : trésorerie totale à répartir (banque + caisse) | H99: =-(SUM(H5:H44)-SUM(I5:I44)+SUM(H47:H94)-SUM(I47:I94)) -> 225108073
B100: Calcul : sorties de banque de l'exercice (crédit 521) | H100: =ROUND((G26+HYPOTHESES!E$51+'INVEST ET FINANCEMENT'!E$47+'INVEST ET FINANCEMENT'!E$51+(D45-E45)+(D46-E46)-H99)/(1-HYPOTHESES!E$29*(1-HYPOTHESES!E$30)),0) -> 819649576
B101: Calcul : approvisionnement de la caisse (% des sorties de banque) | H101: =ROUND(HYPOTHESES!E$29*H100,0) -> 163929915

Sheet BALANCE 2027
A1: BALANCE GÉNÉRALE À 6 COLONNES : EXERCICE 2027 (PRÉVISIONNEL)
A2: Ouverture = clôture de l'exercice précédent (classes 6 à 8 soldées, résultat N-1 en 13). Clôture calculée depuis les hypothèses ; mouvements = flux de l'exercice. Soldes après inventaire, avant écritures de clôture. Ne rien saisir.
D3: Soldes d'ouverture | F3: Mouvements de l'exercice | H3: Soldes de clôture | J3: Contrôle
A4: Compte | B4: Intitulé | C4: Poste | D4: Débit | E4: Crédit | F4: Débit | G4: Crédit | H4: Débit | I4: Crédit | J4: Ouv.+Mvts-Clôt.
A5: 101000 | B5: Capital social | C5: CA | D5: ='BALANCE 2026'!H5 -> 0 | E5: ='BALANCE 2026'!I5 -> 10000000 | F5: =ROUND('INVEST ET FINANCEMENT'!F$51,0)+(H5-I5)-(D5-E5) -> 0 | G5: =ROUND('INVEST ET FINANCEMENT'!F$51,0) -> 0 | H5: 0 | I5: =ROUND(E5+'INVEST ET FINANCEMENT'!F$51,0) -> 10000000 | J5: =(D5-E5)+(F5-G5)-(H5-I5) -> 0
A6: 111000 | B6: Réserve légale | C6: CF | D6: ='BALANCE 2026'!H6 -> 0 | E6: ='BALANCE 2026'!I6 -> 2000000 | F6: =ROUND(HYPOTHESES!F$58,0)+(H6-I6)-(D6-E6) -> 0 | G6: =ROUND(HYPOTHESES!F$58,0) -> 0 | H6: 0 | I6: =ROUND(E6+HYPOTHESES!F$58,0) -> 2000000 | J6: =(D6-E6)+(F6-G6)-(H6-I6) -> 0
A7: 121000 | B7: Report à nouveau | C7: CH | D7: ='BALANCE 2026'!H7 -> 0 | E7: ='BALANCE 2026'!I7 -> 937013596 | F7: =MAX(0,(H7-I7)-(D7-E7)) -> 0 | G7: =MAX(0,(D7-E7)-(H7-I7)) -> 86011527 | H7: =ROUND(MAX(0,-(E7-D7+HYPOTHESES!F$60)),0) -> 0 | I7: =ROUND(MAX(0,(E7-D7+HYPOTHESES!F$60)),0) -> 1023025123 | J7: =(D7-E7)+(F7-G7)-(H7-I7) -> 0
A8: 130100 | B8: Résultat en instance d'affectation : bénéfice | C8: R13 | D8: =MAX(0,-(SUM('BALANCE 2026'!I48:I94)-SUM('BALANCE 2026'!H48:H94))) -> 0 | E8: =MAX(0,(SUM('BALANCE 2026'!I48:I94)-SUM('BALANCE 2026'!H48:H94))) -> 86011527 | F8: =MAX(0,(H8-I8)-(D8-E8)) -> 86011527 | G8: =MAX(0,(D8-E8)-(H8-I8)) -> 0 | H8: 0 | I8: 0 | J8: =(D8-E8)+(F8-G8)-(H8-I8) -> 0
A9: 162002 | B9: Emprunts auprès des établissements de crédit (BNI) | C9: DA | D9: ='BALANCE 2026'!H9 -> 0 | E9: ='BALANCE 2026'!I9 -> 0 | F9: =ROUND('INVEST ET FINANCEMENT'!F$47,0)+(H9-I9)-(D9-E9) -> 0 | G9: =ROUND('INVEST ET FINANCEMENT'!F$47,0) -> 0 | H9: 0 | I9: =ROUND(E9+'INVEST ET FINANCEMENT'!F$47-'INVEST ET FINANCEMENT'!F$48,0) -> 0 | J9: =(D9-E9)+(F9-G9)-(H9-I9) -> 0
A10: 173060 | B10: Dettes de location-acquisition | C10: DB | D10: ='BALANCE 2026'!H10 -> 0 | E10: ='BALANCE 2026'!I10 -> 0 | F10: =ROUND('INVEST ET FINANCEMENT'!F$49,0) -> 0 | G10: =ROUND('INVEST ET FINANCEMENT'!F$49,0)+(D10-E10)-(H10-I10) -> 0 | H10: 0 | I10: =ROUND(E10-'INVEST ET FINANCEMENT'!F$49,0) -> 0 | J10: =(D10-E10)+(F10-G10)-(H10-I10) -> 0
A11: 196100 | B11: Provisions pour pensions et obligations similaires (IFC) | C11: DC | D11: ='BALANCE 2026'!H11 -> 0 | E11: ='BALANCE 2026'!I11 -> 33392488 | F11: =ROUND(HYPOTHESES!F$20,0)+(H11-I11)-(D11-E11) -> 0 | G11: =ROUND(HYPOTHESES!F$20,0) -> 6059296 | H11: 0 | I11: =ROUND(E11+HYPOTHESES!F$20,0) -> 39451784 | J11: =(D11-E11)+(F11-G11)-(H11-I11) -> 0
A12: 234100 | B12: Aménagements, agencements et installations techniques | C12: AL | D12: ='BALANCE 2026'!H12 -> 103601492 | E12: ='BALANCE 2026'!I12 -> 0 | F12: =ROUND('INVEST ET FINANCEMENT'!F$9,0) -> 0 | G12: =ROUND('INVEST ET FINANCEMENT'!F$9,0)+(D12-E12)-(H12-I12) -> 0 | H12: =ROUND(D12+'INVEST ET FINANCEMENT'!F$9,0) -> 103601492 | I12: 0 | J12: =(D12-E12)+(F12-G12)-(H12-I12) -> 0
A13: 241100 | B13: Matériel industriel | C13: AM | D13: ='BALANCE 2026'!H13 -> 343845268 | E13: ='BALANCE 2026'!I13 -> 0 | F13: =ROUND('INVEST ET FINANCEMENT'!F$10,0) -> 30000000 | G13: =ROUND('INVEST ET FINANCEMENT'!F$10,0)+(D13-E13)-(H13-I13) -> 0 | H13: =ROUND(D13+'INVEST ET FINANCEMENT'!F$10,0) -> 373845268 | I13: 0 | J13: =(D13-E13)+(F13-G13)-(H13-I13) -> 0
A14: 244100 | B14: Matériel de bureau | C14: AM | D14: ='BALANCE 2026'!H14 -> 9306956 | E14: ='BALANCE 2026'!I14 -> 0 | F14: =MAX(0,(H14-I14)-(D14-E14)) -> 0 | G14: =MAX(0,(D14-E14)-(H14-I14)) -> 0 | H14: =ROUND(D14,0) -> 9306956 | I14: 0 | J14: =(D14-E14)+(F14-G14)-(H14-I14) -> 0
A15: 244200 | B15: Matériel informatique | C15: AM | D15: ='BALANCE 2026'!H15 -> 18910459 | E15: ='BALANCE 2026'!I15 -> 0 | F15: =ROUND('INVEST ET FINANCEMENT'!F$11,0) -> 5000000 | G15: =ROUND('INVEST ET FINANCEMENT'!F$11,0)+(D15-E15)-(H15-I15) -> 0 | H15: =ROUND(D15+'INVEST ET FINANCEMENT'!F$11,0) -> 23910459 | I15: 0 | J15: =(D15-E15)+(F15-G15)-(H15-I15) -> 0
A16: 245100 | B16: Matériel automobile | C16: AN | D16: ='BALANCE 2026'!H16 -> 423638205 | E16: ='BALANCE 2026'!I16 -> 0 | F16: =ROUND('INVEST ET FINANCEMENT'!F$12,0) -> 0 | G16: =ROUND('INVEST ET FINANCEMENT'!F$12,0)+(D16-E16)-(H16-I16) -> 0 | H16: =ROUND(D16+'INVEST ET FINANCEMENT'!F$12,0) -> 423638205 | I16: 0 | J16: =(D16-E16)+(F16-G16)-(H16-I16) -> 0
A17: 245600 | B17: Matériel de transport en location-acquisition | C17: AN | D17: ='BALANCE 2026'!H17 -> 28619694 | E17: ='BALANCE 2026'!I17 -> 0 | F17: =MAX(0,(H17-I17)-(D17-E17)) -> 0 | G17: =MAX(0,(D17-E17)-(H17-I17)) -> 0 | H17: =ROUND(D17,0) -> 28619694 | I17: 0 | J17: =(D17-E17)+(F17-G17)-(H17-I17) -> 0
A18: 271800 | B18: Autres prêts et créances | C18: AS | D18: ='BALANCE 2026'!H18 -> 25000000 | E18: ='BALANCE 2026'!I18 -> 0 | F18: =MAX(0,(H18-I18)-(D18-E18)) -> 0 | G18: =MAX(0,(D18-E18)-(H18-I18)) -> 0 | H18: =ROUND(D18,0) -> 25000000 | I18: 0 | J18: =(D18-E18)+(F18-G18)-(H18-I18) -> 0
A19: 275100 | B19: Dépôts et cautionnements versés | C19: AS | D19: ='BALANCE 2026'!H19 -> 231420138 | E19: ='BALANCE 2026'!I19 -> 0 | F19: =ROUND('INVEST ET FINANCEMENT'!F$13,0) -> 0 | G19: =ROUND('INVEST ET FINANCEMENT'!F$13,0)+(D19-E19)-(H19-I19) -> 0 | H19: =ROUND(D19+'INVEST ET FINANCEMENT'!F$13,0) -> 231420138 | I19: 0 | J19: =(D19-E19)+(F19-G19)-(H19-I19) -> 0
A20: 283400 | B20: Amortissements des aménagements, agencements | C20: AL | D20: ='BALANCE 2026'!H20 -> 0 | E20: ='BALANCE 2026'!I20 -> 80502166 | F20: =ROUND('INVEST ET FINANCEMENT'!F$31,0)+(H20-I20)-(D20-E20) -> 0 | G20: =ROUND('INVEST ET FINANCEMENT'!F$31,0) -> 19282845 | H20: 0 | I20: =ROUND(E20+'INVEST ET FINANCEMENT'!F$31,0) -> 99785011 | J20: =(D20-E20)+(F20-G20)-(H20-I20) -> 0
A21: 284100 | B21: Amortissements du matériel et outillage | C21: AM | D21: ='BALANCE 2026'!H21 -> 0 | E21: ='BALANCE 2026'!I21 -> 135043749 | F21: =ROUND('INVEST ET FINANCEMENT'!F$34,0)+(H21-I21)-(D21-E21) -> 0 | G21: =ROUND('INVEST ET FINANCEMENT'!F$34,0) -> 56854932 | H21: 0 | I21: =ROUND(E21+'INVEST ET FINANCEMENT'!F$34,0) -> 191898681 | J21: =(D21-E21)+(F21-G21)-(H21-I21) -> 0
A22: 284400 | B22: Amortissements du matériel de bureau et informatique | C22: AM | D22: ='BALANCE 2026'!H22 -> 0 | E22: ='BALANCE 2026'!I22 -> 25717415 | F22: =ROUND('INVEST ET FINANCEMENT'!F$37,0)+(H22-I22)-(D22-E22) -> 0 | G22: =ROUND('INVEST ET FINANCEMENT'!F$37,0) -> 5000000 | H22: 0 | I22: =ROUND(E22+'INVEST ET FINANCEMENT'!F$37,0) -> 30717415 | J22: =(D22-E22)+(F22-G22)-(H22-I22) -> 0
A23: 284500 | B23: Amortissements du matériel de transport | C23: AN | D23: ='BALANCE 2026'!H23 -> 0 | E23: ='BALANCE 2026'!I23 -> 397825832 | F23: =ROUND('INVEST ET FINANCEMENT'!F$40,0)+(H23-I23)-(D23-E23) -> 0 | G23: =ROUND('INVEST ET FINANCEMENT'!F$40,0) -> 15958378 | H23: 0 | I23: =ROUND(E23+'INVEST ET FINANCEMENT'!F$40,0) -> 413784210 | J23: =(D23-E23)+(F23-G23)-(H23-I23) -> 0
A24: 401100 | B24: Fournisseurs | C24: DJ | D24: ='BALANCE 2026'!H24 -> 0 | E24: ='BALANCE 2026'!I24 -> 81595000 | F24: =ROUND(HYPOTHESES!F$49*(1+HYPOTHESES!F$10),0)+(H24-I24)-(D24-E24) -> 537023933 | G24: =ROUND(HYPOTHESES!F$49*(1+HYPOTHESES!F$10),0) -> 541103683 | H24: 0 | I24: =ROUND(HYPOTHESES!F$49*(1+HYPOTHESES!F$10)*HYPOTHESES!F$23/360,0) -> 85674750 | J24: =(D24-E24)+(F24-G24)-(H24-I24) -> 0
A25: 409100 | B25: Fournisseurs avances et accoptes ve | C25: BH | D25: ='BALANCE 2026'!H25 -> 0 | E25: ='BALANCE 2026'!I25 -> 0 | F25: =MAX(0,(H25-I25)-(D25-E25)) -> 0 | G25: =MAX(0,(D25-E25)-(H25-I25)) -> 0 | H25: =ROUND(D25,0) -> 0 | I25: =ROUND(E25,0) -> 0 | J25: =(D25-E25)+(F25-G25)-(H25-I25) -> 0
A26: 411100 | B26: Clients | C26: BI | D26: ='BALANCE 2026'!H26 -> 508573077 | E26: ='BALANCE 2026'!I26 -> 0 | F26: =ROUND(HYPOTHESES!F$42*(1+HYPOTHESES!F$10),0) -> 975840727 | G26: =ROUND(HYPOTHESES!F$42*(1+HYPOTHESES!F$10),0)+(D26-E26)-(H26-I26) -> 950412073 | H26: =ROUND(HYPOTHESES!F$42*(1+HYPOTHESES!F$10)*HYPOTHESES!F$22/360,0) -> 534001731 | I26: 0 | J26: =(D26-E26)+(F26-G26)-(H26-I26) -> 0
A27: 422000 | B27: Personnel, rémunérations dues | C27: DK | D27: ='BALANCE 2026'!H27 -> 0 | E27: ='BALANCE 2026'!I27 -> 12520695 | F27: =ROUND(IF(HYPOTHESES!$C$48=0,0,'BALANCE 2024'!$G$27*HYPOTHESES!F$48/HYPOTHESES!$C$48),0)+(H27-I27)-(D27-E27) -> 95221295 | G27: =ROUND(IF(HYPOTHESES!$C$48=0,0,'BALANCE 2024'!$G$27*HYPOTHESES!F$48/HYPOTHESES!$C$48),0) -> 95847329 | H27: 0 | I27: =ROUND(IF(HYPOTHESES!$C$48=0,0,'BALANCE 2024'!$I$27*HYPOTHESES!F$48/HYPOTHESES!$C$48),0) -> 13146729 | J27: =(D27-E27)+(F27-G27)-(H27-I27) -> 0
A28: 431301 | B28: CNPS, retraite part employeur | C28: DK | D28: ='BALANCE 2026'!H28 -> 0 | E28: ='BALANCE 2026'!I28 -> 5457951 | F28: =ROUND(IF(HYPOTHESES!$C$48=0,0,'BALANCE 2024'!$G$28*HYPOTHESES!F$48/HYPOTHESES!$C$48),0)+(H28-I28)-(D28-E28) -> 7988688 | G28: =ROUND(IF(HYPOTHESES!$C$48=0,0,'BALANCE 2024'!$G$28*HYPOTHESES!F$48/HYPOTHESES!$C$48),0) -> 8261585 | H28: 0 | I28: =ROUND(IF(HYPOTHESES!$C$48=0,0,'BALANCE 2024'!$I$28*HYPOTHESES!F$48/HYPOTHESES!$C$48),0) -> 5730848 | J28: =(D28-E28)+(F28-G28)-(H28-I28) -> 0
A29: 431302 | B29: CNPS, retraite part salariale | C29: DK | D29: ='BALANCE 2026'!H29 -> 0 | E29: ='BALANCE 2026'!I29 -> 1350516 | F29: =ROUND(IF(HYPOTHESES!$C$48=0,0,'BALANCE 2024'!$G$29*HYPOTHESES!F$48/HYPOTHESES!$C$48),0)+(H29-I29)-(D29-E29) -> 13446969 | G29: =ROUND(IF(HYPOTHESES!$C$48=0,0,'BALANCE 2024'!$G$29*HYPOTHESES!F$48/HYPOTHESES!$C$48),0) -> 13514495 | H29: 0 | I29: =ROUND(IF(HYPOTHESES!$C$48=0,0,'BALANCE 2024'!$I$29*HYPOTHESES!F$48/HYPOTHESES!$C$48),0) -> 1418042 | J29: =(D29-E29)+(F29-G29)-(H29-I29) -> 0
A30: 431802 | B30: CMU, part salariale | C30: DK | D30: ='BALANCE 2026'!H30 -> 0 | E30: ='BALANCE 2026'!I30 -> 181885 | F30: =ROUND(IF(HYPOTHESES!$C$48=0,0,'BALANCE 2024'!$G$30*HYPOTHESES!F$48/HYPOTHESES!$C$48),0)+(H30-I30)-(D30-E30) -> 448040 | G30: =ROUND(IF(HYPOTHESES!$C$48=0,0,'BALANCE 2024'!$G$30*HYPOTHESES!F$48/HYPOTHESES!$C$48),0) -> 457135 | H30: 0 | I30: =ROUND(IF(HYPOTHESES!$C$48=0,0,'BALANCE 2024'!$I$30*HYPOTHESES!F$48/HYPOTHESES!$C$48),0) -> 190980 | J30: =(D30-E30)+(F30-G30)-(H30-I30) -> 0
A31: 433300 | B31: Assurance et organisme de sante | C31: DK | D31: ='BALANCE 2026'!H31 -> 0 | E31: ='BALANCE 2026'!I31 -> 0 | F31: =ROUND(IF(HYPOTHESES!$C$48=0,0,'BALANCE 2024'!$G$31*HYPOTHESES!F$48/HYPOTHESES!$C$48),0)+(H31-I31)-(D31-E31) -> 0 | G31: =ROUND(IF(HYPOTHESES!$C$48=0,0,'BALANCE 2024'!$G$31*HYPOTHESES!F$48/HYPOTHESES!$C$48),0) -> 0 | H31: 0 | I31: =ROUND(IF(HYPOTHESES!$C$48=0,0,'BALANCE 2024'!$I$31*HYPOTHESES!F$48/HYPOTHESES!$C$48),0) -> 0 | J31: =(D31-E31)+(F31-G31)-(H31-I31) -> 0
A32: 441000 | B32: État, impôt sur les bénéfices | C32: DK | D32: ='BALANCE 2026'!H32 -> 0 | E32: ='BALANCE 2026'!I32 -> 28670509 | F32: =ROUND(HYPOTHESES!F$56,0)+(H32-I32)-(D32-E32) -> 28670509 | G32: =ROUND(HYPOTHESES!F$56,0) -> 30492779 | H32: 0 | I32: =ROUND(HYPOTHESES!F$56,0) -> 30492779 | J32: =(D32-E32)+(F32-G32)-(H32-I32) -> 0
A33: 442800 | B33: Autres impôts et taxes | C33: DK | D33: ='BALANCE 2026'!H33 -> 0 | E33: ='BALANCE 2026'!I33 -> 814843 | F33: =ROUND(IF(HYPOTHESES!$C$46=0,0,'BALANCE 2024'!$G$33*HYPOTHESES!F$46/HYPOTHESES!$C$46),0)+(H33-I33)-(D33-E33) -> 814843 | G33: =ROUND(IF(HYPOTHESES!$C$46=0,0,'BALANCE 2024'!$G$33*HYPOTHESES!F$46/HYPOTHESES!$C$46),0) -> 855586 | H33: 0 | I33: =ROUND(IF(HYPOTHESES!$C$46=0,0,'BALANCE 2024'!$I$33*HYPOTHESES!F$46/HYPOTHESES!$C$46),0) -> 855586 | J33: =(D33-E33)+(F33-G33)-(H33-I33) -> 0
A34: 442801 | B34: FDFP, taxe d'apprentissage | C34: DK | D34: ='BALANCE 2026'!H34 -> 0 | E34: ='BALANCE 2026'!I34 -> 116856 | F34: =ROUND(IF(HYPOTHESES!$C$46=0,0,'BALANCE 2024'!$G$34*HYPOTHESES!F$46/HYPOTHESES!$C$46),0)+(H34-I34)-(D34-E34) -> 116856 | G34: =ROUND(IF(HYPOTHESES!$C$46=0,0,'BALANCE 2024'!$G$34*HYPOTHESES!F$46/HYPOTHESES!$C$46),0) -> 122699 | H34: 0 | I34: =ROUND(IF(HYPOTHESES!$C$46=0,0,'BALANCE 2024'!$I$34*HYPOTHESES!F$46/HYPOTHESES!$C$46),0) -> 122699 | J34: =(D34-E34)+(F34-G34)-(H34-I34) -> 0
A35: 442802 | B35: FDFP, formation continue | C35: DK | D35: ='BALANCE 2026'!H35 -> 0 | E35: ='BALANCE 2026'!I35 -> 175292 | F35: =ROUND(IF(HYPOTHESES!$C$46=0,0,'BALANCE 2024'!$G$35*HYPOTHESES!F$46/HYPOTHESES!$C$46),0)+(H35-I35)-(D35-E35) -> 175292 | G35: =ROUND(IF(HYPOTHESES!$C$46=0,0,'BALANCE 2024'!$G$35*HYPOTHESES!F$46/HYPOTHESES!$C$46),0) -> 184056 | H35: 0 | I35: =ROUND(IF(HYPOTHESES!$C$46=0,0,'BALANCE 2024'!$I$35*HYPOTHESES!F$46/HYPOTHESES!$C$46),0) -> 184056 | J35: =(D35-E35)+(F35-G35)-(H35-I35) -> 0
A36: 442803 | B36: FDFP, FPC à régulariser | C36: DK | D36: ='BALANCE 2026'!H36 -> 0 | E36: ='BALANCE 2026'!I36 -> 175291 | F36: =ROUND(IF(HYPOTHESES!$C$46=0,0,'BALANCE 2024'!$G$36*HYPOTHESES!F$46/HYPOTHESES!$C$46),0)+(H36-I36)-(D36-E36) -> 175291 | G36: =ROUND(IF(HYPOTHESES!$C$46=0,0,'BALANCE 2024'!$G$36*HYPOTHESES!F$46/HYPOTHESES!$C$46),0) -> 184055 | H36: 0 | I36: =ROUND(IF(HYPOTHESES!$C$46=0,0,'BALANCE 2024'!$I$36*HYPOTHESES!F$46/HYPOTHESES!$C$46),0) -> 184055 | J36: =(D36-E36)+(F36-G36)-(H36-I36) -> 0
A37: 442820 | B37: Impôt sur salaires, part patronale | C37: DK | D37: ='BALANCE 2026'!H37 -> 0 | E37: ='BALANCE 2026'!I37 -> 412790 | F37: =ROUND(IF(HYPOTHESES!$C$46=0,0,'BALANCE 2024'!$G$37*HYPOTHESES!F$46/HYPOTHESES!$C$46),0)+(H37-I37)-(D37-E37) -> 953932 | G37: =ROUND(IF(HYPOTHESES!$C$46=0,0,'BALANCE 2024'!$G$37*HYPOTHESES!F$46/HYPOTHESES!$C$46),0) -> 974572 | H37: 0 | I37: =ROUND(IF(HYPOTHESES!$C$46=0,0,'BALANCE 2024'!$I$37*HYPOTHESES!F$46/HYPOTHESES!$C$46),0) -> 433430 | J37: =(D37-E37)+(F37-G37)-(H37-I37) -> 0
A38: 442840 | B38: Patente | C38: DK | D38: ='BALANCE 2026'!H38 -> 0 | E38: ='BALANCE 2026'!I38 -> 5614514 | F38: =ROUND(IF(HYPOTHESES!$C$46=0,0,'BALANCE 2024'!$G$38*HYPOTHESES!F$46/HYPOTHESES!$C$46),0)+(H38-I38)-(D38-E38) -> 10395710 | G38: =ROUND(IF(HYPOTHESES!$C$46=0,0,'BALANCE 2024'!$G$38*HYPOTHESES!F$46/HYPOTHESES!$C$46),0) -> 10676436 | H38: 0 | I38: =ROUND(IF(HYPOTHESES!$C$46=0,0,'BALANCE 2024'!$I$38*HYPOTHESES!F$46/HYPOTHESES!$C$46),0) -> 5895240 | J38: =(D38-E38)+(F38-G38)-(H38-I38) -> 0
A39: 443300 | B39: État, TVA facturée sur travaux (en attente) | C39: DK | D39: ='BALANCE 2026'!H39 -> 0 | E39: ='BALANCE 2026'!I39 -> 58637133 | F39: =ROUND(HYPOTHESES!F$42*HYPOTHESES!F$10,0)+(H39-I39)-(D39-E39) -> 145925203 | G39: =ROUND(HYPOTHESES!F$42*HYPOTHESES!F$10,0) -> 148857060 | H39: 0 | I39: =ROUND(IF('BALANCE 2024'!$H$26=0,0,'BALANCE 2024'!$I$39*H26/'BALANCE 2024'!$H$26),0) -> 61568990 | J39: =(D39-E39)+(F39-G39)-(H39-I39) -> 0
A40: 446000 | B40: Taxe spéciale d'équipement | C40: DK | D40: ='BALANCE 2026'!H40 -> 0 | E40: ='BALANCE 2026'!I40 -> 224581 | F40: =ROUND(IF(HYPOTHESES!$C$46=0,0,'BALANCE 2024'!$G$40*HYPOTHESES!F$46/HYPOTHESES!$C$46),0)+(H40-I40)-(D40-E40) -> 238358 | G40: =ROUND(IF(HYPOTHESES!$C$46=0,0,'BALANCE 2024'!$G$40*HYPOTHESES!F$46/HYPOTHESES!$C$46),0) -> 249587 | H40: 0 | I40: =ROUND(IF(HYPOTHESES!$C$46=0,0,'BALANCE 2024'!$I$40*HYPOTHESES!F$46/HYPOTHESES!$C$46),0) -> 235810 | J40: =(D40-E40)+(F40-G40)-(H40-I40) -> 0
A41: 447201 | B41: ITS retenu à la source | C41: DK | D41: ='BALANCE 2026'!H41 -> 0 | E41: ='BALANCE 2026'!I41 -> 1832622 | F41: =ROUND(IF(HYPOTHESES!$C$48=0,0,'BALANCE 2024'!$G$41*HYPOTHESES!F$48/HYPOTHESES!$C$48),0)+(H41-I41)-(D41-E41) -> 6867754 | G41: =ROUND(IF(HYPOTHESES!$C$48=0,0,'BALANCE 2024'!$G$41*HYPOTHESES!F$48/HYPOTHESES!$C$48),0) -> 6959385 | H41: 0 | I41: =ROUND(IF(HYPOTHESES!$C$48=0,0,'BALANCE 2024'!$I$41*HYPOTHESES!F$48/HYPOTHESES!$C$48),0) -> 1924253 | J41: =(D41-E41)+(F41-G41)-(H41-I41) -> 0
A42: 462100 | B42: Associés, comptes courants | C42: DM | D42: ='BALANCE 2026'!H42 -> 0 | E42: ='BALANCE 2026'!I42 -> 0 | F42: =ROUND('INVEST ET FINANCEMENT'!F$53,0)+(H42-I42)-(D42-E42) -> 0 | G42: =ROUND('INVEST ET FINANCEMENT'!F$53,0) -> 0 | H42: 0 | I42: =ROUND('INVEST ET FINANCEMENT'!F$54,0) -> 0 | J42: =(D42-E42)+(F42-G42)-(H42-I42) -> 0
A43: 471200 | B43: Créditeurs divers (ajustements des autres dettes) | C43: DMBJ | D43: ='BALANCE 2026'!H43 -> 0 | E43: ='BALANCE 2026'!I43 -> 0 | F43: =MAX(0,(H43-I43)-(D43-E43)) -> 0 | G43: =MAX(0,(D43-E43)-(H43-I43)) -> 0 | H43: =ROUND(MAX(0,-(E43-D43+HYPOTHESES!F$31)),0) -> 0 | I43: =ROUND(MAX(0,(E43-D43+HYPOTHESES!F$31)),0) -> 0 | J43: =(D43-E43)+(F43-G43)-(H43-I43) -> 0
A44: 481200 | B44: Fournisseurs d'investissements | C44: DH | D44: ='BALANCE 2026'!H44 -> 0 | E44: ='BALANCE 2026'!I44 -> 12736111 | F44: =ROUND('INVEST ET FINANCEMENT'!F$41,0)+(H44-I44)-(D44-E44) -> 35000000 | G44: =ROUND('INVEST ET FINANCEMENT'!F$41,0) -> 35000000 | H44: 0 | I44: =ROUND(HYPOTHESES!F$28,0) -> 12736111 | J44: =(D44-E44)+(F44-G44)-(H44-I44) -> 0
A45: 521101 | B45: Banque SGCI | C45: TRESO | D45: ='BALANCE 2026'!H45 -> 216120886 | E45: ='BALANCE 2026'!I45 -> 0 | F45: =ROUND(G26+HYPOTHESES!F$51+'INVEST ET FINANCEMENT'!F$47+'INVEST ET FINANCEMENT'!F$51,0) -> 951260667 | G45: =ROUND(G26+HYPOTHESES!F$51+'INVEST ET FINANCEMENT'!F$47+'INVEST ET FINANCEMENT'!F$51,0)+(D45-E45)-(H45-I45) -> 808394555 | H45: =ROUND(MAX(0,(H99-(H46-I46))),0) -> 358986998 | I45: =ROUND(MAX(0,-(H99-(H46-I46))),0) -> 0 | J45: =(D45-E45)+(F45-G45)-(H45-I45) -> 0
A46: 571101 | B46: Caisse | C46: BS | D46: ='BALANCE 2026'!H46 -> 8987187 | E46: ='BALANCE 2026'!I46 -> 0 | F46: =ROUND(H101,0) -> 161678911 | G46: =ROUND(H101,0)+(D46-E46)-(H46-I46) -> 160062122 | H46: =ROUND(MAX(0,((D46-E46)+H101*(1-HYPOTHESES!F$30))),0) -> 10603976 | I46: =ROUND(MAX(0,-((D46-E46)+H101*(1-HYPOTHESES!F$30))),0) -> 0 | J46: =(D46-E46)+(F46-G46)-(H46-I46) -> 0
A47: 585000 | B47: Virements de fonds | C47: BS | D47: ='BALANCE 2026'!H47 -> 0 | E47: ='BALANCE 2026'!I47 -> 0 | F47: =ROUND(H101,0) -> 161678911 | G47: =ROUND(H101,0)+(D47-E47)-(H47-I47) -> 161678911 | H47: =ROUND(D47,0) -> 0 | I47: =ROUND(E47,0) -> 0 | J47: =(D47-E47)+(F47-G47)-(H47-I47) -> 0
A48: 604300 | B48: Produits d'entretien | C48: RE | D48: 0 | E48: 0 | F48: =MAX(0,(H48-I48)-(D48-E48)) -> 1475201 | G48: =MAX(0,(D48-E48)-(H48-I48)) -> 0 | H48: =ROUND(IF(HYPOTHESES!$C$43=0,0,'BALANCE 2024'!$H$48*HYPOTHESES!F$43/HYPOTHESES!$C$43),0) -> 1475201 | I48: 0 | J48: =(D48-E48)+(F48-G48)-(H48-I48) -> 0
A49: 605100 | B49: Eau | C49: RE | D49: 0 | E49: 0 | F49: =MAX(0,(H49-I49)-(D49-E49)) -> 146973 | G49: =MAX(0,(D49-E49)-(H49-I49)) -> 0 | H49: =ROUND(IF(HYPOTHESES!$C$43=0,0,'BALANCE 2024'!$H$49*HYPOTHESES!F$43/HYPOTHESES!$C$43),0) -> 146973 | I49: 0 | J49: =(D49-E49)+(F49-G49)-(H49-I49) -> 0
A50: 605200 | B50: Eléctricité | C50: RE | D50: 0 | E50: 0 | F50: =MAX(0,(H50-I50)-(D50-E50)) -> 47145846 | G50: =MAX(0,(D50-E50)-(H50-I50)) -> 0 | H50: =ROUND(IF(HYPOTHESES!$C$43=0,0,'BALANCE 2024'!$H$50*HYPOTHESES!F$43/HYPOTHESES!$C$43),0) -> 47145846 | I50: 0 | J50: =(D50-E50)+(F50-G50)-(H50-I50) -> 0
A51: 605300 | B51: Autres énergies | C51: RE | D51: 0 | E51: 0 | F51: =MAX(0,(H51-I51)-(D51-E51)) -> 23405818 | G51: =MAX(0,(D51-E51)-(H51-I51)) -> 0 | H51: =ROUND(IF(HYPOTHESES!$C$43=0,0,'BALANCE 2024'!$H$51*HYPOTHESES!F$43/HYPOTHESES!$C$43),0) -> 23405818 | I51: 0 | J51: =(D51-E51)+(F51-G51)-(H51-I51) -> 0
A52: 605500 | B52: Fournitures de bureau non stockable | C52: RE | D52: 0 | E52: 0 | F52: =MAX(0,(H52-I52)-(D52-E52)) -> 15188094 | G52: =MAX(0,(D52-E52)-(H52-I52)) -> 0 | H52: =ROUND(IF(HYPOTHESES!$C$43=0,0,'BALANCE 2024'!$H$52*HYPOTHESES!F$43/HYPOTHESES!$C$43),0) -> 15188094 | I52: 0 | J52: =(D52-E52)+(F52-G52)-(H52-I52) -> 0
A53: 605600 | B53: Achats de petit matériel et outilla | C53: RE | D53: 0 | E53: 0 | F53: =MAX(0,(H53-I53)-(D53-E53)) -> 4355324 | G53: =MAX(0,(D53-E53)-(H53-I53)) -> 0 | H53: =ROUND(IF(HYPOTHESES!$C$43=0,0,'BALANCE 2024'!$H$53*HYPOTHESES!F$43/HYPOTHESES!$C$43),0) -> 4355324 | I53: 0 | J53: =(D53-E53)+(F53-G53)-(H53-I53) -> 0
A54: 605700 | B54: Achats d'études et prestations de s | C54: RE | D54: 0 | E54: 0 | F54: =MAX(0,(H54-I54)-(D54-E54)) -> 94571946 | G54: =MAX(0,(D54-E54)-(H54-I54)) -> 0 | H54: =ROUND(IF(HYPOTHESES!$C$43=0,0,'BALANCE 2024'!$H$54*HYPOTHESES!F$43/HYPOTHESES!$C$43),0) -> 94571946 | I54: 0 | J54: =(D54-E54)+(F54-G54)-(H54-I54) -> 0
A55: 605800 | B55: Achats de materiels et equiepents | C55: RE | D55: 0 | E55: 0 | F55: =MAX(0,(H55-I55)-(D55-E55)) -> 141857917 | G55: =MAX(0,(D55-E55)-(H55-I55)) -> 0 | H55: =ROUND(HYPOTHESES!F$43-(H48+H49+H50+H51+H52+H53+H54),0) -> 141857917 | I55: 0 | J55: =(D55-E55)+(F55-G55)-(H55-I55) -> 0
A56: 616000 | B56: Transports de plis | C56: RG | D56: 0 | E56: 0 | F56: =MAX(0,(H56-I56)-(D56-E56)) -> 109775 | G56: =MAX(0,(D56-E56)-(H56-I56)) -> 0 | H56: =ROUND(IF(HYPOTHESES!$C$44=0,0,'BALANCE 2024'!$H$56*HYPOTHESES!F$44/HYPOTHESES!$C$44),0) -> 109775 | I56: 0 | J56: =(D56-E56)+(F56-G56)-(H56-I56) -> 0
A57: 618200 | B57: Transports entre ‚tablissement ou c | C57: RG | D57: 0 | E57: 0 | F57: =MAX(0,(H57-I57)-(D57-E57)) -> 1831765 | G57: =MAX(0,(D57-E57)-(H57-I57)) -> 0 | H57: =ROUND(IF(HYPOTHESES!$C$44=0,0,'BALANCE 2024'!$H$57*HYPOTHESES!F$44/HYPOTHESES!$C$44),0) -> 1831765 | I57: 0 | J57: =(D57-E57)+(F57-G57)-(H57-I57) -> 0
A58: 618300 | B58: Transports administratifs | C58: RG | D58: 0 | E58: 0 | F58: =MAX(0,(H58-I58)-(D58-E58)) -> 2524172 | G58: =MAX(0,(D58-E58)-(H58-I58)) -> 0 | H58: =ROUND(HYPOTHESES!F$44-(H56+H57),0) -> 2524172 | I58: 0 | J58: =(D58-E58)+(F58-G58)-(H58-I58) -> 0
A59: 622200 | B59: Location de batiment | C59: RH | D59: 0 | E59: 0 | F59: =MAX(0,(H59-I59)-(D59-E59)) -> 19623501 | G59: =MAX(0,(D59-E59)-(H59-I59)) -> 0 | H59: =ROUND(IF(HYPOTHESES!$C$45=0,0,'BALANCE 2024'!$H$59*HYPOTHESES!F$45/HYPOTHESES!$C$45),0) -> 19623501 | I59: 0 | J59: =(D59-E59)+(F59-G59)-(H59-I59) -> 0
A60: 624200 | B60: Entretien et réparation des biens m | C60: RH | D60: 0 | E60: 0 | F60: =MAX(0,(H60-I60)-(D60-E60)) -> 40347964 | G60: =MAX(0,(D60-E60)-(H60-I60)) -> 0 | H60: =ROUND(HYPOTHESES!F$45-(H59+H61+H62+H63+H64+H65+H66+H67),0) -> 40347964 | I60: 0 | J60: =(D60-E60)+(F60-G60)-(H60-I60) -> 0
A61: 625800 | B61: Autres primes d'assurances | C61: RH | D61: 0 | E61: 0 | F61: =MAX(0,(H61-I61)-(D61-E61)) -> 5414160 | G61: =MAX(0,(D61-E61)-(H61-I61)) -> 0 | H61: =ROUND(IF(HYPOTHESES!$C$45=0,0,'BALANCE 2024'!$H$61*HYPOTHESES!F$45/HYPOTHESES!$C$45),0) -> 5414160 | I61: 0 | J61: =(D61-E61)+(F61-G61)-(H61-I61) -> 0
A62: 626600 | B62: Documentation techniques | C62: RH | D62: 0 | E62: 0 | F62: =MAX(0,(H62-I62)-(D62-E62)) -> 37749 | G62: =MAX(0,(D62-E62)-(H62-I62)) -> 0 | H62: =ROUND(IF(HYPOTHESES!$C$45=0,0,'BALANCE 2024'!$H$62*HYPOTHESES!F$45/HYPOTHESES!$C$45),0) -> 37749 | I62: 0 | J62: =(D62-E62)+(F62-G62)-(H62-I62) -> 0
A63: 627700 | B63: Frais de colloques, séminaires, con | C63: RH | D63: 0 | E63: 0 | F63: =MAX(0,(H63-I63)-(D63-E63)) -> 69009 | G63: =MAX(0,(D63-E63)-(H63-I63)) -> 0 | H63: =ROUND(IF(HYPOTHESES!$C$45=0,0,'BALANCE 2024'!$H$63*HYPOTHESES!F$45/HYPOTHESES!$C$45),0) -> 69009 | I63: 0 | J63: =(D63-E63)+(F63-G63)-(H63-I63) -> 0
A64: 628800 | B64: Autres frais de télécommunications | C64: RH | D64: 0 | E64: 0 | F64: =MAX(0,(H64-I64)-(D64-E64)) -> 936690 | G64: =MAX(0,(D64-E64)-(H64-I64)) -> 0 | H64: =ROUND(IF(HYPOTHESES!$C$45=0,0,'BALANCE 2024'!$H$64*HYPOTHESES!F$45/HYPOTHESES!$C$45),0) -> 936690 | I64: 0 | J64: =(D64-E64)+(F64-G64)-(H64-I64) -> 0
A65: 631800 | B65: Autres frais bancaires | C65: RH | D65: 0 | E65: 0 | F65: =MAX(0,(H65-I65)-(D65-E65)) -> 26648373 | G65: =MAX(0,(D65-E65)-(H65-I65)) -> 0 | H65: =ROUND(IF(HYPOTHESES!$C$45=0,0,'BALANCE 2024'!$H$65*HYPOTHESES!F$45/HYPOTHESES!$C$45),0) -> 26648373 | I65: 0 | J65: =(D65-E65)+(F65-G65)-(H65-I65) -> 0
A66: 632800 | B66: Divers frais | C66: RH | D66: 0 | E66: 0 | F66: =MAX(0,(H66-I66)-(D66-E66)) -> 5606900 | G66: =MAX(0,(D66-E66)-(H66-I66)) -> 0 | H66: =ROUND(IF(HYPOTHESES!$C$45=0,0,'BALANCE 2024'!$H$66*HYPOTHESES!F$45/HYPOTHESES!$C$45),0) -> 5606900 | I66: 0 | J66: =(D66-E66)+(F66-G66)-(H66-I66) -> 0
A67: 638800 | B67: Charges externes diverses | C67: RH | D67: 0 | E67: 0 | F67: =MAX(0,(H67-I67)-(D67-E67)) -> 27265266 | G67: =MAX(0,(D67-E67)-(H67-I67)) -> 0 | H67: =ROUND(IF(HYPOTHESES!$C$45=0,0,'BALANCE 2024'!$H$67*HYPOTHESES!F$45/HYPOTHESES!$C$45),0) -> 27265266 | I67: 0 | J67: =(D67-E67)+(F67-G67)-(H67-I67) -> 0
A68: 641100 | B68: Impot foncier | C68: RI | D68: 0 | E68: 0 | F68: =MAX(0,(H68-I68)-(D68-E68)) -> 424457 | G68: =MAX(0,(D68-E68)-(H68-I68)) -> 0 | H68: =ROUND(IF(HYPOTHESES!$C$46=0,0,'BALANCE 2024'!$H$68*HYPOTHESES!F$46/HYPOTHESES!$C$46),0) -> 424457 | I68: 0 | J68: =(D68-E68)+(F68-G68)-(H68-I68) -> 0
A69: 641201 | B69: Patente commerciale | C69: RI | D69: 0 | E69: 0 | F69: =MAX(0,(H69-I69)-(D69-E69)) -> 10676434 | G69: =MAX(0,(D69-E69)-(H69-I69)) -> 0 | H69: =ROUND(HYPOTHESES!F$46-(H68+H70+H71+H72+H73+H74+H75+H76),0) -> 10676434 | I69: 0 | J69: =(D69-E69)+(F69-G69)-(H69-I69) -> 0
A70: 641202 | B70: Patente transport | C70: RI | D70: 0 | E70: 0 | F70: =MAX(0,(H70-I70)-(D70-E70)) -> 1825986 | G70: =MAX(0,(D70-E70)-(H70-I70)) -> 0 | H70: =ROUND(IF(HYPOTHESES!$C$46=0,0,'BALANCE 2024'!$H$70*HYPOTHESES!F$46/HYPOTHESES!$C$46),0) -> 1825986 | I70: 0 | J70: =(D70-E70)+(F70-G70)-(H70-I70) -> 0
A71: 641300 | B71: Taxes sur appointements et salaires | C71: RI | D71: 0 | E71: 0 | F71: =MAX(0,(H71-I71)-(D71-E71)) -> 974572 | G71: =MAX(0,(D71-E71)-(H71-I71)) -> 0 | H71: =ROUND(IF(HYPOTHESES!$C$46=0,0,'BALANCE 2024'!$H$71*HYPOTHESES!F$46/HYPOTHESES!$C$46),0) -> 974572 | I71: 0 | J71: =(D71-E71)+(F71-G71)-(H71-I71) -> 0
A72: 641400 | B72: Taxes d'apprentissage | C72: RI | D72: 0 | E72: 0 | F72: =MAX(0,(H72-I72)-(D72-E72)) -> 122699 | G72: =MAX(0,(D72-E72)-(H72-I72)) -> 0 | H72: =ROUND(IF(HYPOTHESES!$C$46=0,0,'BALANCE 2024'!$H$72*HYPOTHESES!F$46/HYPOTHESES!$C$46),0) -> 122699 | I72: 0 | J72: =(D72-E72)+(F72-G72)-(H72-I72) -> 0
A73: 641500 | B73: Formation professionnelle continue | C73: RI | D73: 0 | E73: 0 | F73: =MAX(0,(H73-I73)-(D73-E73)) -> 368112 | G73: =MAX(0,(D73-E73)-(H73-I73)) -> 0 | H73: =ROUND(IF(HYPOTHESES!$C$46=0,0,'BALANCE 2024'!$H$73*HYPOTHESES!F$46/HYPOTHESES!$C$46),0) -> 368112 | I73: 0 | J73: =(D73-E73)+(F73-G73)-(H73-I73) -> 0
A74: 641830 | B74: Tse | C74: RI | D74: 0 | E74: 0 | F74: =MAX(0,(H74-I74)-(D74-E74)) -> 249587 | G74: =MAX(0,(D74-E74)-(H74-I74)) -> 0 | H74: =ROUND(IF(HYPOTHESES!$C$46=0,0,'BALANCE 2024'!$H$74*HYPOTHESES!F$46/HYPOTHESES!$C$46),0) -> 249587 | I74: 0 | J74: =(D74-E74)+(F74-G74)-(H74-I74) -> 0
A75: 646200 | B75: Droits de timbre | C75: RI | D75: 0 | E75: 0 | F75: =MAX(0,(H75-I75)-(D75-E75)) -> 2034621 | G75: =MAX(0,(D75-E75)-(H75-I75)) -> 0 | H75: =ROUND(IF(HYPOTHESES!$C$46=0,0,'BALANCE 2024'!$H$75*HYPOTHESES!F$46/HYPOTHESES!$C$46),0) -> 2034621 | I75: 0 | J75: =(D75-E75)+(F75-G75)-(H75-I75) -> 0
A76: 648000 | B76: Autres impots et taxes | C76: RI | D76: 0 | E76: 0 | F76: =MAX(0,(H76-I76)-(D76-E76)) -> 855586 | G76: =MAX(0,(D76-E76)-(H76-I76)) -> 0 | H76: =ROUND(IF(HYPOTHESES!$C$46=0,0,'BALANCE 2024'!$H$76*HYPOTHESES!F$46/HYPOTHESES!$C$46),0) -> 855586 | I76: 0 | J76: =(D76-E76)+(F76-G76)-(H76-I76) -> 0
A77: 658800 | B77: Autres charges diverses | C77: RJ | D77: 0 | E77: 0 | F77: =MAX(0,(H77-I77)-(D77-E77)) -> 1571269 | G77: =MAX(0,(D77-E77)-(H77-I77)) -> 0 | H77: =ROUND(HYPOTHESES!F$47,0) -> 1571269 | I77: 0 | J77: =(D77-E77)+(F77-G77)-(H77-I77) -> 0
A78: 661100 | B78: Appointements salaires national | C78: RK | D78: 0 | E78: 0 | F78: =MAX(0,(H78-I78)-(D78-E78)) -> 69556600 | G78: =MAX(0,(D78-E78)-(H78-I78)) -> 0 | H78: =ROUND(HYPOTHESES!F$48-(H79+H80+H81+H82+H83),0) -> 69556600 | I78: 0 | J78: =(D78-E78)+(F78-G78)-(H78-I78) -> 0
A79: 661200 | B79: Primes et gratifications | C79: RK | D79: 0 | E79: 0 | F79: =MAX(0,(H79-I79)-(D79-E79)) -> 23513642 | G79: =MAX(0,(D79-E79)-(H79-I79)) -> 0 | H79: =ROUND(IF(HYPOTHESES!$C$48=0,0,'BALANCE 2024'!$H$79*HYPOTHESES!F$48/HYPOTHESES!$C$48),0) -> 23513642 | I79: 0 | J79: =(D79-E79)+(F79-G79)-(H79-I79) -> 0
A80: 661300 | B80: Congés payés | C80: RK | D80: 0 | E80: 0 | F80: =MAX(0,(H80-I80)-(D80-E80)) -> 7758368 | G80: =MAX(0,(D80-E80)-(H80-I80)) -> 0 | H80: =ROUND(IF(HYPOTHESES!$C$48=0,0,'BALANCE 2024'!$H$80*HYPOTHESES!F$48/HYPOTHESES!$C$48),0) -> 7758368 | I80: 0 | J80: =(D80-E80)+(F80-G80)-(H80-I80) -> 0
A81: 661400 | B81: Indem.preavis&licenc imposables | C81: RK | D81: 0 | E81: 0 | F81: =MAX(0,(H81-I81)-(D81-E81)) -> 7834949 | G81: =MAX(0,(D81-E81)-(H81-I81)) -> 0 | H81: =ROUND(IF(HYPOTHESES!$C$48=0,0,'BALANCE 2024'!$H$81*HYPOTHESES!F$48/HYPOTHESES!$C$48),0) -> 7834949 | I81: 0 | J81: =(D81-E81)+(F81-G81)-(H81-I81) -> 0
A82: 663400 | B82: Indemnités de transport | C82: RK | D82: 0 | E82: 0 | F82: =MAX(0,(H82-I82)-(D82-E82)) -> 8114786 | G82: =MAX(0,(D82-E82)-(H82-I82)) -> 0 | H82: =ROUND(IF(HYPOTHESES!$C$48=0,0,'BALANCE 2024'!$H$82*HYPOTHESES!F$48/HYPOTHESES!$C$48),0) -> 8114786 | I82: 0 | J82: =(D82-E82)+(F82-G82)-(H82-I82) -> 0
A83: 664104 | B83: Charges socialescr employeur | C83: RK | D83: 0 | E83: 0 | F83: =MAX(0,(H83-I83)-(D83-E83)) -> 8261585 | G83: =MAX(0,(D83-E83)-(H83-I83)) -> 0 | H83: =ROUND(IF(HYPOTHESES!$C$48=0,0,'BALANCE 2024'!$H$83*HYPOTHESES!F$48/HYPOTHESES!$C$48),0) -> 8261585 | I83: 0 | J83: =(D83-E83)+(F83-G83)-(H83-I83) -> 0
A84: 671201 | B84: Interet des emprunts ecobank | C84: RM | D84: 0 | E84: 0 | F84: =MAX(0,(H84-I84)-(D84-E84)) -> 0 | G84: =MAX(0,(D84-E84)-(H84-I84)) -> 0 | H84: =ROUND('INVEST ET FINANCEMENT'!F$64,0) -> 0 | I84: 0 | J84: =(D84-E84)+(F84-G84)-(H84-I84) -> 0
A85: 672301 | B85: Interet de credit bail bni -1 | C85: RM | D85: 0 | E85: 0 | F85: =MAX(0,(H85-I85)-(D85-E85)) -> 0 | G85: =MAX(0,(D85-E85)-(H85-I85)) -> 0 | H85: =ROUND('INVEST ET FINANCEMENT'!F$65,0) -> 0 | I85: 0 | J85: =(D85-E85)+(F85-G85)-(H85-I85) -> 0
A86: 681301 | B86: Dotations aux amortissements : aménagements | C86: RL | D86: 0 | E86: 0 | F86: =MAX(0,(H86-I86)-(D86-E86)) -> 19282845 | G86: =MAX(0,(D86-E86)-(H86-I86)) -> 0 | H86: =ROUND('INVEST ET FINANCEMENT'!F$31,0) -> 19282845 | I86: 0 | J86: =(D86-E86)+(F86-G86)-(H86-I86) -> 0
A87: 681302 | B87: Dotations aux amortissements : matériel et outillage | C87: RL | D87: 0 | E87: 0 | F87: =MAX(0,(H87-I87)-(D87-E87)) -> 56854932 | G87: =MAX(0,(D87-E87)-(H87-I87)) -> 0 | H87: =ROUND('INVEST ET FINANCEMENT'!F$34,0) -> 56854932 | I87: 0 | J87: =(D87-E87)+(F87-G87)-(H87-I87) -> 0
A88: 681303 | B88: Dotations aux amortissements : bureau et informatique | C88: RL | D88: 0 | E88: 0 | F88: =MAX(0,(H88-I88)-(D88-E88)) -> 5000000 | G88: =MAX(0,(D88-E88)-(H88-I88)) -> 0 | H88: =ROUND('INVEST ET FINANCEMENT'!F$37,0) -> 5000000 | I88: 0 | J88: =(D88-E88)+(F88-G88)-(H88-I88) -> 0
A89: 681304 | B89: Dotations aux amortissements : transport | C89: RL | D89: 0 | E89: 0 | F89: =MAX(0,(H89-I89)-(D89-E89)) -> 15958378 | G89: =MAX(0,(D89-E89)-(H89-I89)) -> 0 | H89: =ROUND('INVEST ET FINANCEMENT'!F$40,0) -> 15958378 | I89: 0 | J89: =(D89-E89)+(F89-G89)-(H89-I89) -> 0
A90: 691100 | B90: Dotations aux provisions pour risques et charges | C90: RL | D90: 0 | E90: 0 | F90: =MAX(0,(H90-I90)-(D90-E90)) -> 6059296 | G90: =MAX(0,(D90-E90)-(H90-I90)) -> 0 | H90: =ROUND(HYPOTHESES!F$50,0) -> 6059296 | I90: 0 | J90: =(D90-E90)+(F90-G90)-(H90-I90) -> 0
A91: 705100 | B91: Travaux facturés | C91: TC | D91: 0 | E91: 0 | F91: =MAX(0,(H91-I91)-(D91-E91)) -> 0 | G91: =MAX(0,(D91-E91)-(H91-I91)) -> 826983667 | H91: 0 | I91: =ROUND(HYPOTHESES!F$42,0) -> 826983667 | J91: =(D91-E91)+(F91-G91)-(H91-I91) -> 0
A92: 771200 | B92: Intérêts des prêts | C92: TK | D92: 0 | E92: 0 | F92: =MAX(0,(H92-I92)-(D92-E92)) -> 0 | G92: =MAX(0,(D92-E92)-(H92-I92)) -> 848594 | H92: 0 | I92: =ROUND(HYPOTHESES!F$51,0) -> 848594 | J92: =(D92-E92)+(F92-G92)-(H92-I92) -> 0
A93: 891100 | B93: Impôts sur les bénéfices | C93: RS | D93: 0 | E93: 0 | F93: =MAX(0,(H93-I93)-(D93-E93)) -> 30492779 | G93: =MAX(0,(D93-E93)-(H93-I93)) -> 0 | H93: =ROUND(IF(HYPOTHESES!F$54>=HYPOTHESES!F$55,HYPOTHESES!F$56,0),0) -> 30492779 | I93: 0 | J93: =(D93-E93)+(F93-G93)-(H93-I93) -> 0
A94: 895000 | B94: Impôt minimum forfaitaire (IMF) | C94: RS | D94: 0 | E94: 0 | F94: =MAX(0,(H94-I94)-(D94-E94)) -> 0 | G94: =MAX(0,(D94-E94)-(H94-I94)) -> 0 | H94: =ROUND(IF(HYPOTHESES!F$54<HYPOTHESES!F$55,HYPOTHESES!F$56,0),0) -> 0 | I94: 0 | J94: =(D94-E94)+(F94-G94)-(H94-I94) -> 0
B96: TOTAL BALANCE | D96: =SUM(D5:D94) -> 1918023362 | E96: =SUM(E5:E94) -> 1918023362 | F96: =SUM(F5:F94) -> 3991287342 | G96: =SUM(G5:G94) -> 3991287342 | H96: =SUM(H5:H94) -> 2859288843 | I96: =SUM(I5:I94) -> 2859288843 | J96: =SUM(J5:J94) -> 0
B97: Écart débit - crédit (doit être nul) | D97: =D96-E96 -> 0 | F97: =F96-G96 -> 0 | H97: =H96-I96 -> 0
B99: Calcul : trésorerie totale à répartir (banque + caisse) | H99: =-(SUM(H5:H44)-SUM(I5:I44)+SUM(H47:H94)-SUM(I47:I94)) -> 369590974
B100: Calcul : sorties de banque de l'exercice (crédit 521) | H100: =ROUND((G26+HYPOTHESES!F$51+'INVEST ET FINANCEMENT'!F$47+'INVEST ET FINANCEMENT'!F$51+(D45-E45)+(D46-E46)-H99)/(1-HYPOTHESES!F$29*(1-HYPOTHESES!F$30)),0) -> 808394555
B101: Calcul : approvisionnement de la caisse (% des sorties de banque) | H101: =ROUND(HYPOTHESES!F$29*H100,0) -> 161678911

Sheet BALANCE 2028
A1: BALANCE GÉNÉRALE À 6 COLONNES : EXERCICE 2028 (PRÉVISIONNEL)
A2: Ouverture = clôture de l'exercice précédent (classes 6 à 8 soldées, résultat N-1 en 13). Clôture calculée depuis les hypothèses ; mouvements = flux de l'exercice. Soldes après inventaire, avant écritures de clôture. Ne rien saisir.
D3: Soldes d'ouverture | F3: Mouvements de l'exercice | H3: Soldes de clôture | J3: Contrôle
A4: Compte | B4: Intitulé | C4: Poste | D4: Débit | E4: Crédit | F4: Débit | G4: Crédit | H4: Débit | I4: Crédit | J4: Ouv.+Mvts-Clôt.
A5: 101000 | B5: Capital social | C5: CA | D5: ='BALANCE 2027'!H5 -> 0 | E5: ='BALANCE 2027'!I5 -> 10000000 | F5: =ROUND('INVEST ET FINANCEMENT'!G$51,0)+(H5-I5)-(D5-E5) -> 0 | G5: =ROUND('INVEST ET FINANCEMENT'!G$51,0) -> 0 | H5: 0 | I5: =ROUND(E5+'INVEST ET FINANCEMENT'!G$51,0) -> 10000000 | J5: =(D5-E5)+(F5-G5)-(H5-I5) -> 0
A6: 111000 | B6: Réserve légale | C6: CF | D6: ='BALANCE 2027'!H6 -> 0 | E6: ='BALANCE 2027'!I6 -> 2000000 | F6: =ROUND(HYPOTHESES!G$58,0)+(H6-I6)-(D6-E6) -> 0 | G6: =ROUND(HYPOTHESES!G$58,0) -> 0 | H6: 0 | I6: =ROUND(E6+HYPOTHESES!G$58,0) -> 2000000 | J6: =(D6-E6)+(F6-G6)-(H6-I6) -> 0
A7: 121000 | B7: Report à nouveau | C7: CH | D7: ='BALANCE 2027'!H7 -> 0 | E7: ='BALANCE 2027'!I7 -> 1023025123 | F7: =MAX(0,(H7-I7)-(D7-E7)) -> 0 | G7: =MAX(0,(D7-E7)-(H7-I7)) -> 91478335 | H7: =ROUND(MAX(0,-(E7-D7+HYPOTHESES!G$60)),0) -> 0 | I7: =ROUND(MAX(0,(E7-D7+HYPOTHESES!G$60)),0) -> 1114503458 | J7: =(D7-E7)+(F7-G7)-(H7-I7) -> 0
A8: 130100 | B8: Résultat en instance d'affectation : bénéfice | C8: R13 | D8: =MAX(0,-(SUM('BALANCE 2027'!I48:I94)-SUM('BALANCE 2027'!H48:H94))) -> 0 | E8: =MAX(0,(SUM('BALANCE 2027'!I48:I94)-SUM('BALANCE 2027'!H48:H94))) -> 91478335 | F8: =MAX(0,(H8-I8)-(D8-E8)) -> 91478335 | G8: =MAX(0,(D8-E8)-(H8-I8)) -> 0 | H8: 0 | I8: 0 | J8: =(D8-E8)+(F8-G8)-(H8-I8) -> 0
A9: 162002 | B9: Emprunts auprès des établissements de crédit (BNI) | C9: DA | D9: ='BALANCE 2027'!H9 -> 0 | E9: ='BALANCE 2027'!I9 -> 0 | F9: =ROUND('INVEST ET FINANCEMENT'!G$47,0)+(H9-I9)-(D9-E9) -> 0 | G9: =ROUND('INVEST ET FINANCEMENT'!G$47,0) -> 0 | H9: 0 | I9: =ROUND(E9+'INVEST ET FINANCEMENT'!G$47-'INVEST ET FINANCEMENT'!G$48,0) -> 0 | J9: =(D9-E9)+(F9-G9)-(H9-I9) -> 0
A10: 173060 | B10: Dettes de location-acquisition | C10: DB | D10: ='BALANCE 2027'!H10 -> 0 | E10: ='BALANCE 2027'!I10 -> 0 | F10: =ROUND('INVEST ET FINANCEMENT'!G$49,0) -> 0 | G10: =ROUND('INVEST ET FINANCEMENT'!G$49,0)+(D10-E10)-(H10-I10) -> 0 | H10: 0 | I10: =ROUND(E10-'INVEST ET FINANCEMENT'!G$49,0) -> 0 | J10: =(D10-E10)+(F10-G10)-(H10-I10) -> 0
A11: 196100 | B11: Provisions pour pensions et obligations similaires (IFC) | C11: DC | D11: ='BALANCE 2027'!H11 -> 0 | E11: ='BALANCE 2027'!I11 -> 39451784 | F11: =ROUND(HYPOTHESES!G$20,0)+(H11-I11)-(D11-E11) -> 0 | G11: =ROUND(HYPOTHESES!G$20,0) -> 6059296 | H11: 0 | I11: =ROUND(E11+HYPOTHESES!G$20,0) -> 45511080 | J11: =(D11-E11)+(F11-G11)-(H11-I11) -> 0
A12: 234100 | B12: Aménagements, agencements et installations techniques | C12: AL | D12: ='BALANCE 2027'!H12 -> 103601492 | E12: ='BALANCE 2027'!I12 -> 0 | F12: =ROUND('INVEST ET FINANCEMENT'!G$9,0) -> 0 | G12: =ROUND('INVEST ET FINANCEMENT'!G$9,0)+(D12-E12)-(H12-I12) -> 0 | H12: =ROUND(D12+'INVEST ET FINANCEMENT'!G$9,0) -> 103601492 | I12: 0 | J12: =(D12-E12)+(F12-G12)-(H12-I12) -> 0
A13: 241100 | B13: Matériel industriel | C13: AM | D13: ='BALANCE 2027'!H13 -> 373845268 | E13: ='BALANCE 2027'!I13 -> 0 | F13: =ROUND('INVEST ET FINANCEMENT'!G$10,0) -> 30000000 | G13: =ROUND('INVEST ET FINANCEMENT'!G$10,0)+(D13-E13)-(H13-I13) -> 0 | H13: =ROUND(D13+'INVEST ET FINANCEMENT'!G$10,0) -> 403845268 | I13: 0 | J13: =(D13-E13)+(F13-G13)-(H13-I13) -> 0
A14: 244100 | B14: Matériel de bureau | C14: AM | D14: ='BALANCE 2027'!H14 -> 9306956 | E14: ='BALANCE 2027'!I14 -> 0 | F14: =MAX(0,(H14-I14)-(D14-E14)) -> 0 | G14: =MAX(0,(D14-E14)-(H14-I14)) -> 0 | H14: =ROUND(D14,0) -> 9306956 | I14: 0 | J14: =(D14-E14)+(F14-G14)-(H14-I14) -> 0
A15: 244200 | B15: Matériel informatique | C15: AM | D15: ='BALANCE 2027'!H15 -> 23910459 | E15: ='BALANCE 2027'!I15 -> 0 | F15: =ROUND('INVEST ET FINANCEMENT'!G$11,0) -> 5000000 | G15: =ROUND('INVEST ET FINANCEMENT'!G$11,0)+(D15-E15)-(H15-I15) -> 0 | H15: =ROUND(D15+'INVEST ET FINANCEMENT'!G$11,0) -> 28910459 | I15: 0 | J15: =(D15-E15)+(F15-G15)-(H15-I15) -> 0
A16: 245100 | B16: Matériel automobile | C16: AN | D16: ='BALANCE 2027'!H16 -> 423638205 | E16: ='BALANCE 2027'!I16 -> 0 | F16: =ROUND('INVEST ET FINANCEMENT'!G$12,0) -> 40000000 | G16: =ROUND('INVEST ET FINANCEMENT'!G$12,0)+(D16-E16)-(H16-I16) -> 0 | H16: =ROUND(D16+'INVEST ET FINANCEMENT'!G$12,0) -> 463638205 | I16: 0 | J16: =(D16-E16)+(F16-G16)-(H16-I16) -> 0
A17: 245600 | B17: Matériel de transport en location-acquisition | C17: AN | D17: ='BALANCE 2027'!H17 -> 28619694 | E17: ='BALANCE 2027'!I17 -> 0 | F17: =MAX(0,(H17-I17)-(D17-E17)) -> 0 | G17: =MAX(0,(D17-E17)-(H17-I17)) -> 0 | H17: =ROUND(D17,0) -> 28619694 | I17: 0 | J17: =(D17-E17)+(F17-G17)-(H17-I17) -> 0
A18: 271800 | B18: Autres prêts et créances | C18: AS | D18: ='BALANCE 2027'!H18 -> 25000000 | E18: ='BALANCE 2027'!I18 -> 0 | F18: =MAX(0,(H18-I18)-(D18-E18)) -> 0 | G18: =MAX(0,(D18-E18)-(H18-I18)) -> 0 | H18: =ROUND(D18,0) -> 25000000 | I18: 0 | J18: =(D18-E18)+(F18-G18)-(H18-I18) -> 0
A19: 275100 | B19: Dépôts et cautionnements versés | C19: AS | D19: ='BALANCE 2027'!H19 -> 231420138 | E19: ='BALANCE 2027'!I19 -> 0 | F19: =ROUND('INVEST ET FINANCEMENT'!G$13,0) -> 0 | G19: =ROUND('INVEST ET FINANCEMENT'!G$13,0)+(D19-E19)-(H19-I19) -> 0 | H19: =ROUND(D19+'INVEST ET FINANCEMENT'!G$13,0) -> 231420138 | I19: 0 | J19: =(D19-E19)+(F19-G19)-(H19-I19) -> 0
A20: 283400 | B20: Amortissements des aménagements, agencements | C20: AL | D20: ='BALANCE 2027'!H20 -> 0 | E20: ='BALANCE 2027'!I20 -> 99785011 | F20: =ROUND('INVEST ET FINANCEMENT'!G$31,0)+(H20-I20)-(D20-E20) -> 0 | G20: =ROUND('INVEST ET FINANCEMENT'!G$31,0) -> 3816481 | H20: 0 | I20: =ROUND(E20+'INVEST ET FINANCEMENT'!G$31,0) -> 103601492 | J20: =(D20-E20)+(F20-G20)-(H20-I20) -> 0
A21: 284100 | B21: Amortissements du matériel et outillage | C21: AM | D21: ='BALANCE 2027'!H21 -> 0 | E21: ='BALANCE 2027'!I21 -> 191898681 | F21: =ROUND('INVEST ET FINANCEMENT'!G$34,0)+(H21-I21)-(D21-E21) -> 0 | G21: =ROUND('INVEST ET FINANCEMENT'!G$34,0) -> 62854932 | H21: 0 | I21: =ROUND(E21+'INVEST ET FINANCEMENT'!G$34,0) -> 254753613 | J21: =(D21-E21)+(F21-G21)-(H21-I21) -> 0
A22: 284400 | B22: Amortissements du matériel de bureau et informatique | C22: AM | D22: ='BALANCE 2027'!H22 -> 0 | E22: ='BALANCE 2027'!I22 -> 30717415 | F22: =ROUND('INVEST ET FINANCEMENT'!G$37,0)+(H22-I22)-(D22-E22) -> 0 | G22: =ROUND('INVEST ET FINANCEMENT'!G$37,0) -> 5000000 | H22: 0 | I22: =ROUND(E22+'INVEST ET FINANCEMENT'!G$37,0) -> 35717415 | J22: =(D22-E22)+(F22-G22)-(H22-I22) -> 0
A23: 284500 | B23: Amortissements du matériel de transport | C23: AN | D23: ='BALANCE 2027'!H23 -> 0 | E23: ='BALANCE 2027'!I23 -> 413784210 | F23: =ROUND('INVEST ET FINANCEMENT'!G$40,0)+(H23-I23)-(D23-E23) -> 0 | G23: =ROUND('INVEST ET FINANCEMENT'!G$40,0) -> 24093971 | H23: 0 | I23: =ROUND(E23+'INVEST ET FINANCEMENT'!G$40,0) -> 437878181 | J23: =(D23-E23)+(F23-G23)-(H23-I23) -> 0
A24: 401100 | B24: Fournisseurs | C24: DJ | D24: ='BALANCE 2027'!H24 -> 0 | E24: ='BALANCE 2027'!I24 -> 85674750 | F24: =ROUND(HYPOTHESES!G$49*(1+HYPOTHESES!G$10),0)+(H24-I24)-(D24-E24) -> 563875130 | G24: =ROUND(HYPOTHESES!G$49*(1+HYPOTHESES!G$10),0) -> 568158867 | H24: 0 | I24: =ROUND(HYPOTHESES!G$49*(1+HYPOTHESES!G$10)*HYPOTHESES!G$23/360,0) -> 89958487 | J24: =(D24-E24)+(F24-G24)-(H24-I24) -> 0
A25: 409100 | B25: Fournisseurs avances et accoptes ve | C25: BH | D25: ='BALANCE 2027'!H25 -> 0 | E25: ='BALANCE 2027'!I25 -> 0 | F25: =MAX(0,(H25-I25)-(D25-E25)) -> 0 | G25: =MAX(0,(D25-E25)-(H25-I25)) -> 0 | H25: =ROUND(D25,0) -> 0 | I25: =ROUND(E25,0) -> 0 | J25: =(D25-E25)+(F25-G25)-(H25-I25) -> 0
A26: 411100 | B26: Clients | C26: BI | D26: ='BALANCE 2027'!H26 -> 534001731 | E26: ='BALANCE 2027'!I26 -> 0 | F26: =ROUND(HYPOTHESES!G$42*(1+HYPOTHESES!G$10),0) -> 1024632763 | G26: =ROUND(HYPOTHESES!G$42*(1+HYPOTHESES!G$10),0)+(D26-E26)-(H26-I26) -> 997932676 | H26: =ROUND(HYPOTHESES!G$42*(1+HYPOTHESES!G$10)*HYPOTHESES!G$22/360,0) -> 560701818 | I26: 0 | J26: =(D26-E26)+(F26-G26)-(H26-I26) -> 0
A27: 422000 | B27: Personnel, rémunérations dues | C27: DK | D27: ='BALANCE 2027'!H27 -> 0 | E27: ='BALANCE 2027'!I27 -> 13146729 | F27: =ROUND(IF(HYPOTHESES!$C$48=0,0,'BALANCE 2024'!$G$27*HYPOTHESES!G$48/HYPOTHESES!$C$48),0)+(H27-I27)-(D27-E27) -> 99982359 | G27: =ROUND(IF(HYPOTHESES!$C$48=0,0,'BALANCE 2024'!$G$27*HYPOTHESES!G$48/HYPOTHESES!$C$48),0) -> 100639696 | H27: 0 | I27: =ROUND(IF(HYPOTHESES!$C$48=0,0,'BALANCE 2024'!$I$27*HYPOTHESES!G$48/HYPOTHESES!$C$48),0) -> 13804066 | J27: =(D27-E27)+(F27-G27)-(H27-I27) -> 0
A28: 431301 | B28: CNPS, retraite part employeur | C28: DK | D28: ='BALANCE 2027'!H28 -> 0 | E28: ='BALANCE 2027'!I28 -> 5730848 | F28: =ROUND(IF(HYPOTHESES!$C$48=0,0,'BALANCE 2024'!$G$28*HYPOTHESES!G$48/HYPOTHESES!$C$48),0)+(H28-I28)-(D28-E28) -> 8388122 | G28: =ROUND(IF(HYPOTHESES!$C$48=0,0,'BALANCE 2024'!$G$28*HYPOTHESES!G$48/HYPOTHESES!$C$48),0) -> 8674665 | H28: 0 | I28: =ROUND(IF(HYPOTHESES!$C$48=0,0,'BALANCE 2024'!$I$28*HYPOTHESES!G$48/HYPOTHESES!$C$48),0) -> 6017391 | J28: =(D28-E28)+(F28-G28)-(H28-I28) -> 0
A29: 431302 | B29: CNPS, retraite part salariale | C29: DK | D29: ='BALANCE 2027'!H29 -> 0 | E29: ='BALANCE 2027'!I29 -> 1418042 | F29: =ROUND(IF(HYPOTHESES!$C$48=0,0,'BALANCE 2024'!$G$29*HYPOTHESES!G$48/HYPOTHESES!$C$48),0)+(H29-I29)-(D29-E29) -> 14119318 | G29: =ROUND(IF(HYPOTHESES!$C$48=0,0,'BALANCE 2024'!$G$29*HYPOTHESES!G$48/HYPOTHESES!$C$48),0) -> 14190220 | H29: 0 | I29: =ROUND(IF(HYPOTHESES!$C$48=0,0,'BALANCE 2024'!$I$29*HYPOTHESES!G$48/HYPOTHESES!$C$48),0) -> 1488944 | J29: =(D29-E29)+(F29-G29)-(H29-I29) -> 0
A30: 431802 | B30: CMU, part salariale | C30: DK | D30: ='BALANCE 2027'!H30 -> 0 | E30: ='BALANCE 2027'!I30 -> 190980 | F30: =ROUND(IF(HYPOTHESES!$C$48=0,0,'BALANCE 2024'!$G$30*HYPOTHESES!G$48/HYPOTHESES!$C$48),0)+(H30-I30)-(D30-E30) -> 470443 | G30: =ROUND(IF(HYPOTHESES!$C$48=0,0,'BALANCE 2024'!$G$30*HYPOTHESES!G$48/HYPOTHESES!$C$48),0) -> 479992 | H30: 0 | I30: =ROUND(IF(HYPOTHESES!$C$48=0,0,'BALANCE 2024'!$I$30*HYPOTHESES!G$48/HYPOTHESES!$C$48),0) -> 200529 | J30: =(D30-E30)+(F30-G30)-(H30-I30) -> 0
A31: 433300 | B31: Assurance et organisme de sante | C31: DK | D31: ='BALANCE 2027'!H31 -> 0 | E31: ='BALANCE 2027'!I31 -> 0 | F31: =ROUND(IF(HYPOTHESES!$C$48=0,0,'BALANCE 2024'!$G$31*HYPOTHESES!G$48/HYPOTHESES!$C$48),0)+(H31-I31)-(D31-E31) -> 0 | G31: =ROUND(IF(HYPOTHESES!$C$48=0,0,'BALANCE 2024'!$G$31*HYPOTHESES!G$48/HYPOTHESES!$C$48),0) -> 0 | H31: 0 | I31: =ROUND(IF(HYPOTHESES!$C$48=0,0,'BALANCE 2024'!$I$31*HYPOTHESES!G$48/HYPOTHESES!$C$48),0) -> 0 | J31: =(D31-E31)+(F31-G31)-(H31-I31) -> 0
A32: 441000 | B32: État, impôt sur les bénéfices | C32: DK | D32: ='BALANCE 2027'!H32 -> 0 | E32: ='BALANCE 2027'!I32 -> 30492779 | F32: =ROUND(HYPOTHESES!G$56,0)+(H32-I32)-(D32-E32) -> 30492779 | G32: =ROUND(HYPOTHESES!G$56,0) -> 33628946 | H32: 0 | I32: =ROUND(HYPOTHESES!G$56,0) -> 33628946 | J32: =(D32-E32)+(F32-G32)-(H32-I32) -> 0
A33: 442800 | B33: Autres impôts et taxes | C33: DK | D33: ='BALANCE 2027'!H33 -> 0 | E33: ='BALANCE 2027'!I33 -> 855586 | F33: =ROUND(IF(HYPOTHESES!$C$46=0,0,'BALANCE 2024'!$G$33*HYPOTHESES!G$46/HYPOTHESES!$C$46),0)+(H33-I33)-(D33-E33) -> 855586 | G33: =ROUND(IF(HYPOTHESES!$C$46=0,0,'BALANCE 2024'!$G$33*HYPOTHESES!G$46/HYPOTHESES!$C$46),0) -> 898365 | H33: 0 | I33: =ROUND(IF(HYPOTHESES!$C$46=0,0,'BALANCE 2024'!$I$33*HYPOTHESES!G$46/HYPOTHESES!$C$46),0) -> 898365 | J33: =(D33-E33)+(F33-G33)-(H33-I33) -> 0
A34: 442801 | B34: FDFP, taxe d'apprentissage | C34: DK | D34: ='BALANCE 2027'!H34 -> 0 | E34: ='BALANCE 2027'!I34 -> 122699 | F34: =ROUND(IF(HYPOTHESES!$C$46=0,0,'BALANCE 2024'!$G$34*HYPOTHESES!G$46/HYPOTHESES!$C$46),0)+(H34-I34)-(D34-E34) -> 122699 | G34: =ROUND(IF(HYPOTHESES!$C$46=0,0,'BALANCE 2024'!$G$34*HYPOTHESES!G$46/HYPOTHESES!$C$46),0) -> 128834 | H34: 0 | I34: =ROUND(IF(HYPOTHESES!$C$46=0,0,'BALANCE 2024'!$I$34*HYPOTHESES!G$46/HYPOTHESES!$C$46),0) -> 128834 | J34: =(D34-E34)+(F34-G34)-(H34-I34) -> 0
A35: 442802 | B35: FDFP, formation continue | C35: DK | D35: ='BALANCE 2027'!H35 -> 0 | E35: ='BALANCE 2027'!I35 -> 184056 | F35: =ROUND(IF(HYPOTHESES!$C$46=0,0,'BALANCE 2024'!$G$35*HYPOTHESES!G$46/HYPOTHESES!$C$46),0)+(H35-I35)-(D35-E35) -> 184056 | G35: =ROUND(IF(HYPOTHESES!$C$46=0,0,'BALANCE 2024'!$G$35*HYPOTHESES!G$46/HYPOTHESES!$C$46),0) -> 193259 | H35: 0 | I35: =ROUND(IF(HYPOTHESES!$C$46=0,0,'BALANCE 2024'!$I$35*HYPOTHESES!G$46/HYPOTHESES!$C$46),0) -> 193259 | J35: =(D35-E35)+(F35-G35)-(H35-I35) -> 0
A36: 442803 | B36: FDFP, FPC à régulariser | C36: DK | D36: ='BALANCE 2027'!H36 -> 0 | E36: ='BALANCE 2027'!I36 -> 184055 | F36: =ROUND(IF(HYPOTHESES!$C$46=0,0,'BALANCE 2024'!$G$36*HYPOTHESES!G$46/HYPOTHESES!$C$46),0)+(H36-I36)-(D36-E36) -> 184055 | G36: =ROUND(IF(HYPOTHESES!$C$46=0,0,'BALANCE 2024'!$G$36*HYPOTHESES!G$46/HYPOTHESES!$C$46),0) -> 193258 | H36: 0 | I36: =ROUND(IF(HYPOTHESES!$C$46=0,0,'BALANCE 2024'!$I$36*HYPOTHESES!G$46/HYPOTHESES!$C$46),0) -> 193258 | J36: =(D36-E36)+(F36-G36)-(H36-I36) -> 0
A37: 442820 | B37: Impôt sur salaires, part patronale | C37: DK | D37: ='BALANCE 2027'!H37 -> 0 | E37: ='BALANCE 2027'!I37 -> 433430 | F37: =ROUND(IF(HYPOTHESES!$C$46=0,0,'BALANCE 2024'!$G$37*HYPOTHESES!G$46/HYPOTHESES!$C$46),0)+(H37-I37)-(D37-E37) -> 1001629 | G37: =ROUND(IF(HYPOTHESES!$C$46=0,0,'BALANCE 2024'!$G$37*HYPOTHESES!G$46/HYPOTHESES!$C$46),0) -> 1023300 | H37: 0 | I37: =ROUND(IF(HYPOTHESES!$C$46=0,0,'BALANCE 2024'!$I$37*HYPOTHESES!G$46/HYPOTHESES!$C$46),0) -> 455101 | J37: =(D37-E37)+(F37-G37)-(H37-I37) -> 0
A38: 442840 | B38: Patente | C38: DK | D38: ='BALANCE 2027'!H38 -> 0 | E38: ='BALANCE 2027'!I38 -> 5895240 | F38: =ROUND(IF(HYPOTHESES!$C$46=0,0,'BALANCE 2024'!$G$38*HYPOTHESES!G$46/HYPOTHESES!$C$46),0)+(H38-I38)-(D38-E38) -> 10915495 | G38: =ROUND(IF(HYPOTHESES!$C$46=0,0,'BALANCE 2024'!$G$38*HYPOTHESES!G$46/HYPOTHESES!$C$46),0) -> 11210257 | H38: 0 | I38: =ROUND(IF(HYPOTHESES!$C$46=0,0,'BALANCE 2024'!$I$38*HYPOTHESES!G$46/HYPOTHESES!$C$46),0) -> 6190002 | J38: =(D38-E38)+(F38-G38)-(H38-I38) -> 0
A39: 443300 | B39: État, TVA facturée sur travaux (en attente) | C39: DK | D39: ='BALANCE 2027'!H39 -> 0 | E39: ='BALANCE 2027'!I39 -> 61568990 | F39: =ROUND(HYPOTHESES!G$42*HYPOTHESES!G$10,0)+(H39-I39)-(D39-E39) -> 153221464 | G39: =ROUND(HYPOTHESES!G$42*HYPOTHESES!G$10,0) -> 156299913 | H39: 0 | I39: =ROUND(IF('BALANCE 2024'!$H$26=0,0,'BALANCE 2024'!$I$39*H26/'BALANCE 2024'!$H$26),0) -> 64647439 | J39: =(D39-E39)+(F39-G39)-(H39-I39) -> 0
A40: 446000 | B40: Taxe spéciale d'équipement | C40: DK | D40: ='BALANCE 2027'!H40 -> 0 | E40: ='BALANCE 2027'!I40 -> 235810 | F40: =ROUND(IF(HYPOTHESES!$C$46=0,0,'BALANCE 2024'!$G$40*HYPOTHESES!G$46/HYPOTHESES!$C$46),0)+(H40-I40)-(D40-E40) -> 250276 | G40: =ROUND(IF(HYPOTHESES!$C$46=0,0,'BALANCE 2024'!$G$40*HYPOTHESES!G$46/HYPOTHESES!$C$46),0) -> 262066 | H40: 0 | I40: =ROUND(IF(HYPOTHESES!$C$46=0,0,'BALANCE 2024'!$I$40*HYPOTHESES!G$46/HYPOTHESES!$C$46),0) -> 247600 | J40: =(D40-E40)+(F40-G40)-(H40-I40) -> 0
A41: 447201 | B41: ITS retenu à la source | C41: DK | D41: ='BALANCE 2027'!H41 -> 0 | E41: ='BALANCE 2027'!I41 -> 1924253 | F41: =ROUND(IF(HYPOTHESES!$C$48=0,0,'BALANCE 2024'!$G$41*HYPOTHESES!G$48/HYPOTHESES!$C$48),0)+(H41-I41)-(D41-E41) -> 7211141 | G41: =ROUND(IF(HYPOTHESES!$C$48=0,0,'BALANCE 2024'!$G$41*HYPOTHESES!G$48/HYPOTHESES!$C$48),0) -> 7307354 | H41: 0 | I41: =ROUND(IF(HYPOTHESES!$C$48=0,0,'BALANCE 2024'!$I$41*HYPOTHESES!G$48/HYPOTHESES!$C$48),0) -> 2020466 | J41: =(D41-E41)+(F41-G41)-(H41-I41) -> 0
A42: 462100 | B42: Associés, comptes courants | C42: DM | D42: ='BALANCE 2027'!H42 -> 0 | E42: ='BALANCE 2027'!I42 -> 0 | F42: =ROUND('INVEST ET FINANCEMENT'!G$53,0)+(H42-I42)-(D42-E42) -> 0 | G42: =ROUND('INVEST ET FINANCEMENT'!G$53,0) -> 0 | H42: 0 | I42: =ROUND('INVEST ET FINANCEMENT'!G$54,0) -> 0 | J42: =(D42-E42)+(F42-G42)-(H42-I42) -> 0
A43: 471200 | B43: Créditeurs divers (ajustements des autres dettes) | C43: DMBJ | D43: ='BALANCE 2027'!H43 -> 0 | E43: ='BALANCE 2027'!I43 -> 0 | F43: =MAX(0,(H43-I43)-(D43-E43)) -> 0 | G43: =MAX(0,(D43-E43)-(H43-I43)) -> 0 | H43: =ROUND(MAX(0,-(E43-D43+HYPOTHESES!G$31)),0) -> 0 | I43: =ROUND(MAX(0,(E43-D43+HYPOTHESES!G$31)),0) -> 0 | J43: =(D43-E43)+(F43-G43)-(H43-I43) -> 0
A44: 481200 | B44: Fournisseurs d'investissements | C44: DH | D44: ='BALANCE 2027'!H44 -> 0 | E44: ='BALANCE 2027'!I44 -> 12736111 | F44: =ROUND('INVEST ET FINANCEMENT'!G$41,0)+(H44-I44)-(D44-E44) -> 60444444 | G44: =ROUND('INVEST ET FINANCEMENT'!G$41,0) -> 75000000 | H44: 0 | I44: =ROUND(HYPOTHESES!G$28,0) -> 27291667 | J44: =(D44-E44)+(F44-G44)-(H44-I44) -> 0
A45: 521101 | B45: Banque SGCI | C45: TRESO | D45: ='BALANCE 2027'!H45 -> 358986998 | E45: ='BALANCE 2027'!I45 -> 0 | F45: =ROUND(G26+HYPOTHESES!G$51+'INVEST ET FINANCEMENT'!G$47+'INVEST ET FINANCEMENT'!G$51,0) -> 998781270 | G45: =ROUND(G26+HYPOTHESES!G$51+'INVEST ET FINANCEMENT'!G$47+'INVEST ET FINANCEMENT'!G$51,0)+(D45-E45)-(H45-I45) -> 872945734 | H45: =ROUND(MAX(0,(H99-(H46-I46))),0) -> 484822534 | I45: =ROUND(MAX(0,-(H99-(H46-I46))),0) -> 0 | J45: =(D45-E45)+(F45-G45)-(H45-I45) -> 0
A46: 571101 | B46: Caisse | C46: BS | D46: ='BALANCE 2027'!H46 -> 10603976 | E46: ='BALANCE 2027'!I46 -> 0 | F46: =ROUND(H101,0) -> 174589147 | G46: =ROUND(H101,0)+(D46-E46)-(H46-I46) -> 172843256 | H46: =ROUND(MAX(0,((D46-E46)+H101*(1-HYPOTHESES!G$30))),0) -> 12349867 | I46: =ROUND(MAX(0,-((D46-E46)+H101*(1-HYPOTHESES!G$30))),0) -> 0 | J46: =(D46-E46)+(F46-G46)-(H46-I46) -> 0
A47: 585000 | B47: Virements de fonds | C47: BS | D47: ='BALANCE 2027'!H47 -> 0 | E47: ='BALANCE 2027'!I47 -> 0 | F47: =ROUND(H101,0) -> 174589147 | G47: =ROUND(H101,0)+(D47-E47)-(H47-I47) -> 174589147 | H47: =ROUND(D47,0) -> 0 | I47: =ROUND(E47,0) -> 0 | J47: =(D47-E47)+(F47-G47)-(H47-I47) -> 0
A48: 604300 | B48: Produits d'entretien | C48: RE | D48: 0 | E48: 0 | F48: =MAX(0,(H48-I48)-(D48-E48)) -> 1548961 | G48: =MAX(0,(D48-E48)-(H48-I48)) -> 0 | H48: =ROUND(IF(HYPOTHESES!$C$43=0,0,'BALANCE 2024'!$H$48*HYPOTHESES!G$43/HYPOTHESES!$C$43),0) -> 1548961 | I48: 0 | J48: =(D48-E48)+(F48-G48)-(H48-I48) -> 0
A49: 605100 | B49: Eau | C49: RE | D49: 0 | E49: 0 | F49: =MAX(0,(H49-I49)-(D49-E49)) -> 154322 | G49: =MAX(0,(D49-E49)-(H49-I49)) -> 0 | H49: =ROUND(IF(HYPOTHESES!$C$43=0,0,'BALANCE 2024'!$H$49*HYPOTHESES!G$43/HYPOTHESES!$C$43),0) -> 154322 | I49: 0 | J49: =(D49-E49)+(F49-G49)-(H49-I49) -> 0
A50: 605200 | B50: Eléctricité | C50: RE | D50: 0 | E50: 0 | F50: =MAX(0,(H50-I50)-(D50-E50)) -> 49503138 | G50: =MAX(0,(D50-E50)-(H50-I50)) -> 0 | H50: =ROUND(IF(HYPOTHESES!$C$43=0,0,'BALANCE 2024'!$H$50*HYPOTHESES!G$43/HYPOTHESES!$C$43),0) -> 49503138 | I50: 0 | J50: =(D50-E50)+(F50-G50)-(H50-I50) -> 0
A51: 605300 | B51: Autres énergies | C51: RE | D51: 0 | E51: 0 | F51: =MAX(0,(H51-I51)-(D51-E51)) -> 24576109 | G51: =MAX(0,(D51-E51)-(H51-I51)) -> 0 | H51: =ROUND(IF(HYPOTHESES!$C$43=0,0,'BALANCE 2024'!$H$51*HYPOTHESES!G$43/HYPOTHESES!$C$43),0) -> 24576109 | I51: 0 | J51: =(D51-E51)+(F51-G51)-(H51-I51) -> 0
A52: 605500 | B52: Fournitures de bureau non stockable | C52: RE | D52: 0 | E52: 0 | F52: =MAX(0,(H52-I52)-(D52-E52)) -> 15947499 | G52: =MAX(0,(D52-E52)-(H52-I52)) -> 0 | H52: =ROUND(IF(HYPOTHESES!$C$43=0,0,'BALANCE 2024'!$H$52*HYPOTHESES!G$43/HYPOTHESES!$C$43),0) -> 15947499 | I52: 0 | J52: =(D52-E52)+(F52-G52)-(H52-I52) -> 0
A53: 605600 | B53: Achats de petit matériel et outilla | C53: RE | D53: 0 | E53: 0 | F53: =MAX(0,(H53-I53)-(D53-E53)) -> 4573090 | G53: =MAX(0,(D53-E53)-(H53-I53)) -> 0 | H53: =ROUND(IF(HYPOTHESES!$C$43=0,0,'BALANCE 2024'!$H$53*HYPOTHESES!G$43/HYPOTHESES!$C$43),0) -> 4573090 | I53: 0 | J53: =(D53-E53)+(F53-G53)-(H53-I53) -> 0
A54: 605700 | B54: Achats d'études et prestations de s | C54: RE | D54: 0 | E54: 0 | F54: =MAX(0,(H54-I54)-(D54-E54)) -> 99300543 | G54: =MAX(0,(D54-E54)-(H54-I54)) -> 0 | H54: =ROUND(IF(HYPOTHESES!$C$43=0,0,'BALANCE 2024'!$H$54*HYPOTHESES!G$43/HYPOTHESES!$C$43),0) -> 99300543 | I54: 0 | J54: =(D54-E54)+(F54-G54)-(H54-I54) -> 0
A55: 605800 | B55: Achats de materiels et equiepents | C55: RE | D55: 0 | E55: 0 | F55: =MAX(0,(H55-I55)-(D55-E55)) -> 148950813 | G55: =MAX(0,(D55-E55)-(H55-I55)) -> 0 | H55: =ROUND(HYPOTHESES!G$43-(H48+H49+H50+H51+H52+H53+H54),0) -> 148950813 | I55: 0 | J55: =(D55-E55)+(F55-G55)-(H55-I55) -> 0
A56: 616000 | B56: Transports de plis | C56: RG | D56: 0 | E56: 0 | F56: =MAX(0,(H56-I56)-(D56-E56)) -> 115264 | G56: =MAX(0,(D56-E56)-(H56-I56)) -> 0 | H56: =ROUND(IF(HYPOTHESES!$C$44=0,0,'BALANCE 2024'!$H$56*HYPOTHESES!G$44/HYPOTHESES!$C$44),0) -> 115264 | I56: 0 | J56: =(D56-E56)+(F56-G56)-(H56-I56) -> 0
A57: 618200 | B57: Transports entre ‚tablissement ou c | C57: RG | D57: 0 | E57: 0 | F57: =MAX(0,(H57-I57)-(D57-E57)) -> 1923353 | G57: =MAX(0,(D57-E57)-(H57-I57)) -> 0 | H57: =ROUND(IF(HYPOTHESES!$C$44=0,0,'BALANCE 2024'!$H$57*HYPOTHESES!G$44/HYPOTHESES!$C$44),0) -> 1923353 | I57: 0 | J57: =(D57-E57)+(F57-G57)-(H57-I57) -> 0
A58: 618300 | B58: Transports administratifs | C58: RG | D58: 0 | E58: 0 | F58: =MAX(0,(H58-I58)-(D58-E58)) -> 2650380 | G58: =MAX(0,(D58-E58)-(H58-I58)) -> 0 | H58: =ROUND(HYPOTHESES!G$44-(H56+H57),0) -> 2650380 | I58: 0 | J58: =(D58-E58)+(F58-G58)-(H58-I58) -> 0
A59: 622200 | B59: Location de batiment | C59: RH | D59: 0 | E59: 0 | F59: =MAX(0,(H59-I59)-(D59-E59)) -> 20604677 | G59: =MAX(0,(D59-E59)-(H59-I59)) -> 0 | H59: =ROUND(IF(HYPOTHESES!$C$45=0,0,'BALANCE 2024'!$H$59*HYPOTHESES!G$45/HYPOTHESES!$C$45),0) -> 20604677 | I59: 0 | J59: =(D59-E59)+(F59-G59)-(H59-I59) -> 0
A60: 624200 | B60: Entretien et réparation des biens m | C60: RH | D60: 0 | E60: 0 | F60: =MAX(0,(H60-I60)-(D60-E60)) -> 42365360 | G60: =MAX(0,(D60-E60)-(H60-I60)) -> 0 | H60: =ROUND(HYPOTHESES!G$45-(H59+H61+H62+H63+H64+H65+H66+H67),0) -> 42365360 | I60: 0 | J60: =(D60-E60)+(F60-G60)-(H60-I60) -> 0
A61: 625800 | B61: Autres primes d'assurances | C61: RH | D61: 0 | E61: 0 | F61: =MAX(0,(H61-I61)-(D61-E61)) -> 5684868 | G61: =MAX(0,(D61-E61)-(H61-I61)) -> 0 | H61: =ROUND(IF(HYPOTHESES!$C$45=0,0,'BALANCE 2024'!$H$61*HYPOTHESES!G$45/HYPOTHESES!$C$45),0) -> 5684868 | I61: 0 | J61: =(D61-E61)+(F61-G61)-(H61-I61) -> 0
A62: 626600 | B62: Documentation techniques | C62: RH | D62: 0 | E62: 0 | F62: =MAX(0,(H62-I62)-(D62-E62)) -> 39636 | G62: =MAX(0,(D62-E62)-(H62-I62)) -> 0 | H62: =ROUND(IF(HYPOTHESES!$C$45=0,0,'BALANCE 2024'!$H$62*HYPOTHESES!G$45/HYPOTHESES!$C$45),0) -> 39636 | I62: 0 | J62: =(D62-E62)+(F62-G62)-(H62-I62) -> 0
A63: 627700 | B63: Frais de colloques, séminaires, con | C63: RH | D63: 0 | E63: 0 | F63: =MAX(0,(H63-I63)-(D63-E63)) -> 72460 | G63: =MAX(0,(D63-E63)-(H63-I63)) -> 0 | H63: =ROUND(IF(HYPOTHESES!$C$45=0,0,'BALANCE 2024'!$H$63*HYPOTHESES!G$45/HYPOTHESES!$C$45),0) -> 72460 | I63: 0 | J63: =(D63-E63)+(F63-G63)-(H63-I63) -> 0
A64: 628800 | B64: Autres frais de télécommunications | C64: RH | D64: 0 | E64: 0 | F64: =MAX(0,(H64-I64)-(D64-E64)) -> 983525 | G64: =MAX(0,(D64-E64)-(H64-I64)) -> 0 | H64: =ROUND(IF(HYPOTHESES!$C$45=0,0,'BALANCE 2024'!$H$64*HYPOTHESES!G$45/HYPOTHESES!$C$45),0) -> 983525 | I64: 0 | J64: =(D64-E64)+(F64-G64)-(H64-I64) -> 0
A65: 631800 | B65: Autres frais bancaires | C65: RH | D65: 0 | E65: 0 | F65: =MAX(0,(H65-I65)-(D65-E65)) -> 27980792 | G65: =MAX(0,(D65-E65)-(H65-I65)) -> 0 | H65: =ROUND(IF(HYPOTHESES!$C$45=0,0,'BALANCE 2024'!$H$65*HYPOTHESES!G$45/HYPOTHESES!$C$45),0) -> 27980792 | I65: 0 | J65: =(D65-E65)+(F65-G65)-(H65-I65) -> 0
A66: 632800 | B66: Divers frais | C66: RH | D66: 0 | E66: 0 | F66: =MAX(0,(H66-I66)-(D66-E66)) -> 5887245 | G66: =MAX(0,(D66-E66)-(H66-I66)) -> 0 | H66: =ROUND(IF(HYPOTHESES!$C$45=0,0,'BALANCE 2024'!$H$66*HYPOTHESES!G$45/HYPOTHESES!$C$45),0) -> 5887245 | I66: 0 | J66: =(D66-E66)+(F66-G66)-(H66-I66) -> 0
A67: 638800 | B67: Charges externes diverses | C67: RH | D67: 0 | E67: 0 | F67: =MAX(0,(H67-I67)-(D67-E67)) -> 28628530 | G67: =MAX(0,(D67-E67)-(H67-I67)) -> 0 | H67: =ROUND(IF(HYPOTHESES!$C$45=0,0,'BALANCE 2024'!$H$67*HYPOTHESES!G$45/HYPOTHESES!$C$45),0) -> 28628530 | I67: 0 | J67: =(D67-E67)+(F67-G67)-(H67-I67) -> 0
A68: 641100 | B68: Impot foncier | C68: RI | D68: 0 | E68: 0 | F68: =MAX(0,(H68-I68)-(D68-E68)) -> 445680 | G68: =MAX(0,(D68-E68)-(H68-I68)) -> 0 | H68: =ROUND(IF(HYPOTHESES!$C$46=0,0,'BALANCE 2024'!$H$68*HYPOTHESES!G$46/HYPOTHESES!$C$46),0) -> 445680 | I68: 0 | J68: =(D68-E68)+(F68-G68)-(H68-I68) -> 0
A69: 641201 | B69: Patente commerciale | C69: RI | D69: 0 | E69: 0 | F69: =MAX(0,(H69-I69)-(D69-E69)) -> 11210257 | G69: =MAX(0,(D69-E69)-(H69-I69)) -> 0 | H69: =ROUND(HYPOTHESES!G$46-(H68+H70+H71+H72+H73+H74+H75+H76),0) -> 11210257 | I69: 0 | J69: =(D69-E69)+(F69-G69)-(H69-I69) -> 0
A70: 641202 | B70: Patente transport | C70: RI | D70: 0 | E70: 0 | F70: =MAX(0,(H70-I70)-(D70-E70)) -> 1917285 | G70: =MAX(0,(D70-E70)-(H70-I70)) -> 0 | H70: =ROUND(IF(HYPOTHESES!$C$46=0,0,'BALANCE 2024'!$H$70*HYPOTHESES!G$46/HYPOTHESES!$C$46),0) -> 1917285 | I70: 0 | J70: =(D70-E70)+(F70-G70)-(H70-I70) -> 0
A71: 641300 | B71: Taxes sur appointements et salaires | C71: RI | D71: 0 | E71: 0 | F71: =MAX(0,(H71-I71)-(D71-E71)) -> 1023300 | G71: =MAX(0,(D71-E71)-(H71-I71)) -> 0 | H71: =ROUND(IF(HYPOTHESES!$C$46=0,0,'BALANCE 2024'!$H$71*HYPOTHESES!G$46/HYPOTHESES!$C$46),0) -> 1023300 | I71: 0 | J71: =(D71-E71)+(F71-G71)-(H71-I71) -> 0
A72: 641400 | B72: Taxes d'apprentissage | C72: RI | D72: 0 | E72: 0 | F72: =MAX(0,(H72-I72)-(D72-E72)) -> 128834 | G72: =MAX(0,(D72-E72)-(H72-I72)) -> 0 | H72: =ROUND(IF(HYPOTHESES!$C$46=0,0,'BALANCE 2024'!$H$72*HYPOTHESES!G$46/HYPOTHESES!$C$46),0) -> 128834 | I72: 0 | J72: =(D72-E72)+(F72-G72)-(H72-I72) -> 0
A73: 641500 | B73: Formation professionnelle continue | C73: RI | D73: 0 | E73: 0 | F73: =MAX(0,(H73-I73)-(D73-E73)) -> 386517 | G73: =MAX(0,(D73-E73)-(H73-I73)) -> 0 | H73: =ROUND(IF(HYPOTHESES!$C$46=0,0,'BALANCE 2024'!$H$73*HYPOTHESES!G$46/HYPOTHESES!$C$46),0) -> 386517 | I73: 0 | J73: =(D73-E73)+(F73-G73)-(H73-I73) -> 0
A74: 641830 | B74: Tse | C74: RI | D74: 0 | E74: 0 | F74: =MAX(0,(H74-I74)-(D74-E74)) -> 262066 | G74: =MAX(0,(D74-E74)-(H74-I74)) -> 0 | H74: =ROUND(IF(HYPOTHESES!$C$46=0,0,'BALANCE 2024'!$H$74*HYPOTHESES!G$46/HYPOTHESES!$C$46),0) -> 262066 | I74: 0 | J74: =(D74-E74)+(F74-G74)-(H74-I74) -> 0
A75: 646200 | B75: Droits de timbre | C75: RI | D75: 0 | E75: 0 | F75: =MAX(0,(H75-I75)-(D75-E75)) -> 2136352 | G75: =MAX(0,(D75-E75)-(H75-I75)) -> 0 | H75: =ROUND(IF(HYPOTHESES!$C$46=0,0,'BALANCE 2024'!$H$75*HYPOTHESES!G$46/HYPOTHESES!$C$46),0) -> 2136352 | I75: 0 | J75: =(D75-E75)+(F75-G75)-(H75-I75) -> 0
A76: 648000 | B76: Autres impots et taxes | C76: RI | D76: 0 | E76: 0 | F76: =MAX(0,(H76-I76)-(D76-E76)) -> 898365 | G76: =MAX(0,(D76-E76)-(H76-I76)) -> 0 | H76: =ROUND(IF(HYPOTHESES!$C$46=0,0,'BALANCE 2024'!$H$76*HYPOTHESES!G$46/HYPOTHESES!$C$46),0) -> 898365 | I76: 0 | J76: =(D76-E76)+(F76-G76)-(H76-I76) -> 0
A77: 658800 | B77: Autres charges diverses | C77: RJ | D77: 0 | E77: 0 | F77: =MAX(0,(H77-I77)-(D77-E77)) -> 1649832 | G77: =MAX(0,(D77-E77)-(H77-I77)) -> 0 | H77: =ROUND(HYPOTHESES!G$47,0) -> 1649832 | I77: 0 | J77: =(D77-E77)+(F77-G77)-(H77-I77) -> 0
A78: 661100 | B78: Appointements salaires national | C78: RK | D78: 0 | E78: 0 | F78: =MAX(0,(H78-I78)-(D78-E78)) -> 73034430 | G78: =MAX(0,(D78-E78)-(H78-I78)) -> 0 | H78: =ROUND(HYPOTHESES!G$48-(H79+H80+H81+H82+H83),0) -> 73034430 | I78: 0 | J78: =(D78-E78)+(F78-G78)-(H78-I78) -> 0
A79: 661200 | B79: Primes et gratifications | C79: RK | D79: 0 | E79: 0 | F79: =MAX(0,(H79-I79)-(D79-E79)) -> 24689324 | G79: =MAX(0,(D79-E79)-(H79-I79)) -> 0 | H79: =ROUND(IF(HYPOTHESES!$C$48=0,0,'BALANCE 2024'!$H$79*HYPOTHESES!G$48/HYPOTHESES!$C$48),0) -> 24689324 | I79: 0 | J79: =(D79-E79)+(F79-G79)-(H79-I79) -> 0
A80: 661300 | B80: Congés payés | C80: RK | D80: 0 | E80: 0 | F80: =MAX(0,(H80-I80)-(D80-E80)) -> 8146286 | G80: =MAX(0,(D80-E80)-(H80-I80)) -> 0 | H80: =ROUND(IF(HYPOTHESES!$C$48=0,0,'BALANCE 2024'!$H$80*HYPOTHESES!G$48/HYPOTHESES!$C$48),0) -> 8146286 | I80: 0 | J80: =(D80-E80)+(F80-G80)-(H80-I80) -> 0
A81: 661400 | B81: Indem.preavis&licenc imposables | C81: RK | D81: 0 | E81: 0 | F81: =MAX(0,(H81-I81)-(D81-E81)) -> 8226697 | G81: =MAX(0,(D81-E81)-(H81-I81)) -> 0 | H81: =ROUND(IF(HYPOTHESES!$C$48=0,0,'BALANCE 2024'!$H$81*HYPOTHESES!G$48/HYPOTHESES!$C$48),0) -> 8226697 | I81: 0 | J81: =(D81-E81)+(F81-G81)-(H81-I81) -> 0
A82: 663400 | B82: Indemnités de transport | C82: RK | D82: 0 | E82: 0 | F82: =MAX(0,(H82-I82)-(D82-E82)) -> 8520525 | G82: =MAX(0,(D82-E82)-(H82-I82)) -> 0 | H82: =ROUND(IF(HYPOTHESES!$C$48=0,0,'BALANCE 2024'!$H$82*HYPOTHESES!G$48/HYPOTHESES!$C$48),0) -> 8520525 | I82: 0 | J82: =(D82-E82)+(F82-G82)-(H82-I82) -> 0
A83: 664104 | B83: Charges socialescr employeur | C83: RK | D83: 0 | E83: 0 | F83: =MAX(0,(H83-I83)-(D83-E83)) -> 8674665 | G83: =MAX(0,(D83-E83)-(H83-I83)) -> 0 | H83: =ROUND(IF(HYPOTHESES!$C$48=0,0,'BALANCE 2024'!$H$83*HYPOTHESES!G$48/HYPOTHESES!$C$48),0) -> 8674665 | I83: 0 | J83: =(D83-E83)+(F83-G83)-(H83-I83) -> 0
A84: 671201 | B84: Interet des emprunts ecobank | C84: RM | D84: 0 | E84: 0 | F84: =MAX(0,(H84-I84)-(D84-E84)) -> 0 | G84: =MAX(0,(D84-E84)-(H84-I84)) -> 0 | H84: =ROUND('INVEST ET FINANCEMENT'!G$64,0) -> 0 | I84: 0 | J84: =(D84-E84)+(F84-G84)-(H84-I84) -> 0
A85: 672301 | B85: Interet de credit bail bni -1 | C85: RM | D85: 0 | E85: 0 | F85: =MAX(0,(H85-I85)-(D85-E85)) -> 0 | G85: =MAX(0,(D85-E85)-(H85-I85)) -> 0 | H85: =ROUND('INVEST ET FINANCEMENT'!G$65,0) -> 0 | I85: 0 | J85: =(D85-E85)+(F85-G85)-(H85-I85) -> 0
A86: 681301 | B86: Dotations aux amortissements : aménagements | C86: RL | D86: 0 | E86: 0 | F86: =MAX(0,(H86-I86)-(D86-E86)) -> 3816481 | G86: =MAX(0,(D86-E86)-(H86-I86)) -> 0 | H86: =ROUND('INVEST ET FINANCEMENT'!G$31,0) -> 3816481 | I86: 0 | J86: =(D86-E86)+(F86-G86)-(H86-I86) -> 0
A87: 681302 | B87: Dotations aux amortissements : matériel et outillage | C87: RL | D87: 0 | E87: 0 | F87: =MAX(0,(H87-I87)-(D87-E87)) -> 62854932 | G87: =MAX(0,(D87-E87)-(H87-I87)) -> 0 | H87: =ROUND('INVEST ET FINANCEMENT'!G$34,0) -> 62854932 | I87: 0 | J87: =(D87-E87)+(F87-G87)-(H87-I87) -> 0
A88: 681303 | B88: Dotations aux amortissements : bureau et informatique | C88: RL | D88: 0 | E88: 0 | F88: =MAX(0,(H88-I88)-(D88-E88)) -> 5000000 | G88: =MAX(0,(D88-E88)-(H88-I88)) -> 0 | H88: =ROUND('INVEST ET FINANCEMENT'!G$37,0) -> 5000000 | I88: 0 | J88: =(D88-E88)+(F88-G88)-(H88-I88) -> 0
A89: 681304 | B89: Dotations aux amortissements : transport | C89: RL | D89: 0 | E89: 0 | F89: =MAX(0,(H89-I89)-(D89-E89)) -> 24093971 | G89: =MAX(0,(D89-E89)-(H89-I89)) -> 0 | H89: =ROUND('INVEST ET FINANCEMENT'!G$40,0) -> 24093971 | I89: 0 | J89: =(D89-E89)+(F89-G89)-(H89-I89) -> 0
A90: 691100 | B90: Dotations aux provisions pour risques et charges | C90: RL | D90: 0 | E90: 0 | F90: =MAX(0,(H90-I90)-(D90-E90)) -> 6059296 | G90: =MAX(0,(D90-E90)-(H90-I90)) -> 0 | H90: =ROUND(HYPOTHESES!G$50,0) -> 6059296 | I90: 0 | J90: =(D90-E90)+(F90-G90)-(H90-I90) -> 0
A91: 705100 | B91: Travaux facturés | C91: TC | D91: 0 | E91: 0 | F91: =MAX(0,(H91-I91)-(D91-E91)) -> 0 | G91: =MAX(0,(D91-E91)-(H91-I91)) -> 868332850 | H91: 0 | I91: =ROUND(HYPOTHESES!G$42,0) -> 868332850 | J91: =(D91-E91)+(F91-G91)-(H91-I91) -> 0
A92: 771200 | B92: Intérêts des prêts | C92: TK | D92: 0 | E92: 0 | F92: =MAX(0,(H92-I92)-(D92-E92)) -> 0 | G92: =MAX(0,(D92-E92)-(H92-I92)) -> 848594 | H92: 0 | I92: =ROUND(HYPOTHESES!G$51,0) -> 848594 | J92: =(D92-E92)+(F92-G92)-(H92-I92) -> 0
A93: 891100 | B93: Impôts sur les bénéfices | C93: RS | D93: 0 | E93: 0 | F93: =MAX(0,(H93-I93)-(D93-E93)) -> 33628946 | G93: =MAX(0,(D93-E93)-(H93-I93)) -> 0 | H93: =ROUND(IF(HYPOTHESES!G$54>=HYPOTHESES!G$55,HYPOTHESES!G$56,0),0) -> 33628946 | I93: 0 | J93: =(D93-E93)+(F93-G93)-(H93-I93) -> 0
A94: 895000 | B94: Impôt minimum forfaitaire (IMF) | C94: RS | D94: 0 | E94: 0 | F94: =MAX(0,(H94-I94)-(D94-E94)) -> 0 | G94: =MAX(0,(D94-E94)-(H94-I94)) -> 0 | H94: =ROUND(IF(HYPOTHESES!G$54<HYPOTHESES!G$55,HYPOTHESES!G$56,0),0) -> 0 | I94: 0 | J94: =(D94-E94)+(F94-G94)-(H94-I94) -> 0
B96: TOTAL BALANCE | D96: =SUM(D5:D94) -> 2122934917 | E96: =SUM(E5:E94) -> 2122934917 | F96: =SUM(F5:F94) -> 4259084264 | G96: =SUM(G5:G94) -> 4259084264 | H96: =SUM(H5:H94) -> 3120511037 | I96: =SUM(I5:I94) -> 3120511037 | J96: =SUM(J5:J94) -> 0
B97: Écart débit - crédit (doit être nul) | D97: =D96-E96 -> 0 | F97: =F96-G96 -> 0 | H97: =H96-I96 -> 0
B99: Calcul : trésorerie totale à répartir (banque + caisse) | H99: =-(SUM(H5:H44)-SUM(I5:I44)+SUM(H47:H94)-SUM(I47:I94)) -> 497172401
B100: Calcul : sorties de banque de l'exercice (crédit 521) | H100: =ROUND((G26+HYPOTHESES!G$51+'INVEST ET FINANCEMENT'!G$47+'INVEST ET FINANCEMENT'!G$51+(D45-E45)+(D46-E46)-H99)/(1-HYPOTHESES!G$29*(1-HYPOTHESES!G$30)),0) -> 872945734
B101: Calcul : approvisionnement de la caisse (% des sorties de banque) | H101: =ROUND(HYPOTHESES!G$29*H100,0) -> 174589147

Sheet BALANCE 2029
A1: BALANCE GÉNÉRALE À 6 COLONNES : EXERCICE 2029 (PRÉVISIONNEL)
A2: Ouverture = clôture de l'exercice précédent (classes 6 à 8 soldées, résultat N-1 en 13). Clôture calculée depuis les hypothèses ; mouvements = flux de l'exercice. Soldes après inventaire, avant écritures de clôture. Ne rien saisir.
D3: Soldes d'ouverture | F3: Mouvements de l'exercice | H3: Soldes de clôture | J3: Contrôle
A4: Compte | B4: Intitulé | C4: Poste | D4: Débit | E4: Crédit | F4: Débit | G4: Crédit | H4: Débit | I4: Crédit | J4: Ouv.+Mvts-Clôt.
A5: 101000 | B5: Capital social | C5: CA | D5: ='BALANCE 2028'!H5 -> 0 | E5: ='BALANCE 2028'!I5 -> 10000000 | F5: =ROUND('INVEST ET FINANCEMENT'!H$51,0)+(H5-I5)-(D5-E5) -> 0 | G5: =ROUND('INVEST ET FINANCEMENT'!H$51,0) -> 0 | H5: 0 | I5: =ROUND(E5+'INVEST ET FINANCEMENT'!H$51,0) -> 10000000 | J5: =(D5-E5)+(F5-G5)-(H5-I5) -> 0
A6: 111000 | B6: Réserve légale | C6: CF | D6: ='BALANCE 2028'!H6 -> 0 | E6: ='BALANCE 2028'!I6 -> 2000000 | F6: =ROUND(HYPOTHESES!H$58,0)+(H6-I6)-(D6-E6) -> 0 | G6: =ROUND(HYPOTHESES!H$58,0) -> 0 | H6: 0 | I6: =ROUND(E6+HYPOTHESES!H$58,0) -> 2000000 | J6: =(D6-E6)+(F6-G6)-(H6-I6) -> 0
A7: 121000 | B7: Report à nouveau | C7: CH | D7: ='BALANCE 2028'!H7 -> 0 | E7: ='BALANCE 2028'!I7 -> 1114503458 | F7: =MAX(0,(H7-I7)-(D7-E7)) -> 0 | G7: =MAX(0,(D7-E7)-(H7-I7)) -> 100886838 | H7: =ROUND(MAX(0,-(E7-D7+HYPOTHESES!H$60)),0) -> 0 | I7: =ROUND(MAX(0,(E7-D7+HYPOTHESES!H$60)),0) -> 1215390296 | J7: =(D7-E7)+(F7-G7)-(H7-I7) -> 0
A8: 130100 | B8: Résultat en instance d'affectation : bénéfice | C8: R13 | D8: =MAX(0,-(SUM('BALANCE 2028'!I48:I94)-SUM('BALANCE 2028'!H48:H94))) -> 0 | E8: =MAX(0,(SUM('BALANCE 2028'!I48:I94)-SUM('BALANCE 2028'!H48:H94))) -> 100886838 | F8: =MAX(0,(H8-I8)-(D8-E8)) -> 100886838 | G8: =MAX(0,(D8-E8)-(H8-I8)) -> 0 | H8: 0 | I8: 0 | J8: =(D8-E8)+(F8-G8)-(H8-I8) -> 0
A9: 162002 | B9: Emprunts auprès des établissements de crédit (BNI) | C9: DA | D9: ='BALANCE 2028'!H9 -> 0 | E9: ='BALANCE 2028'!I9 -> 0 | F9: =ROUND('INVEST ET FINANCEMENT'!H$47,0)+(H9-I9)-(D9-E9) -> 0 | G9: =ROUND('INVEST ET FINANCEMENT'!H$47,0) -> 0 | H9: 0 | I9: =ROUND(E9+'INVEST ET FINANCEMENT'!H$47-'INVEST ET FINANCEMENT'!H$48,0) -> 0 | J9: =(D9-E9)+(F9-G9)-(H9-I9) -> 0
A10: 173060 | B10: Dettes de location-acquisition | C10: DB | D10: ='BALANCE 2028'!H10 -> 0 | E10: ='BALANCE 2028'!I10 -> 0 | F10: =ROUND('INVEST ET FINANCEMENT'!H$49,0) -> 0 | G10: =ROUND('INVEST ET FINANCEMENT'!H$49,0)+(D10-E10)-(H10-I10) -> 0 | H10: 0 | I10: =ROUND(E10-'INVEST ET FINANCEMENT'!H$49,0) -> 0 | J10: =(D10-E10)+(F10-G10)-(H10-I10) -> 0
A11: 196100 | B11: Provisions pour pensions et obligations similaires (IFC) | C11: DC | D11: ='BALANCE 2028'!H11 -> 0 | E11: ='BALANCE 2028'!I11 -> 45511080 | F11: =ROUND(HYPOTHESES!H$20,0)+(H11-I11)-(D11-E11) -> 0 | G11: =ROUND(HYPOTHESES!H$20,0) -> 6059296 | H11: 0 | I11: =ROUND(E11+HYPOTHESES!H$20,0) -> 51570376 | J11: =(D11-E11)+(F11-G11)-(H11-I11) -> 0
A12: 234100 | B12: Aménagements, agencements et installations techniques | C12: AL | D12: ='BALANCE 2028'!H12 -> 103601492 | E12: ='BALANCE 2028'!I12 -> 0 | F12: =ROUND('INVEST ET FINANCEMENT'!H$9,0) -> 0 | G12: =ROUND('INVEST ET FINANCEMENT'!H$9,0)+(D12-E12)-(H12-I12) -> 0 | H12: =ROUND(D12+'INVEST ET FINANCEMENT'!H$9,0) -> 103601492 | I12: 0 | J12: =(D12-E12)+(F12-G12)-(H12-I12) -> 0
A13: 241100 | B13: Matériel industriel | C13: AM | D13: ='BALANCE 2028'!H13 -> 403845268 | E13: ='BALANCE 2028'!I13 -> 0 | F13: =ROUND('INVEST ET FINANCEMENT'!H$10,0) -> 30000000 | G13: =ROUND('INVEST ET FINANCEMENT'!H$10,0)+(D13-E13)-(H13-I13) -> 0 | H13: =ROUND(D13+'INVEST ET FINANCEMENT'!H$10,0) -> 433845268 | I13: 0 | J13: =(D13-E13)+(F13-G13)-(H13-I13) -> 0
A14: 244100 | B14: Matériel de bureau | C14: AM | D14: ='BALANCE 2028'!H14 -> 9306956 | E14: ='BALANCE 2028'!I14 -> 0 | F14: =MAX(0,(H14-I14)-(D14-E14)) -> 0 | G14: =MAX(0,(D14-E14)-(H14-I14)) -> 0 | H14: =ROUND(D14,0) -> 9306956 | I14: 0 | J14: =(D14-E14)+(F14-G14)-(H14-I14) -> 0
A15: 244200 | B15: Matériel informatique | C15: AM | D15: ='BALANCE 2028'!H15 -> 28910459 | E15: ='BALANCE 2028'!I15 -> 0 | F15: =ROUND('INVEST ET FINANCEMENT'!H$11,0) -> 5000000 | G15: =ROUND('INVEST ET FINANCEMENT'!H$11,0)+(D15-E15)-(H15-I15) -> 0 | H15: =ROUND(D15+'INVEST ET FINANCEMENT'!H$11,0) -> 33910459 | I15: 0 | J15: =(D15-E15)+(F15-G15)-(H15-I15) -> 0
A16: 245100 | B16: Matériel automobile | C16: AN | D16: ='BALANCE 2028'!H16 -> 463638205 | E16: ='BALANCE 2028'!I16 -> 0 | F16: =ROUND('INVEST ET FINANCEMENT'!H$12,0) -> 0 | G16: =ROUND('INVEST ET FINANCEMENT'!H$12,0)+(D16-E16)-(H16-I16) -> 0 | H16: =ROUND(D16+'INVEST ET FINANCEMENT'!H$12,0) -> 463638205 | I16: 0 | J16: =(D16-E16)+(F16-G16)-(H16-I16) -> 0
A17: 245600 | B17: Matériel de transport en location-acquisition | C17: AN | D17: ='BALANCE 2028'!H17 -> 28619694 | E17: ='BALANCE 2028'!I17 -> 0 | F17: =MAX(0,(H17-I17)-(D17-E17)) -> 0 | G17: =MAX(0,(D17-E17)-(H17-I17)) -> 0 | H17: =ROUND(D17,0) -> 28619694 | I17: 0 | J17: =(D17-E17)+(F17-G17)-(H17-I17) -> 0
A18: 271800 | B18: Autres prêts et créances | C18: AS | D18: ='BALANCE 2028'!H18 -> 25000000 | E18: ='BALANCE 2028'!I18 -> 0 | F18: =MAX(0,(H18-I18)-(D18-E18)) -> 0 | G18: =MAX(0,(D18-E18)-(H18-I18)) -> 0 | H18: =ROUND(D18,0) -> 25000000 | I18: 0 | J18: =(D18-E18)+(F18-G18)-(H18-I18) -> 0
A19: 275100 | B19: Dépôts et cautionnements versés | C19: AS | D19: ='BALANCE 2028'!H19 -> 231420138 | E19: ='BALANCE 2028'!I19 -> 0 | F19: =ROUND('INVEST ET FINANCEMENT'!H$13,0) -> 0 | G19: =ROUND('INVEST ET FINANCEMENT'!H$13,0)+(D19-E19)-(H19-I19) -> 0 | H19: =ROUND(D19+'INVEST ET FINANCEMENT'!H$13,0) -> 231420138 | I19: 0 | J19: =(D19-E19)+(F19-G19)-(H19-I19) -> 0
A20: 283400 | B20: Amortissements des aménagements, agencements | C20: AL | D20: ='BALANCE 2028'!H20 -> 0 | E20: ='BALANCE 2028'!I20 -> 103601492 | F20: =ROUND('INVEST ET FINANCEMENT'!H$31,0)+(H20-I20)-(D20-E20) -> 0 | G20: =ROUND('INVEST ET FINANCEMENT'!H$31,0) -> 0 | H20: 0 | I20: =ROUND(E20+'INVEST ET FINANCEMENT'!H$31,0) -> 103601492 | J20: =(D20-E20)+(F20-G20)-(H20-I20) -> 0
A21: 284100 | B21: Amortissements du matériel et outillage | C21: AM | D21: ='BALANCE 2028'!H21 -> 0 | E21: ='BALANCE 2028'!I21 -> 254753613 | F21: =ROUND('INVEST ET FINANCEMENT'!H$34,0)+(H21-I21)-(D21-E21) -> 0 | G21: =ROUND('INVEST ET FINANCEMENT'!H$34,0) -> 68854932 | H21: 0 | I21: =ROUND(E21+'INVEST ET FINANCEMENT'!H$34,0) -> 323608545 | J21: =(D21-E21)+(F21-G21)-(H21-I21) -> 0
A22: 284400 | B22: Amortissements du matériel de bureau et informatique | C22: AM | D22: ='BALANCE 2028'!H22 -> 0 | E22: ='BALANCE 2028'!I22 -> 35717415 | F22: =ROUND('INVEST ET FINANCEMENT'!H$37,0)+(H22-I22)-(D22-E22) -> 0 | G22: =ROUND('INVEST ET FINANCEMENT'!H$37,0) -> 5000000 | H22: 0 | I22: =ROUND(E22+'INVEST ET FINANCEMENT'!H$37,0) -> 40717415 | J22: =(D22-E22)+(F22-G22)-(H22-I22) -> 0
A23: 284500 | B23: Amortissements du matériel de transport | C23: AN | D23: ='BALANCE 2028'!H23 -> 0 | E23: ='BALANCE 2028'!I23 -> 437878181 | F23: =ROUND('INVEST ET FINANCEMENT'!H$40,0)+(H23-I23)-(D23-E23) -> 0 | G23: =ROUND('INVEST ET FINANCEMENT'!H$40,0) -> 24093971 | H23: 0 | I23: =ROUND(E23+'INVEST ET FINANCEMENT'!H$40,0) -> 461972152 | J23: =(D23-E23)+(F23-G23)-(H23-I23) -> 0
A24: 401100 | B24: Fournisseurs | C24: DJ | D24: ='BALANCE 2028'!H24 -> 0 | E24: ='BALANCE 2028'!I24 -> 89958487 | F24: =ROUND(HYPOTHESES!H$49*(1+HYPOTHESES!H$10),0)+(H24-I24)-(D24-E24) -> 592068886 | G24: =ROUND(HYPOTHESES!H$49*(1+HYPOTHESES!H$10),0) -> 596566811 | H24: 0 | I24: =ROUND(HYPOTHESES!H$49*(1+HYPOTHESES!H$10)*HYPOTHESES!H$23/360,0) -> 94456412 | J24: =(D24-E24)+(F24-G24)-(H24-I24) -> 0
A25: 409100 | B25: Fournisseurs avances et accoptes ve | C25: BH | D25: ='BALANCE 2028'!H25 -> 0 | E25: ='BALANCE 2028'!I25 -> 0 | F25: =MAX(0,(H25-I25)-(D25-E25)) -> 0 | G25: =MAX(0,(D25-E25)-(H25-I25)) -> 0 | H25: =ROUND(D25,0) -> 0 | I25: =ROUND(E25,0) -> 0 | J25: =(D25-E25)+(F25-G25)-(H25-I25) -> 0
A26: 411100 | B26: Clients | C26: BI | D26: ='BALANCE 2028'!H26 -> 560701818 | E26: ='BALANCE 2028'!I26 -> 0 | F26: =ROUND(HYPOTHESES!H$42*(1+HYPOTHESES!H$10),0) -> 1075864402 | G26: =ROUND(HYPOTHESES!H$42*(1+HYPOTHESES!H$10),0)+(D26-E26)-(H26-I26) -> 1047829311 | H26: =ROUND(HYPOTHESES!H$42*(1+HYPOTHESES!H$10)*HYPOTHESES!H$22/360,0) -> 588736909 | I26: 0 | J26: =(D26-E26)+(F26-G26)-(H26-I26) -> 0
A27: 422000 | B27: Personnel, rémunérations dues | C27: DK | D27: ='BALANCE 2028'!H27 -> 0 | E27: ='BALANCE 2028'!I27 -> 13804066 | F27: =ROUND(IF(HYPOTHESES!$C$48=0,0,'BALANCE 2024'!$G$27*HYPOTHESES!H$48/HYPOTHESES!$C$48),0)+(H27-I27)-(D27-E27) -> 104981478 | G27: =ROUND(IF(HYPOTHESES!$C$48=0,0,'BALANCE 2024'!$G$27*HYPOTHESES!H$48/HYPOTHESES!$C$48),0) -> 105671681 | H27: 0 | I27: =ROUND(IF(HYPOTHESES!$C$48=0,0,'BALANCE 2024'!$I$27*HYPOTHESES!H$48/HYPOTHESES!$C$48),0) -> 14494269 | J27: =(D27-E27)+(F27-G27)-(H27-I27) -> 0
A28: 431301 | B28: CNPS, retraite part employeur | C28: DK | D28: ='BALANCE 2028'!H28 -> 0 | E28: ='BALANCE 2028'!I28 -> 6017391 | F28: =ROUND(IF(HYPOTHESES!$C$48=0,0,'BALANCE 2024'!$G$28*HYPOTHESES!H$48/HYPOTHESES!$C$48),0)+(H28-I28)-(D28-E28) -> 8807529 | G28: =ROUND(IF(HYPOTHESES!$C$48=0,0,'BALANCE 2024'!$G$28*HYPOTHESES!H$48/HYPOTHESES!$C$48),0) -> 9108398 | H28: 0 | I28: =ROUND(IF(HYPOTHESES!$C$48=0,0,'BALANCE 2024'!$I$28*HYPOTHESES!H$48/HYPOTHESES!$C$48),0) -> 6318260 | J28: =(D28-E28)+(F28-G28)-(H28-I28) -> 0
A29: 431302 | B29: CNPS, retraite part salariale | C29: DK | D29: ='BALANCE 2028'!H29 -> 0 | E29: ='BALANCE 2028'!I29 -> 1488944 | F29: =ROUND(IF(HYPOTHESES!$C$48=0,0,'BALANCE 2024'!$G$29*HYPOTHESES!H$48/HYPOTHESES!$C$48),0)+(H29-I29)-(D29-E29) -> 14825284 | G29: =ROUND(IF(HYPOTHESES!$C$48=0,0,'BALANCE 2024'!$G$29*HYPOTHESES!H$48/HYPOTHESES!$C$48),0) -> 14899731 | H29: 0 | I29: =ROUND(IF(HYPOTHESES!$C$48=0,0,'BALANCE 2024'!$I$29*HYPOTHESES!H$48/HYPOTHESES!$C$48),0) -> 1563391 | J29: =(D29-E29)+(F29-G29)-(H29-I29) -> 0
A30: 431802 | B30: CMU, part salariale | C30: DK | D30: ='BALANCE 2028'!H30 -> 0 | E30: ='BALANCE 2028'!I30 -> 200529 | F30: =ROUND(IF(HYPOTHESES!$C$48=0,0,'BALANCE 2024'!$G$30*HYPOTHESES!H$48/HYPOTHESES!$C$48),0)+(H30-I30)-(D30-E30) -> 493965 | G30: =ROUND(IF(HYPOTHESES!$C$48=0,0,'BALANCE 2024'!$G$30*HYPOTHESES!H$48/HYPOTHESES!$C$48),0) -> 503991 | H30: 0 | I30: =ROUND(IF(HYPOTHESES!$C$48=0,0,'BALANCE 2024'!$I$30*HYPOTHESES!H$48/HYPOTHESES!$C$48),0) -> 210555 | J30: =(D30-E30)+(F30-G30)-(H30-I30) -> 0
A31: 433300 | B31: Assurance et organisme de sante | C31: DK | D31: ='BALANCE 2028'!H31 -> 0 | E31: ='BALANCE 2028'!I31 -> 0 | F31: =ROUND(IF(HYPOTHESES!$C$48=0,0,'BALANCE 2024'!$G$31*HYPOTHESES!H$48/HYPOTHESES!$C$48),0)+(H31-I31)-(D31-E31) -> 0 | G31: =ROUND(IF(HYPOTHESES!$C$48=0,0,'BALANCE 2024'!$G$31*HYPOTHESES!H$48/HYPOTHESES!$C$48),0) -> 0 | H31: 0 | I31: =ROUND(IF(HYPOTHESES!$C$48=0,0,'BALANCE 2024'!$I$31*HYPOTHESES!H$48/HYPOTHESES!$C$48),0) -> 0 | J31: =(D31-E31)+(F31-G31)-(H31-I31) -> 0
A32: 441000 | B32: État, impôt sur les bénéfices | C32: DK | D32: ='BALANCE 2028'!H32 -> 0 | E32: ='BALANCE 2028'!I32 -> 33628946 | F32: =ROUND(HYPOTHESES!H$56,0)+(H32-I32)-(D32-E32) -> 33628946 | G32: =ROUND(HYPOTHESES!H$56,0) -> 36026715 | H32: 0 | I32: =ROUND(HYPOTHESES!H$56,0) -> 36026715 | J32: =(D32-E32)+(F32-G32)-(H32-I32) -> 0
A33: 442800 | B33: Autres impôts et taxes | C33: DK | D33: ='BALANCE 2028'!H33 -> 0 | E33: ='BALANCE 2028'!I33 -> 898365 | F33: =ROUND(IF(HYPOTHESES!$C$46=0,0,'BALANCE 2024'!$G$33*HYPOTHESES!H$46/HYPOTHESES!$C$46),0)+(H33-I33)-(D33-E33) -> 898365 | G33: =ROUND(IF(HYPOTHESES!$C$46=0,0,'BALANCE 2024'!$G$33*HYPOTHESES!H$46/HYPOTHESES!$C$46),0) -> 943283 | H33: 0 | I33: =ROUND(IF(HYPOTHESES!$C$46=0,0,'BALANCE 2024'!$I$33*HYPOTHESES!H$46/HYPOTHESES!$C$46),0) -> 943283 | J33: =(D33-E33)+(F33-G33)-(H33-I33) -> 0
A34: 442801 | B34: FDFP, taxe d'apprentissage | C34: DK | D34: ='BALANCE 2028'!H34 -> 0 | E34: ='BALANCE 2028'!I34 -> 128834 | F34: =ROUND(IF(HYPOTHESES!$C$46=0,0,'BALANCE 2024'!$G$34*HYPOTHESES!H$46/HYPOTHESES!$C$46),0)+(H34-I34)-(D34-E34) -> 128834 | G34: =ROUND(IF(HYPOTHESES!$C$46=0,0,'BALANCE 2024'!$G$34*HYPOTHESES!H$46/HYPOTHESES!$C$46),0) -> 135275 | H34: 0 | I34: =ROUND(IF(HYPOTHESES!$C$46=0,0,'BALANCE 2024'!$I$34*HYPOTHESES!H$46/HYPOTHESES!$C$46),0) -> 135275 | J34: =(D34-E34)+(F34-G34)-(H34-I34) -> 0
A35: 442802 | B35: FDFP, formation continue | C35: DK | D35: ='BALANCE 2028'!H35 -> 0 | E35: ='BALANCE 2028'!I35 -> 193259 | F35: =ROUND(IF(HYPOTHESES!$C$46=0,0,'BALANCE 2024'!$G$35*HYPOTHESES!H$46/HYPOTHESES!$C$46),0)+(H35-I35)-(D35-E35) -> 193259 | G35: =ROUND(IF(HYPOTHESES!$C$46=0,0,'BALANCE 2024'!$G$35*HYPOTHESES!H$46/HYPOTHESES!$C$46),0) -> 202922 | H35: 0 | I35: =ROUND(IF(HYPOTHESES!$C$46=0,0,'BALANCE 2024'!$I$35*HYPOTHESES!H$46/HYPOTHESES!$C$46),0) -> 202922 | J35: =(D35-E35)+(F35-G35)-(H35-I35) -> 0
A36: 442803 | B36: FDFP, FPC à régulariser | C36: DK | D36: ='BALANCE 2028'!H36 -> 0 | E36: ='BALANCE 2028'!I36 -> 193258 | F36: =ROUND(IF(HYPOTHESES!$C$46=0,0,'BALANCE 2024'!$G$36*HYPOTHESES!H$46/HYPOTHESES!$C$46),0)+(H36-I36)-(D36-E36) -> 193258 | G36: =ROUND(IF(HYPOTHESES!$C$46=0,0,'BALANCE 2024'!$G$36*HYPOTHESES!H$46/HYPOTHESES!$C$46),0) -> 202921 | H36: 0 | I36: =ROUND(IF(HYPOTHESES!$C$46=0,0,'BALANCE 2024'!$I$36*HYPOTHESES!H$46/HYPOTHESES!$C$46),0) -> 202921 | J36: =(D36-E36)+(F36-G36)-(H36-I36) -> 0
A37: 442820 | B37: Impôt sur salaires, part patronale | C37: DK | D37: ='BALANCE 2028'!H37 -> 0 | E37: ='BALANCE 2028'!I37 -> 455101 | F37: =ROUND(IF(HYPOTHESES!$C$46=0,0,'BALANCE 2024'!$G$37*HYPOTHESES!H$46/HYPOTHESES!$C$46),0)+(H37-I37)-(D37-E37) -> 1051710 | G37: =ROUND(IF(HYPOTHESES!$C$46=0,0,'BALANCE 2024'!$G$37*HYPOTHESES!H$46/HYPOTHESES!$C$46),0) -> 1074465 | H37: 0 | I37: =ROUND(IF(HYPOTHESES!$C$46=0,0,'BALANCE 2024'!$I$37*HYPOTHESES!H$46/HYPOTHESES!$C$46),0) -> 477856 | J37: =(D37-E37)+(F37-G37)-(H37-I37) -> 0
A38: 442840 | B38: Patente | C38: DK | D38: ='BALANCE 2028'!H38 -> 0 | E38: ='BALANCE 2028'!I38 -> 6190002 | F38: =ROUND(IF(HYPOTHESES!$C$46=0,0,'BALANCE 2024'!$G$38*HYPOTHESES!H$46/HYPOTHESES!$C$46),0)+(H38-I38)-(D38-E38) -> 11461270 | G38: =ROUND(IF(HYPOTHESES!$C$46=0,0,'BALANCE 2024'!$G$38*HYPOTHESES!H$46/HYPOTHESES!$C$46),0) -> 11770770 | H38: 0 | I38: =ROUND(IF(HYPOTHESES!$C$46=0,0,'BALANCE 2024'!$I$38*HYPOTHESES!H$46/HYPOTHESES!$C$46),0) -> 6499502 | J38: =(D38-E38)+(F38-G38)-(H38-I38) -> 0
A39: 443300 | B39: État, TVA facturée sur travaux (en attente) | C39: DK | D39: ='BALANCE 2028'!H39 -> 0 | E39: ='BALANCE 2028'!I39 -> 64647439 | F39: =ROUND(HYPOTHESES!H$42*HYPOTHESES!H$10,0)+(H39-I39)-(D39-E39) -> 160882537 | G39: =ROUND(HYPOTHESES!H$42*HYPOTHESES!H$10,0) -> 164114909 | H39: 0 | I39: =ROUND(IF('BALANCE 2024'!$H$26=0,0,'BALANCE 2024'!$I$39*H26/'BALANCE 2024'!$H$26),0) -> 67879811 | J39: =(D39-E39)+(F39-G39)-(H39-I39) -> 0
A40: 446000 | B40: Taxe spéciale d'équipement | C40: DK | D40: ='BALANCE 2028'!H40 -> 0 | E40: ='BALANCE 2028'!I40 -> 247600 | F40: =ROUND(IF(HYPOTHESES!$C$46=0,0,'BALANCE 2024'!$G$40*HYPOTHESES!H$46/HYPOTHESES!$C$46),0)+(H40-I40)-(D40-E40) -> 262789 | G40: =ROUND(IF(HYPOTHESES!$C$46=0,0,'BALANCE 2024'!$G$40*HYPOTHESES!H$46/HYPOTHESES!$C$46),0) -> 275169 | H40: 0 | I40: =ROUND(IF(HYPOTHESES!$C$46=0,0,'BALANCE 2024'!$I$40*HYPOTHESES!H$46/HYPOTHESES!$C$46),0) -> 259980 | J40: =(D40-E40)+(F40-G40)-(H40-I40) -> 0
A41: 447201 | B41: ITS retenu à la source | C41: DK | D41: ='BALANCE 2028'!H41 -> 0 | E41: ='BALANCE 2028'!I41 -> 2020466 | F41: =ROUND(IF(HYPOTHESES!$C$48=0,0,'BALANCE 2024'!$G$41*HYPOTHESES!H$48/HYPOTHESES!$C$48),0)+(H41-I41)-(D41-E41) -> 7571699 | G41: =ROUND(IF(HYPOTHESES!$C$48=0,0,'BALANCE 2024'!$G$41*HYPOTHESES!H$48/HYPOTHESES!$C$48),0) -> 7672722 | H41: 0 | I41: =ROUND(IF(HYPOTHESES!$C$48=0,0,'BALANCE 2024'!$I$41*HYPOTHESES!H$48/HYPOTHESES!$C$48),0) -> 2121489 | J41: =(D41-E41)+(F41-G41)-(H41-I41) -> 0
A42: 462100 | B42: Associés, comptes courants | C42: DM | D42: ='BALANCE 2028'!H42 -> 0 | E42: ='BALANCE 2028'!I42 -> 0 | F42: =ROUND('INVEST ET FINANCEMENT'!H$53,0)+(H42-I42)-(D42-E42) -> 0 | G42: =ROUND('INVEST ET FINANCEMENT'!H$53,0) -> 0 | H42: 0 | I42: =ROUND('INVEST ET FINANCEMENT'!H$54,0) -> 0 | J42: =(D42-E42)+(F42-G42)-(H42-I42) -> 0
A43: 471200 | B43: Créditeurs divers (ajustements des autres dettes) | C43: DMBJ | D43: ='BALANCE 2028'!H43 -> 0 | E43: ='BALANCE 2028'!I43 -> 0 | F43: =MAX(0,(H43-I43)-(D43-E43)) -> 0 | G43: =MAX(0,(D43-E43)-(H43-I43)) -> 0 | H43: =ROUND(MAX(0,-(E43-D43+HYPOTHESES!H$31)),0) -> 0 | I43: =ROUND(MAX(0,(E43-D43+HYPOTHESES!H$31)),0) -> 0 | J43: =(D43-E43)+(F43-G43)-(H43-I43) -> 0
A44: 481200 | B44: Fournisseurs d'investissements | C44: DH | D44: ='BALANCE 2028'!H44 -> 0 | E44: ='BALANCE 2028'!I44 -> 27291667 | F44: =ROUND('INVEST ET FINANCEMENT'!H$41,0)+(H44-I44)-(D44-E44) -> 49555556 | G44: =ROUND('INVEST ET FINANCEMENT'!H$41,0) -> 35000000 | H44: 0 | I44: =ROUND(HYPOTHESES!H$28,0) -> 12736111 | J44: =(D44-E44)+(F44-G44)-(H44-I44) -> 0
A45: 521101 | B45: Banque SGCI | C45: TRESO | D45: ='BALANCE 2028'!H45 -> 484822534 | E45: ='BALANCE 2028'!I45 -> 0 | F45: =ROUND(G26+HYPOTHESES!H$51+'INVEST ET FINANCEMENT'!H$47+'INVEST ET FINANCEMENT'!H$51,0) -> 1048677905 | G45: =ROUND(G26+HYPOTHESES!H$51+'INVEST ET FINANCEMENT'!H$47+'INVEST ET FINANCEMENT'!H$51,0)+(D45-E45)-(H45-I45) -> 904268794 | H45: =ROUND(MAX(0,(H99-(H46-I46))),0) -> 629231645 | I45: =ROUND(MAX(0,-(H99-(H46-I46))),0) -> 0 | J45: =(D45-E45)+(F45-G45)-(H45-I45) -> 0
A46: 571101 | B46: Caisse | C46: BS | D46: ='BALANCE 2028'!H46 -> 12349867 | E46: ='BALANCE 2028'!I46 -> 0 | F46: =ROUND(H101,0) -> 180853759 | G46: =ROUND(H101,0)+(D46-E46)-(H46-I46) -> 179045221 | H46: =ROUND(MAX(0,((D46-E46)+H101*(1-HYPOTHESES!H$30))),0) -> 14158405 | I46: =ROUND(MAX(0,-((D46-E46)+H101*(1-HYPOTHESES!H$30))),0) -> 0 | J46: =(D46-E46)+(F46-G46)-(H46-I46) -> 0
A47: 585000 | B47: Virements de fonds | C47: BS | D47: ='BALANCE 2028'!H47 -> 0 | E47: ='BALANCE 2028'!I47 -> 0 | F47: =ROUND(H101,0) -> 180853759 | G47: =ROUND(H101,0)+(D47-E47)-(H47-I47) -> 180853759 | H47: =ROUND(D47,0) -> 0 | I47: =ROUND(E47,0) -> 0 | J47: =(D47-E47)+(F47-G47)-(H47-I47) -> 0
A48: 604300 | B48: Produits d'entretien | C48: RE | D48: 0 | E48: 0 | F48: =MAX(0,(H48-I48)-(D48-E48)) -> 1626409 | G48: =MAX(0,(D48-E48)-(H48-I48)) -> 0 | H48: =ROUND(IF(HYPOTHESES!$C$43=0,0,'BALANCE 2024'!$H$48*HYPOTHESES!H$43/HYPOTHESES!$C$43),0) -> 1626409 | I48: 0 | J48: =(D48-E48)+(F48-G48)-(H48-I48) -> 0
A49: 605100 | B49: Eau | C49: RE | D49: 0 | E49: 0 | F49: =MAX(0,(H49-I49)-(D49-E49)) -> 162038 | G49: =MAX(0,(D49-E49)-(H49-I49)) -> 0 | H49: =ROUND(IF(HYPOTHESES!$C$43=0,0,'BALANCE 2024'!$H$49*HYPOTHESES!H$43/HYPOTHESES!$C$43),0) -> 162038 | I49: 0 | J49: =(D49-E49)+(F49-G49)-(H49-I49) -> 0
A50: 605200 | B50: Eléctricité | C50: RE | D50: 0 | E50: 0 | F50: =MAX(0,(H50-I50)-(D50-E50)) -> 51978295 | G50: =MAX(0,(D50-E50)-(H50-I50)) -> 0 | H50: =ROUND(IF(HYPOTHESES!$C$43=0,0,'BALANCE 2024'!$H$50*HYPOTHESES!H$43/HYPOTHESES!$C$43),0) -> 51978295 | I50: 0 | J50: =(D50-E50)+(F50-G50)-(H50-I50) -> 0
A51: 605300 | B51: Autres énergies | C51: RE | D51: 0 | E51: 0 | F51: =MAX(0,(H51-I51)-(D51-E51)) -> 25804914 | G51: =MAX(0,(D51-E51)-(H51-I51)) -> 0 | H51: =ROUND(IF(HYPOTHESES!$C$43=0,0,'BALANCE 2024'!$H$51*HYPOTHESES!H$43/HYPOTHESES!$C$43),0) -> 25804914 | I51: 0 | J51: =(D51-E51)+(F51-G51)-(H51-I51) -> 0
A52: 605500 | B52: Fournitures de bureau non stockable | C52: RE | D52: 0 | E52: 0 | F52: =MAX(0,(H52-I52)-(D52-E52)) -> 16744874 | G52: =MAX(0,(D52-E52)-(H52-I52)) -> 0 | H52: =ROUND(IF(HYPOTHESES!$C$43=0,0,'BALANCE 2024'!$H$52*HYPOTHESES!H$43/HYPOTHESES!$C$43),0) -> 16744874 | I52: 0 | J52: =(D52-E52)+(F52-G52)-(H52-I52) -> 0
A53: 605600 | B53: Achats de petit matériel et outilla | C53: RE | D53: 0 | E53: 0 | F53: =MAX(0,(H53-I53)-(D53-E53)) -> 4801744 | G53: =MAX(0,(D53-E53)-(H53-I53)) -> 0 | H53: =ROUND(IF(HYPOTHESES!$C$43=0,0,'BALANCE 2024'!$H$53*HYPOTHESES!H$43/HYPOTHESES!$C$43),0) -> 4801744 | I53: 0 | J53: =(D53-E53)+(F53-G53)-(H53-I53) -> 0
A54: 605700 | B54: Achats d'études et prestations de s | C54: RE | D54: 0 | E54: 0 | F54: =MAX(0,(H54-I54)-(D54-E54)) -> 104265570 | G54: =MAX(0,(D54-E54)-(H54-I54)) -> 0 | H54: =ROUND(IF(HYPOTHESES!$C$43=0,0,'BALANCE 2024'!$H$54*HYPOTHESES!H$43/HYPOTHESES!$C$43),0) -> 104265570 | I54: 0 | J54: =(D54-E54)+(F54-G54)-(H54-I54) -> 0
A55: 605800 | B55: Achats de materiels et equiepents | C55: RE | D55: 0 | E55: 0 | F55: =MAX(0,(H55-I55)-(D55-E55)) -> 156398355 | G55: =MAX(0,(D55-E55)-(H55-I55)) -> 0 | H55: =ROUND(HYPOTHESES!H$43-(H48+H49+H50+H51+H52+H53+H54),0) -> 156398355 | I55: 0 | J55: =(D55-E55)+(F55-G55)-(H55-I55) -> 0
A56: 616000 | B56: Transports de plis | C56: RG | D56: 0 | E56: 0 | F56: =MAX(0,(H56-I56)-(D56-E56)) -> 121027 | G56: =MAX(0,(D56-E56)-(H56-I56)) -> 0 | H56: =ROUND(IF(HYPOTHESES!$C$44=0,0,'BALANCE 2024'!$H$56*HYPOTHESES!H$44/HYPOTHESES!$C$44),0) -> 121027 | I56: 0 | J56: =(D56-E56)+(F56-G56)-(H56-I56) -> 0
A57: 618200 | B57: Transports entre ‚tablissement ou c | C57: RG | D57: 0 | E57: 0 | F57: =MAX(0,(H57-I57)-(D57-E57)) -> 2019520 | G57: =MAX(0,(D57-E57)-(H57-I57)) -> 0 | H57: =ROUND(IF(HYPOTHESES!$C$44=0,0,'BALANCE 2024'!$H$57*HYPOTHESES!H$44/HYPOTHESES!$C$44),0) -> 2019520 | I57: 0 | J57: =(D57-E57)+(F57-G57)-(H57-I57) -> 0
A58: 618300 | B58: Transports administratifs | C58: RG | D58: 0 | E58: 0 | F58: =MAX(0,(H58-I58)-(D58-E58)) -> 2782900 | G58: =MAX(0,(D58-E58)-(H58-I58)) -> 0 | H58: =ROUND(HYPOTHESES!H$44-(H56+H57),0) -> 2782900 | I58: 0 | J58: =(D58-E58)+(F58-G58)-(H58-I58) -> 0
A59: 622200 | B59: Location de batiment | C59: RH | D59: 0 | E59: 0 | F59: =MAX(0,(H59-I59)-(D59-E59)) -> 21634910 | G59: =MAX(0,(D59-E59)-(H59-I59)) -> 0 | H59: =ROUND(IF(HYPOTHESES!$C$45=0,0,'BALANCE 2024'!$H$59*HYPOTHESES!H$45/HYPOTHESES!$C$45),0) -> 21634910 | I59: 0 | J59: =(D59-E59)+(F59-G59)-(H59-I59) -> 0
A60: 624200 | B60: Entretien et réparation des biens m | C60: RH | D60: 0 | E60: 0 | F60: =MAX(0,(H60-I60)-(D60-E60)) -> 44483630 | G60: =MAX(0,(D60-E60)-(H60-I60)) -> 0 | H60: =ROUND(HYPOTHESES!H$45-(H59+H61+H62+H63+H64+H65+H66+H67),0) -> 44483630 | I60: 0 | J60: =(D60-E60)+(F60-G60)-(H60-I60) -> 0
A61: 625800 | B61: Autres primes d'assurances | C61: RH | D61: 0 | E61: 0 | F61: =MAX(0,(H61-I61)-(D61-E61)) -> 5969111 | G61: =MAX(0,(D61-E61)-(H61-I61)) -> 0 | H61: =ROUND(IF(HYPOTHESES!$C$45=0,0,'BALANCE 2024'!$H$61*HYPOTHESES!H$45/HYPOTHESES!$C$45),0) -> 5969111 | I61: 0 | J61: =(D61-E61)+(F61-G61)-(H61-I61) -> 0
A62: 626600 | B62: Documentation techniques | C62: RH | D62: 0 | E62: 0 | F62: =MAX(0,(H62-I62)-(D62-E62)) -> 41618 | G62: =MAX(0,(D62-E62)-(H62-I62)) -> 0 | H62: =ROUND(IF(HYPOTHESES!$C$45=0,0,'BALANCE 2024'!$H$62*HYPOTHESES!H$45/HYPOTHESES!$C$45),0) -> 41618 | I62: 0 | J62: =(D62-E62)+(F62-G62)-(H62-I62) -> 0
A63: 627700 | B63: Frais de colloques, séminaires, con | C63: RH | D63: 0 | E63: 0 | F63: =MAX(0,(H63-I63)-(D63-E63)) -> 76083 | G63: =MAX(0,(D63-E63)-(H63-I63)) -> 0 | H63: =ROUND(IF(HYPOTHESES!$C$45=0,0,'BALANCE 2024'!$H$63*HYPOTHESES!H$45/HYPOTHESES!$C$45),0) -> 76083 | I63: 0 | J63: =(D63-E63)+(F63-G63)-(H63-I63) -> 0
A64: 628800 | B64: Autres frais de télécommunications | C64: RH | D64: 0 | E64: 0 | F64: =MAX(0,(H64-I64)-(D64-E64)) -> 1032701 | G64: =MAX(0,(D64-E64)-(H64-I64)) -> 0 | H64: =ROUND(IF(HYPOTHESES!$C$45=0,0,'BALANCE 2024'!$H$64*HYPOTHESES!H$45/HYPOTHESES!$C$45),0) -> 1032701 | I64: 0 | J64: =(D64-E64)+(F64-G64)-(H64-I64) -> 0
A65: 631800 | B65: Autres frais bancaires | C65: RH | D65: 0 | E65: 0 | F65: =MAX(0,(H65-I65)-(D65-E65)) -> 29379832 | G65: =MAX(0,(D65-E65)-(H65-I65)) -> 0 | H65: =ROUND(IF(HYPOTHESES!$C$45=0,0,'BALANCE 2024'!$H$65*HYPOTHESES!H$45/HYPOTHESES!$C$45),0) -> 29379832 | I65: 0 | J65: =(D65-E65)+(F65-G65)-(H65-I65) -> 0
A66: 632800 | B66: Divers frais | C66: RH | D66: 0 | E66: 0 | F66: =MAX(0,(H66-I66)-(D66-E66)) -> 6181607 | G66: =MAX(0,(D66-E66)-(H66-I66)) -> 0 | H66: =ROUND(IF(HYPOTHESES!$C$45=0,0,'BALANCE 2024'!$H$66*HYPOTHESES!H$45/HYPOTHESES!$C$45),0) -> 6181607 | I66: 0 | J66: =(D66-E66)+(F66-G66)-(H66-I66) -> 0
A67: 638800 | B67: Charges externes diverses | C67: RH | D67: 0 | E67: 0 | F67: =MAX(0,(H67-I67)-(D67-E67)) -> 30059956 | G67: =MAX(0,(D67-E67)-(H67-I67)) -> 0 | H67: =ROUND(IF(HYPOTHESES!$C$45=0,0,'BALANCE 2024'!$H$67*HYPOTHESES!H$45/HYPOTHESES!$C$45),0) -> 30059956 | I67: 0 | J67: =(D67-E67)+(F67-G67)-(H67-I67) -> 0
A68: 641100 | B68: Impot foncier | C68: RI | D68: 0 | E68: 0 | F68: =MAX(0,(H68-I68)-(D68-E68)) -> 467964 | G68: =MAX(0,(D68-E68)-(H68-I68)) -> 0 | H68: =ROUND(IF(HYPOTHESES!$C$46=0,0,'BALANCE 2024'!$H$68*HYPOTHESES!H$46/HYPOTHESES!$C$46),0) -> 467964 | I68: 0 | J68: =(D68-E68)+(F68-G68)-(H68-I68) -> 0
A69: 641201 | B69: Patente commerciale | C69: RI | D69: 0 | E69: 0 | F69: =MAX(0,(H69-I69)-(D69-E69)) -> 11770772 | G69: =MAX(0,(D69-E69)-(H69-I69)) -> 0 | H69: =ROUND(HYPOTHESES!H$46-(H68+H70+H71+H72+H73+H74+H75+H76),0) -> 11770772 | I69: 0 | J69: =(D69-E69)+(F69-G69)-(H69-I69) -> 0
A70: 641202 | B70: Patente transport | C70: RI | D70: 0 | E70: 0 | F70: =MAX(0,(H70-I70)-(D70-E70)) -> 2013149 | G70: =MAX(0,(D70-E70)-(H70-I70)) -> 0 | H70: =ROUND(IF(HYPOTHESES!$C$46=0,0,'BALANCE 2024'!$H$70*HYPOTHESES!H$46/HYPOTHESES!$C$46),0) -> 2013149 | I70: 0 | J70: =(D70-E70)+(F70-G70)-(H70-I70) -> 0
A71: 641300 | B71: Taxes sur appointements et salaires | C71: RI | D71: 0 | E71: 0 | F71: =MAX(0,(H71-I71)-(D71-E71)) -> 1074465 | G71: =MAX(0,(D71-E71)-(H71-I71)) -> 0 | H71: =ROUND(IF(HYPOTHESES!$C$46=0,0,'BALANCE 2024'!$H$71*HYPOTHESES!H$46/HYPOTHESES!$C$46),0) -> 1074465 | I71: 0 | J71: =(D71-E71)+(F71-G71)-(H71-I71) -> 0
A72: 641400 | B72: Taxes d'apprentissage | C72: RI | D72: 0 | E72: 0 | F72: =MAX(0,(H72-I72)-(D72-E72)) -> 135275 | G72: =MAX(0,(D72-E72)-(H72-I72)) -> 0 | H72: =ROUND(IF(HYPOTHESES!$C$46=0,0,'BALANCE 2024'!$H$72*HYPOTHESES!H$46/HYPOTHESES!$C$46),0) -> 135275 | I72: 0 | J72: =(D72-E72)+(F72-G72)-(H72-I72) -> 0
A73: 641500 | B73: Formation professionnelle continue | C73: RI | D73: 0 | E73: 0 | F73: =MAX(0,(H73-I73)-(D73-E73)) -> 405843 | G73: =MAX(0,(D73-E73)-(H73-I73)) -> 0 | H73: =ROUND(IF(HYPOTHESES!$C$46=0,0,'BALANCE 2024'!$H$73*HYPOTHESES!H$46/HYPOTHESES!$C$46),0) -> 405843 | I73: 0 | J73: =(D73-E73)+(F73-G73)-(H73-I73) -> 0
A74: 641830 | B74: Tse | C74: RI | D74: 0 | E74: 0 | F74: =MAX(0,(H74-I74)-(D74-E74)) -> 275169 | G74: =MAX(0,(D74-E74)-(H74-I74)) -> 0 | H74: =ROUND(IF(HYPOTHESES!$C$46=0,0,'BALANCE 2024'!$H$74*HYPOTHESES!H$46/HYPOTHESES!$C$46),0) -> 275169 | I74: 0 | J74: =(D74-E74)+(F74-G74)-(H74-I74) -> 0
A75: 646200 | B75: Droits de timbre | C75: RI | D75: 0 | E75: 0 | F75: =MAX(0,(H75-I75)-(D75-E75)) -> 2243169 | G75: =MAX(0,(D75-E75)-(H75-I75)) -> 0 | H75: =ROUND(IF(HYPOTHESES!$C$46=0,0,'BALANCE 2024'!$H$75*HYPOTHESES!H$46/HYPOTHESES!$C$46),0) -> 2243169 | I75: 0 | J75: =(D75-E75)+(F75-G75)-(H75-I75) -> 0
A76: 648000 | B76: Autres impots et taxes | C76: RI | D76: 0 | E76: 0 | F76: =MAX(0,(H76-I76)-(D76-E76)) -> 943283 | G76: =MAX(0,(D76-E76)-(H76-I76)) -> 0 | H76: =ROUND(IF(HYPOTHESES!$C$46=0,0,'BALANCE 2024'!$H$76*HYPOTHESES!H$46/HYPOTHESES!$C$46),0) -> 943283 | I76: 0 | J76: =(D76-E76)+(F76-G76)-(H76-I76) -> 0
A77: 658800 | B77: Autres charges diverses | C77: RJ | D77: 0 | E77: 0 | F77: =MAX(0,(H77-I77)-(D77-E77)) -> 1732324 | G77: =MAX(0,(D77-E77)-(H77-I77)) -> 0 | H77: =ROUND(HYPOTHESES!H$47,0) -> 1732324 | I77: 0 | J77: =(D77-E77)+(F77-G77)-(H77-I77) -> 0
A78: 661100 | B78: Appointements salaires national | C78: RK | D78: 0 | E78: 0 | F78: =MAX(0,(H78-I78)-(D78-E78)) -> 76686151 | G78: =MAX(0,(D78-E78)-(H78-I78)) -> 0 | H78: =ROUND(HYPOTHESES!H$48-(H79+H80+H81+H82+H83),0) -> 76686151 | I78: 0 | J78: =(D78-E78)+(F78-G78)-(H78-I78) -> 0
A79: 661200 | B79: Primes et gratifications | C79: RK | D79: 0 | E79: 0 | F79: =MAX(0,(H79-I79)-(D79-E79)) -> 25923790 | G79: =MAX(0,(D79-E79)-(H79-I79)) -> 0 | H79: =ROUND(IF(HYPOTHESES!$C$48=0,0,'BALANCE 2024'!$H$79*HYPOTHESES!H$48/HYPOTHESES!$C$48),0) -> 25923790 | I79: 0 | J79: =(D79-E79)+(F79-G79)-(H79-I79) -> 0
A80: 661300 | B80: Congés payés | C80: RK | D80: 0 | E80: 0 | F80: =MAX(0,(H80-I80)-(D80-E80)) -> 8553600 | G80: =MAX(0,(D80-E80)-(H80-I80)) -> 0 | H80: =ROUND(IF(HYPOTHESES!$C$48=0,0,'BALANCE 2024'!$H$80*HYPOTHESES!H$48/HYPOTHESES!$C$48),0) -> 8553600 | I80: 0 | J80: =(D80-E80)+(F80-G80)-(H80-I80) -> 0
A81: 661400 | B81: Indem.preavis&licenc imposables | C81: RK | D81: 0 | E81: 0 | F81: =MAX(0,(H81-I81)-(D81-E81)) -> 8638032 | G81: =MAX(0,(D81-E81)-(H81-I81)) -> 0 | H81: =ROUND(IF(HYPOTHESES!$C$48=0,0,'BALANCE 2024'!$H$81*HYPOTHESES!H$48/HYPOTHESES!$C$48),0) -> 8638032 | I81: 0 | J81: =(D81-E81)+(F81-G81)-(H81-I81) -> 0
A82: 663400 | B82: Indemnités de transport | C82: RK | D82: 0 | E82: 0 | F82: =MAX(0,(H82-I82)-(D82-E82)) -> 8946552 | G82: =MAX(0,(D82-E82)-(H82-I82)) -> 0 | H82: =ROUND(IF(HYPOTHESES!$C$48=0,0,'BALANCE 2024'!$H$82*HYPOTHESES!H$48/HYPOTHESES!$C$48),0) -> 8946552 | I82: 0 | J82: =(D82-E82)+(F82-G82)-(H82-I82) -> 0
A83: 664104 | B83: Charges socialescr employeur | C83: RK | D83: 0 | E83: 0 | F83: =MAX(0,(H83-I83)-(D83-E83)) -> 9108398 | G83: =MAX(0,(D83-E83)-(H83-I83)) -> 0 | H83: =ROUND(IF(HYPOTHESES!$C$48=0,0,'BALANCE 2024'!$H$83*HYPOTHESES!H$48/HYPOTHESES!$C$48),0) -> 9108398 | I83: 0 | J83: =(D83-E83)+(F83-G83)-(H83-I83) -> 0
A84: 671201 | B84: Interet des emprunts ecobank | C84: RM | D84: 0 | E84: 0 | F84: =MAX(0,(H84-I84)-(D84-E84)) -> 0 | G84: =MAX(0,(D84-E84)-(H84-I84)) -> 0 | H84: =ROUND('INVEST ET FINANCEMENT'!H$64,0) -> 0 | I84: 0 | J84: =(D84-E84)+(F84-G84)-(H84-I84) -> 0
A85: 672301 | B85: Interet de credit bail bni -1 | C85: RM | D85: 0 | E85: 0 | F85: =MAX(0,(H85-I85)-(D85-E85)) -> 0 | G85: =MAX(0,(D85-E85)-(H85-I85)) -> 0 | H85: =ROUND('INVEST ET FINANCEMENT'!H$65,0) -> 0 | I85: 0 | J85: =(D85-E85)+(F85-G85)-(H85-I85) -> 0
A86: 681301 | B86: Dotations aux amortissements : aménagements | C86: RL | D86: 0 | E86: 0 | F86: =MAX(0,(H86-I86)-(D86-E86)) -> 0 | G86: =MAX(0,(D86-E86)-(H86-I86)) -> 0 | H86: =ROUND('INVEST ET FINANCEMENT'!H$31,0) -> 0 | I86: 0 | J86: =(D86-E86)+(F86-G86)-(H86-I86) -> 0
A87: 681302 | B87: Dotations aux amortissements : matériel et outillage | C87: RL | D87: 0 | E87: 0 | F87: =MAX(0,(H87-I87)-(D87-E87)) -> 68854932 | G87: =MAX(0,(D87-E87)-(H87-I87)) -> 0 | H87: =ROUND('INVEST ET FINANCEMENT'!H$34,0) -> 68854932 | I87: 0 | J87: =(D87-E87)+(F87-G87)-(H87-I87) -> 0
A88: 681303 | B88: Dotations aux amortissements : bureau et informatique | C88: RL | D88: 0 | E88: 0 | F88: =MAX(0,(H88-I88)-(D88-E88)) -> 5000000 | G88: =MAX(0,(D88-E88)-(H88-I88)) -> 0 | H88: =ROUND('INVEST ET FINANCEMENT'!H$37,0) -> 5000000 | I88: 0 | J88: =(D88-E88)+(F88-G88)-(H88-I88) -> 0
A89: 681304 | B89: Dotations aux amortissements : transport | C89: RL | D89: 0 | E89: 0 | F89: =MAX(0,(H89-I89)-(D89-E89)) -> 24093971 | G89: =MAX(0,(D89-E89)-(H89-I89)) -> 0 | H89: =ROUND('INVEST ET FINANCEMENT'!H$40,0) -> 24093971 | I89: 0 | J89: =(D89-E89)+(F89-G89)-(H89-I89) -> 0
A90: 691100 | B90: Dotations aux provisions pour risques et charges | C90: RL | D90: 0 | E90: 0 | F90: =MAX(0,(H90-I90)-(D90-E90)) -> 6059296 | G90: =MAX(0,(D90-E90)-(H90-I90)) -> 0 | H90: =ROUND(HYPOTHESES!H$50,0) -> 6059296 | I90: 0 | J90: =(D90-E90)+(F90-G90)-(H90-I90) -> 0
A91: 705100 | B91: Travaux facturés | C91: TC | D91: 0 | E91: 0 | F91: =MAX(0,(H91-I91)-(D91-E91)) -> 0 | G91: =MAX(0,(D91-E91)-(H91-I91)) -> 911749493 | H91: 0 | I91: =ROUND(HYPOTHESES!H$42,0) -> 911749493 | J91: =(D91-E91)+(F91-G91)-(H91-I91) -> 0
A92: 771200 | B92: Intérêts des prêts | C92: TK | D92: 0 | E92: 0 | F92: =MAX(0,(H92-I92)-(D92-E92)) -> 0 | G92: =MAX(0,(D92-E92)-(H92-I92)) -> 848594 | H92: 0 | I92: =ROUND(HYPOTHESES!H$51,0) -> 848594 | J92: =(D92-E92)+(F92-G92)-(H92-I92) -> 0
